Workbook
Name TOTALDU: #REF!

Sheet Index
C4: Upstate House, LLC
C5: 46113
C8: CONTENTS | D8: Description
C9: Assumptions
C10: Unit Mix
C11: Sources and Uses
C12: Mortgage
C13: Construction Interest
C14: Operating Expenses & Reserves
C15: Taxcredit Analysis
C16: Budget
C17: Development Cash flow
C18: Rental Cash flow
C19: Debt Schedule
C20: KPI's
C22: COLOR CODING | D22: TEXT COLOR
C23: Inputs/assumptions | D23: BLUE | E23: Inputs, or any hard-coded data, such as historical values, assumptions, and drivers.
C24: Formulas/results | D24: BLACK | E24: Formulas, calculations, or references deriving from inputs
C25: Regulatory Requirements | D25: GREEN | E25: Requirement as per NCF, HPD or IRS.
C26: Market Rates | D26: ORANGE | E26: Requirement as per latest target Market standards

Sheet Assumptions
B2: Assumptions
B4: All input cells are in Yellow
B6: Project Timeline
B8: Model start date | C8: 46204
B9: No. of months (Pre Development phase) | C9: 6 | D9: months
B10: Development start date | C10: =EOMONTH(C8,C9) -> 46418
B11: No. of months (Development phase) | C11: 24 | D11: months
B12: Rent up an conversion | C12: 6 | D12: months
B13: Rent start Date (Post construction phase) | C13: =EOMONTH(C10,(C11+C12)) -> 47330
B14: No. of months | C14: =30*12 -> 360 | D14: months
B15: Exit date | C15: =EOMONTH(C13,C14) -> 58287
B16: Total Holding Period | C16: =ROUND((C15-C8)/365.25,0) -> 33 | D16: years
B19: Checklist
B20: Maximum average AMI | C20: =(D34*B34)+(D35*B35)+(B36*D36)+(B37*D37)+(B38*D38) -> 0.575 | D20: =IF(C20<=60%,"OK","check") -> OK
B21: Distributed and Allocated Units | C21: =IF(C39='Unit Mix'!H82,"EQUAL","UNEQUAL") -> EQUAL | D21: =IF(C21="EQUAL","OK","check") -> OK
B23: Design
B24: 63 | C24: Studio | D24: =B24/$B$28 -> 0.19207317 | E24: Max 25% Studio
B25: 58 | C25: 1 Bedroom | D25: =B25/$B$28 -> 0.17682927 | E25: Min 15% 1BR
B26: 128 | C26: 2 Bedroom | D26: =B26/$B$28 -> 0.3902439 | E26: Min 30% 2BR+
B27: 79 | C27: 3 Bedroom | D27: =B27/$B$28 -> 0.24085366
B28: =SUM(B24:B27) -> 328 | D28: =B28/$B$28 -> 1
B29: 1 | C29: Super's Unit
B30: =SUM(B28:B29) -> 329
B32: Distribution by AMI
B33: AMI Tier | C33: Units | D33: %
B34: 0.3 | C34: =ROUND($B$28*D34,0) -> 49 | D34: 0.15 | E34: 15-30% as per NCF
B35: 0.4 | C35: =ROUND($B$28*D35,0) -> 82 | D35: 0.25
B36: 0.6 | C36: =ROUND($B$28*D36,0) -> 82 | D36: 0.25
B37: 0.8 | C37: =B28-SUM(C34:C36) -> 115 | D37: 0.35
B38: 0 | C38: =$B$28*D38 -> 0 | D38: =0 -> 0 | E38: Max. 4 tiers as per NCF
B39: Total | C39: =SUM(C34:C38) -> 328 | D39: =SUM(D34:D38) -> 1
B42: Gross Sqare foot Distribution
B43: Residential GSF | C43: 305300
B44: Commercial GSF | C44: 0
B45: Community GSF | C45: 18000
B46: Parking GSF | C46: 0
B47: Total GSF | C47: =SUM(C43:C46) -> 323300
B49: Price PSF (Target Location)
B50: Residential Price per square foot | C50: 540
B51: Non-Residential Price per square foot | C51: 350
B53: COMMERICAL AND ANCILLARY INCOME
C54: # of Spaces | D54: Monthly Rent | E54: Annual Income
B55: Parking | C55: 75 | D55: 50 | E55: =C55*D55*12 -> 45000
B56: Commercial | C56: 0 | D56: 30 | E56: =D56*C56 -> 0
B57: Community Facility | C57: =C45 -> 18000 | D57: 0 | E57: =D57*C57 -> 0
B58: Laundry | C58: =B30 -> 329 | D58: 120 | E58: =D58*C58 -> 39480
B60: Developer Fee Draw Schedule
C61: % | D61: $
B62: Total Developer Fee | C62: =SUM(C63:C65) -> 1 | D62: =References!C26 -> 8780000 | E62: 4% of TDC
B63: At Construction Loan Closing | C63: 0 | D63: =D62*C63 -> 0 | E63: Max 25% as per NCF
B64: During Construction | C64: 0.1 | D64: =D62*C64 -> 878000 | E64: Max 25% as per NCF
B65: Post Construction | C65: =100%-SUM(C63:C64) -> 0.9 | D65: =D62*C65 -> 7902000 | E65: =12*15 -> 180
B69: Development Costs
B70: Residential Price per square foot | C70: =Assumptions!C50 -> 540
B71: Non-Residential Price per square foot | C71: =Assumptions!C51 -> 350
C73: Development Cost | E73: LIHTC Eligibility | F73: LIHTC Eligible Cost
B74: Acquisition Costs
B75: Building Acquisition | C75: 0 | E75: No | F75: =IF(E75="Yes",C75,0) -> 0
B76: Land Acquisition | C76: 1 | E76: Yes | F76: =IF(E76="Yes",C76,0) -> 1
B77: Total Acquisition Costs | C77: =SUM(C75:C76) -> 1 | F77: =SUM(F75:F76) -> 1
B79: Construction Costs
B80: Contractor Price
B81: Residential | C81: =Assumptions!$C$70*'Unit Mix'!D88 -> 164862000 | E81: Yes | F81: =IF(E81="Yes",C81,0) -> 164862000
B82: Commercial Space | C82: =Assumptions!$C$71*'Unit Mix'!D89 -> 0 | E82: No | F82: =IF(E82="Yes",C82,0) -> 0
B83: Community Space | C83: =Assumptions!$C$71*'Unit Mix'!D90 -> 6300000 | E83: Yes | F83: =IF(E83="Yes",C83,0) -> 6300000
B84: Parking | C84: =Assumptions!$C$71*'Unit Mix'!D91 -> 0 | E84: No | F84: =IF(E84="Yes",C84,0) -> 0
B85: Developer Fee | C85: =D64 -> 878000 | E85: Yes | F85: =IF(E85="Yes",C85,0) -> 878000
B86: Contingent Hard Costs | D86: HFA Standards
B87: General Conditions | C87: =D87*($C$81+$C$82+$C$83+$C$84) -> 10269720 | D87: 0.06 | E87: Yes | F87: =IF(E87="Yes",C87,0) -> 10269720
B88: Overhead | C88: =D88*($C$81+$C$82+$C$83+$C$84) -> 3423240 | D88: 0.02 | E88: Yes | F88: =IF(E88="Yes",C88,0) -> 3423240
B89: Contractor Profit | C89: =D89*($C$81+$C$82+$C$83+$C$84) -> 10269720 | D89: 0.06 | E89: Yes | F89: =IF(E89="Yes",C89,0) -> 10269720
B90: Bond Premium | C90: =D90*($C$81+$C$82+$C$83+$C$84) -> 1711620 | D90: 0.01 | E90: Yes | F90: =IF(E90="Yes",C90,0) -> 1711620
B91: Contingency | C91: =D91*($C$81+$C$82+$C$83+$C$84) -> 8558100 | D91: 0.05 | E91: Yes | F91: =IF(E91="Yes",C91,0) -> 8558100
B92: Total Hard Cost | C92: =SUM(C81:C91) -> 206272400 | F92: =SUM(F81:F91) -> 206272400
B94: Soft Costs
B95: Accounting & Cost Certification | C95: 30000 | E95: Yes | F95: =IF(E95="Yes",C95,0) -> 30000
B96: Appraisal | C96: 10000 | E96: Yes | F96: =IF(E96="Yes",C96,0) -> 10000
B97: Architect / Engineer | C97: 2400000 | E97: Yes | F97: =IF(E97="Yes",C97,0) -> 2400000
B98: Permits and Expediting | C98: 95000 | E98: Yes | F98: =IF(E98="Yes",C98,0) -> 95000
B99: Environmental Phase I & II | C99: 35000 | E99: Yes | F99: =IF(E99="Yes",C99,0) -> 35000
B100: Geotechnical | C100: 0 | E100: Yes | F100: =IF(E100="Yes",C100,0) -> 0
B101: Insurance | C101: 1000000 | E101: Yes | F101: =IF(E101="Yes",C101,0) -> 1000000
B102: Market Study | C102: 7500 | E102: Yes | F102: =IF(E102="Yes",C102,0) -> 7500
B103: Marketing | C103: 329000 | E103: No | F103: =IF(E103="Yes",C103,0) -> 0
B104: Permits / Fees | C104: 75000 | E104: Yes | F104: =IF(E104="Yes",C104,0) -> 75000
B105: Survey | C105: 7500 | E105: Yes | F105: =IF(E105="Yes",C105,0) -> 7500
B106: Borings | C106: 125000 | E106: Yes | F106: =IF(E106="Yes",C106,0) -> 125000
B107: Title & Recording | C107: 866708.32 | E107: Yes | F107: =IF(E107="Yes",C107,0) -> 866708.32
B108: Developer Fee | C108: =D63 -> 0 | E108: Yes | F108: =IF(E108="Yes",C108,0) -> 0
B109: Soft Cost Contingency | C109: 1885875.5 | D109: 5% of soft cost | E109: Yes | F109: =IF(E109="Yes",C109,0) -> 1885875.5
B110: Sub total | C110: =SUM(C95:C109) -> 6866583.8 | F110: =SUM(F95:F109) -> 6537583.8
B112: Legal Fees and Syndication Costs
B113: Borrower Legal | C113: 375000 | E113: Yes | F113: =IF(E113="Yes",C113,0) -> 375000
B114: Bank Legal | C114: 40000 | E114: Yes | F114: =IF(E114="Yes",C114,0) -> 40000
B115: Tax Credit Certification | C115: 421496 | E115: No | F115: =IF(E115="Yes",C115,0) -> 0
B116: Sub total | C116: =SUM(C113:C115) -> 836496 | F116: =SUM(F113:F115) -> 415000
B118: Total soft costs | C118: =C116+C110 -> 7703079.8 | E118: Yes
B120: Finance Cost
B122: Construction Lender Fees & Interest
B123: Construction Interest: Bonds | C123: =SUM('Construction Interest'!G38:G39) -> 20076858 | E123: Yes | F123: =IF(E123="Yes",C123,0) -> 20076858
...

Sheet Unit Mix
B3: Design | F3: Total units | G3: =C19 -> 328
B4: =Assumptions!B24 -> 63 | C4: Studio | D4: =B4/SUM($B$4:$B$7) -> 0.19207317
B5: =Assumptions!B25 -> 58 | C5: 1 Bedroom | D5: =B5/SUM($B$4:$B$7) -> 0.17682927
B6: =Assumptions!B26 -> 128 | C6: 2 Bedroom | D6: =B6/SUM($B$4:$B$7) -> 0.3902439
B7: =Assumptions!B27 -> 79 | C7: 3 Bedroom | D7: =B7/SUM($B$4:$B$7) -> 0.24085366
B8: =SUM(B4:B7) -> 328 | D8: =B8/SUM($B$4:$B$7) -> 1
B9: =Assumptions!B29 -> 1 | C9: Super Unit
B10: =SUM(B8:B9) -> 329
B12: Summary
B13: AMI Tier | C13: Units | D13: %
B14: =Assumptions!B34 -> 0.3 | C14: =Assumptions!C34 -> 49 | D14: =Assumptions!D34 -> 0.15
B15: =Assumptions!B35 -> 0.4 | C15: =Assumptions!C35 -> 82 | D15: =Assumptions!D35 -> 0.25
B16: =Assumptions!B36 -> 0.6 | C16: =Assumptions!C36 -> 82 | D16: =Assumptions!D36 -> 0.25
B17: =Assumptions!B37 -> 0.8 | C17: =Assumptions!C37 -> 115 | D17: =Assumptions!D37 -> 0.35
B18: =Assumptions!B38 -> 0 | C18: =Assumptions!C38 -> 0 | D18: =Assumptions!D38 -> 0
B19: Total | C19: =SUM(C14:C18) -> 328 | D19: =SUM(D14:D18) -> 1
B21: Unit size | C21: Net Square Footage
C22: Min | D22: Max
B23: Studio | C23: 350 | D23: 400 | E23: sqft
B24: 1 Bedroom | C24: 500 | D24: 550 | E24: sqft
B25: 2 Bedroom | C25: 650 | D25: 725 | E25: sqft
B26: 3 Bedroom | C26: 850 | D26: 950 | E26: sqft
B27: 4 Bedroom | C27: 950 | D27: 1075 | E27: sqft
B30: UNIT DISTRIBUTION
C31: Number of units | D31: Number of Rooms per unit | E31: Total rooms | F31: Avg NSF/Unit
B32: Studio | C32: =B4 -> 63 | D32: 2 | E32: =C32*D32 -> 126 | F32: =AVERAGE(C23,D23) -> 375
B33: 1 Bedroom | C33: =B5 -> 58 | D33: 3 | E33: =C33*D33 -> 174 | F33: =AVERAGE(C24,D24) -> 525
B34: 2 Bedroom | C34: =B6 -> 128 | D34: 4 | E34: =C34*D34 -> 512 | F34: =AVERAGE(C25,D25) -> 687.5
B35: 3 Bedroom | C35: =B7 -> 79 | D35: 5 | E35: =C35*D35 -> 395 | F35: =AVERAGE(C26,D26) -> 900
B36: 4 Bedroom | C36: 0 | D36: 0 | E36: =C36*D36 -> 0
B37: Subtotal | C37: =SUM(C32:C36) -> 328 | E37: =SUM(E32:E36) -> 1207 | F37: =SUM(F32:F36) -> 2487.5
B38: Super's Unit | C38: 1 | E38: 0
B39: Total | C39: =C37+C38 -> 329 | E39: =SUM(E37:E38) -> 1207 | F39: =C32*F32+C33*F33+C34*F34+C35*F35+C38*F38 -> 213175
B41: Unit Allocation Matrix
C42: {=TRANSPOSE(B14:B18)} -> 0.3 | D42: 0.4 | E42: 0.6 | F42: 0.8 | G42: 0
B43: =B23 -> Studio | C43: =Assumptions!$C$34*Assumptions!$D24 -> 9.4115854 | D43: =Assumptions!$C$35*Assumptions!$D24 -> 15.75 | E43: =Assumptions!$C$36*Assumptions!$D24 -> 15.75 | F43: =B4-SUM(C43+D43+E43) -> 22.088415 | G43: =Assumptions!$B$38*Assumptions!$D24 -> 0
B44: =B24 -> 1 Bedroom | C44: =Assumptions!$C$34*Assumptions!$D25 -> 8.6646341 | D44: =Assumptions!$C$35*Assumptions!$D25 -> 14.5 | E44: =Assumptions!$C$36*Assumptions!$D25 -> 14.5 | F44: =B5-SUM(C44+D44+E44) -> 20.335366 | G44: =Assumptions!$B$38*Assumptions!$D25 -> 0
B45: =B25 -> 2 Bedroom | C45: =Assumptions!$C$34*Assumptions!$D26 -> 19.121951 | D45: =Assumptions!$C$35*Assumptions!$D26 -> 32 | E45: =Assumptions!$C$36*Assumptions!$D26 -> 32 | F45: =B6-SUM(C45+D45+E45) -> 44.878049 | G45: =Assumptions!$B$38*Assumptions!$D26 -> 0
B46: =B26 -> 3 Bedroom | C46: =Assumptions!$C$34*Assumptions!$D27 -> 11.801829 | D46: =Assumptions!$C$35*Assumptions!$D27 -> 19.75 | E46: =Assumptions!$C$36*Assumptions!$D27 -> 19.75 | F46: =B7-SUM(C46+D46+E46) -> 27.698171 | G46: =Assumptions!$B$38*Assumptions!$D27 -> 0
B47: =B27 -> 4 Bedroom | C47: =Assumptions!C38*Assumptions!D24 -> 0 | D47: =Assumptions!$C$38*Assumptions!D25 -> 0 | E47: =Assumptions!$C$38*Assumptions!D26 -> 0 | F47: =Assumptions!$C$38*Assumptions!D27 -> 0 | G47: =Assumptions!$B$38*Assumptions!$D28 -> 0
B50: RESIDENTIAL INCOME UPON OCCUPANCY
B51: Unit size | C51: Rooms | D51: Income Level (AMI) | E51: Number of Units | F51: LIHTC Rents | G51: Utility Allowance | H51: Max Net Monthly Rent | I51: Annual Rent
B52: Studio | C52: =_xlfn.XLOOKUP(B52,$B$32:$B$36,$D$32:$D$36) -> 2 | D52: =$B$14 -> 0.3 | E52: =INDEX($C$43:$C$47,MATCH(B52,$B$43:$B$47,0)) -> 9.4115854 | F52: 850 | G52: 35 | H52: =F52-G52 -> 815 | I52: =H52*E52*12 -> 92045.305
B53: 1 Bedroom | C53: =_xlfn.XLOOKUP(B53,$B$32:$B$36,$D$32:$D$36) -> 3 | D53: =$B$14 -> 0.3 | E53: =INDEX($C$43:$C$47,MATCH(B53,$B$43:$B$47,0)) -> 8.6646341 | F53: 911 | G53: 41 | H53: =F53-G53 -> 870 | I53: =H53*E53*12 -> 90458.78
B54: 2 Bedroom | C54: =_xlfn.XLOOKUP(B54,$B$32:$B$36,$D$32:$D$36) -> 4 | D54: =$B$14 -> 0.3 | E54: =INDEX($C$43:$C$47,MATCH(B54,$B$43:$B$47,0)) -> 19.121951 | F54: 1093 | G54: 58 | H54: =F54-G54 -> 1035 | I54: =H54*E54*12 -> 237494.63
B55: 3 Bedroom | C55: =_xlfn.XLOOKUP(B55,$B$32:$B$36,$D$32:$D$36) -> 5 | D55: =$B$14 -> 0.3 | E55: =INDEX($C$43:$C$47,MATCH(B55,$B$43:$B$47,0)) -> 11.801829 | F55: 1263 | G55: 75 | H55: =F55-G55 -> 1188 | I55: =H55*E55*12 -> 168246.88
B56: 4 Bedroom | C56: =_xlfn.XLOOKUP(B56,$B$32:$B$36,$D$32:$D$36) -> 0 | D56: =$B$14 -> 0.3 | E56: =INDEX($C$43:$C$47,MATCH(B56,$B$43:$B$47,0)) -> 0 | F56: 0 | G56: 0 | H56: =F56-G56 -> 0 | I56: =H56*E56*12 -> 0
B57: =E57/$H$82 -> 0.14939024 | D57: Sub-Total | E57: =SUM(E52:E56) -> 49
B58: Studio | C58: =_xlfn.XLOOKUP(B58,$B$32:$B$36,$D$32:$D$36) -> 2 | D58: =$B$15 -> 0.4 | E58: =INDEX($D$43:$D$47,MATCH(B58,$B$43:$B$47,0)) -> 15.75 | F58: 1134 | G58: 35 | H58: =F58-G58 -> 1099 | I58: =H58*E58*12 -> 207711
B59: 1 Bedroom | C59: =_xlfn.XLOOKUP(B59,$B$32:$B$36,$D$32:$D$36) -> 3 | D59: =$B$15 -> 0.4 | E59: =INDEX($D$43:$D$47,MATCH(B59,$B$43:$B$47,0)) -> 14.5 | F59: 1215 | G59: 41 | H59: =F59-G59 -> 1174 | I59: =H59*E59*12 -> 204276
B60: 2 Bedroom | C60: =_xlfn.XLOOKUP(B60,$B$32:$B$36,$D$32:$D$36) -> 4 | D60: =$B$15 -> 0.4 | E60: =INDEX($D$43:$D$47,MATCH(B60,$B$43:$B$47,0)) -> 32 | F60: 1458 | G60: 58 | H60: =F60-G60 -> 1400 | I60: =H60*E60*12 -> 537600
B61: 3 Bedroom | C61: =_xlfn.XLOOKUP(B61,$B$32:$B$36,$D$32:$D$36) -> 5 | D61: =$B$15 -> 0.4 | E61: =INDEX($D$43:$D$47,MATCH(B61,$B$43:$B$47,0)) -> 19.75 | F61: 1685 | G61: 75 | H61: =F61-G61 -> 1610 | I61: =H61*E61*12 -> 381570
B62: 4 Bedroom | C62: =_xlfn.XLOOKUP(B62,$B$32:$B$36,$D$32:$D$36) -> 0 | D62: =$B$15 -> 0.4 | E62: =INDEX($D$43:$D$47,MATCH(B62,$B$43:$B$47,0)) -> 0 | F62: 0 | G62: 0 | H62: =F62-G62 -> 0 | I62: =H62*E62*12 -> 0
B63: =E63/$H$82 -> 0.25 | D63: Sub-Total | E63: =SUM(E58:E62) -> 82
B64: Studio | C64: =_xlfn.XLOOKUP(B64,$B$32:$B$36,$D$32:$D$36) -> 2 | D64: =$B$16 -> 0.6 | E64: =INDEX($E$43:$E$47,MATCH(B64,$B$43:$B$47,0)) -> 15.75 | F64: 1701 | G64: 35 | H64: =F64-G64 -> 1666 | I64: =H64*E64*12 -> 314874
B65: 1 Bedroom | C65: =_xlfn.XLOOKUP(B65,$B$32:$B$36,$D$32:$D$36) -> 3 | D65: =$B$16 -> 0.6 | E65: =INDEX($E$43:$E$47,MATCH(B65,$B$43:$B$47,0)) -> 14.5 | F65: 1822 | G65: 41 | H65: =F65-G65 -> 1781 | I65: =H65*E65*12 -> 309894
B66: 2 Bedroom | C66: =_xlfn.XLOOKUP(B66,$B$32:$B$36,$D$32:$D$36) -> 4 | D66: =$B$16 -> 0.6 | E66: =INDEX($E$43:$E$47,MATCH(B66,$B$43:$B$47,0)) -> 32 | F66: 2187 | G66: 58 | H66: =F66-G66 -> 2129 | I66: =H66*E66*12 -> 817536
B67: 3 Bedroom | C67: =_xlfn.XLOOKUP(B67,$B$32:$B$36,$D$32:$D$36) -> 5 | D67: =$B$16 -> 0.6 | E67: =INDEX($E$43:$E$47,MATCH(B67,$B$43:$B$47,0)) -> 19.75 | F67: 2527 | G67: 75 | H67: =F67-G67 -> 2452 | I67: =H67*E67*12 -> 581124
B68: 4 Bedroom | C68: =_xlfn.XLOOKUP(B68,$B$32:$B$36,$D$32:$D$36) -> 0 | D68: =$B$16 -> 0.6 | E68: =INDEX($E$43:$E$47,MATCH(B68,$B$43:$B$47,0)) -> 0 | F68: 0 | G68: 0 | H68: =F68-G68 -> 0 | I68: =H68*E68*12 -> 0
B69: =E69/$H$82 -> 0.25 | D69: Sub-Total | E69: =SUM(E64:E68) -> 82
B70: Studio | C70: =_xlfn.XLOOKUP(B70,$B$32:$B$36,$D$32:$D$36) -> 2 | D70: =$B$17 -> 0.8 | E70: =INDEX($F$43:$F$47,MATCH(B70,$B$43:$B$47,0)) -> 22.088415 | F70: 2268 | G70: =G64 -> 35 | H70: =F70-G70 -> 2233 | I70: =H70*E70*12 -> 591881.16
B71: 1 Bedroom | C71: =_xlfn.XLOOKUP(B71,$B$32:$B$36,$D$32:$D$36) -> 3 | D71: =$B$17 -> 0.8 | E71: =INDEX($F$43:$F$47,MATCH(B71,$B$43:$B$47,0)) -> 20.335366 | F71: 2430 | G71: =G65 -> 41 | H71: =F71-G71 -> 2389 | I71: =H71*E71*12 -> 582974.27
B72: 2 Bedroom | C72: =_xlfn.XLOOKUP(B72,$B$32:$B$36,$D$32:$D$36) -> 4 | D72: =$B$17 -> 0.8 | E72: =INDEX($F$43:$F$47,MATCH(B72,$B$43:$B$47,0)) -> 44.878049 | F72: 2916 | G72: =G66 -> 58 | H72: =F72-G72 -> 2858 | I72: =H72*E72*12 -> 1539137.6
B73: 3 Bedroom | C73: =_xlfn.XLOOKUP(B73,$B$32:$B$36,$D$32:$D$36) -> 5 | D73: =$B$17 -> 0.8 | E73: =INDEX($F$43:$F$47,MATCH(B73,$B$43:$B$47,0)) -> 27.698171 | F73: 3370 | G73: =G67 -> 75 | H73: =F73-G73 -> 3295 | I73: =H73*E73*12 -> 1095185.7
B74: 4 Bedroom | C74: =_xlfn.XLOOKUP(B74,$B$32:$B$36,$D$32:$D$36) -> 0 | D74: =$B$17 -> 0.8 | E74: =INDEX($F$43:$F$47,MATCH(B74,$B$43:$B$47,0)) -> 0 | F74: 0 | G74: 0 | H74: =F74-G74 -> 0 | I74: =H74*E74*12 -> 0
B75: =E75/$H$82 -> 0.35060976 | D75: Sub-Total | E75: =SUM(E70:E74) -> 115
B76: Studio | C76: =_xlfn.XLOOKUP(B76,$B$32:$B$36,$D$32:$D$36) -> 2 | D76: =$B$18 -> 0 | E76: =INDEX($G$43:$G$47,MATCH(B76,$B$43:$B$47,0)) -> 0 | H76: =F76-G76 -> 0 | I76: =H76*E76*12 -> 0
B77: 1 Bedroom | C77: =_xlfn.XLOOKUP(B77,$B$32:$B$36,$D$32:$D$36) -> 3 | D77: =$B$18 -> 0 | E77: =INDEX($G$43:$G$47,MATCH(B77,$B$43:$B$47,0)) -> 0 | H77: =F77-G77 -> 0 | I77: =H77*E77*12 -> 0
B78: 2 Bedroom | C78: =_xlfn.XLOOKUP(B78,$B$32:$B$36,$D$32:$D$36) -> 4 | D78: =$B$18 -> 0 | E78: =INDEX($G$43:$G$47,MATCH(B78,$B$43:$B$47,0)) -> 0 | H78: =F78-G78 -> 0 | I78: =H78*E78*12 -> 0
B79: 3 Bedroom | C79: =_xlfn.XLOOKUP(B79,$B$32:$B$36,$D$32:$D$36) -> 5 | D79: =$B$18 -> 0 | E79: =INDEX($G$43:$G$47,MATCH(B79,$B$43:$B$47,0)) -> 0 | H79: =F79-G79 -> 0 | I79: =H79*E79*12 -> 0
B80: 4 Bedroom | C80: =_xlfn.XLOOKUP(B80,$B$32:$B$36,$D$32:$D$36) -> 0 | D80: =$B$18 -> 0 | E80: =INDEX($G$43:$G$47,MATCH(B80,$B$43:$B$47,0)) -> 0 | F80: 0 | G80: 0 | H80: =F80-G80 -> 0 | I80: =H80*E80*12 -> 0
B81: =E81/$H$82 -> 0 | D81: Sub-Total | E81: =SUM(E76:E80) -> 0 | H81: Total Annual Rental Income | I81: =SUM(I52:I56)+SUM(I58:I62)+SUM(I64:I68)+SUM(I70:I74)+SUM(I76:I80) -> 7752009.3
B82: =B57+B63+B69+B75+B81 -> 1 | G82: Total Revenue units | H82: =SUM(E52:E56)+SUM(E58:E62)+SUM(E64:E68)+SUM(E70:E74)+SUM(E76:E80) -> 328 | I82: Applicable Fraction:
G83: Total LIHTC units | H83: =SUM(E52:E56)+SUM(E58:E62)+SUM(E64:E68)+SUM(E70:E74)+SUM(E76:E80) -> 328 | I83: =H83/H82 -> 1
H84: TOTAL ANNUAL PROJECT INCOME: | I84: =I81+F102 -> 7836489.3
B86: SF DISTRIBUTION
D87: GSF | G87: Efficiency | H87: NSF
B88: =D88/$D$92 -> 0.94432416 | D88: =Assumptions!C43 -> 305300 | E88: Residential GSF | G88: =H88/D88 -> 0.69824763 | H88: =F39 -> 213175
B89: =D89/$D$92 -> 0 | D89: =Assumptions!C44 -> 0 | E89: Commercial GSF | G89: =100% -> 1 | H89: =G89*D89 -> 0
B90: =D90/$D$92 -> 0.055675843 | D90: =Assumptions!C45 -> 18000 | E90: Community GSF | G90: =100% -> 1 | H90: =G90*D90 -> 18000
B91: =D91/$D$92 -> 0 | D91: =Assumptions!C46 -> 0 | E91: Parking GSF | G91: =100% -> 1 | H91: =G91*D91 -> 0
D92: =SUM(D88:D91) -> 323300 | E92: Total Project GSF | H92: =SUM(H88:H91) -> 231175
B95: COMMERICAL AND ANCILLARY INCOME
C96: # of Spaces | D96: Monthly Rent | F96: Annual Income
B97: Parking | C97: 75 | D97: 50 | F97: =C97*D97*12 -> 45000
B98: Commercial | C98: =D89 -> 0 | D98: 30 | F98: =D98*C98 -> 0
B99: Community Facility | C99: =D90 -> 18000 | D99: 0 | F99: =D99*C99 -> 0
B100: Laundry | C100: =C39 -> 329 | D100: 120 | F100: =D100*C100 -> 39480
E102: Total Commercial & Ancillary Income | F102: =F97+F98+F99+F100 -> 84480

Sheet Sources and Uses
B2: SOURCES AND USES | D2: Units: | E2: ='Unit Mix'!C19 -> 328
B4: Construction Sources | D4: Per DU | E4: % of Total
B5: HFA First Mortgage | C5: =Mortgage!C48 -> 47186010 | D5: =C5/'Unit Mix'!$C$19 -> 143859.79 | E5: =C5/$C$12 -> 0.18382958
B6: HFA Construction Loan | C6: 1.3503435e+08 | D6: =C6/'Unit Mix'!$C$19 -> 411690.09 | E6: =C6/$C$12 -> 0.52607346
B7: NCF | C7: =Mortgage!D64 -> 47232000 | D7: =C7/'Unit Mix'!$C$19 -> 144000 | E7: =C7/$C$12 -> 0.18400875
B8: LIHTC | C8: ='Tax Credit Analysis'!D8*Assumptions!C159 -> 10635591 | D8: =C8/'Unit Mix'!$C$19 -> 32425.583 | E8: =C8/$C$12 -> 0.041434659
B9: Sponsor's Equity | C9: =Assumptions!C156 -> 0 | D9: =C9/'Unit Mix'!$C$19 -> 0 | E9: =C9/$C$12 -> 0
B10: SLIHTC | C10: 7815499.3 | D10: =C10/'Unit Mix'!$C$19 -> 23827.742 | E10: =C10/$C$12 -> 0.030448006 | F10: =C10/C18 -> 0.18277796
B11: Deferred Developer Fee | C11: =Assumptions!D62 -> 8780000 | D11: =C11/'Unit Mix'!$C$19 -> 26768.293 | E11: =C11/$C$12 -> 0.034205555
B12: Total Construction Sources | C12: =SUM(C5:C11) -> 2.5668345e+08 | D12: =C12/'Unit Mix'!$C$19 -> 782571.5 | E12: =C12/$C$12 -> 1
B14: Permament Sources | D14: Per DU | E14: % of Total
B15: HFA First Mortgage | C15: =Mortgage!C48 -> 47186010 | D15: =C15/'Unit Mix'!$C$19 -> 143859.79 | E15: =C15/$C$20 -> 0.18382958
B16: NCF | C16: =Mortgage!C63 -> 52480000 | D16: =C16/'Unit Mix'!$C$19 -> 160000 | E16: =C16/$C$20 -> 0.20445416
B17: LIHTC | C17: ='Tax Credit Analysis'!D8 -> 1.0635591e+08 | D17: =C17/'Unit Mix'!$C$19 -> 324255.83 | E17: =C17/$C$20 -> 0.41434659
B18: SLIHTC | C18: 42759527 | D18: =C18/'Unit Mix'!$C$19 -> 130364.41 | E18: =C18/$C$20 -> 0.16658467
B19: Deferred Developer Fee | C19: =Assumptions!D65 -> 7902000 | D19: =C19/'Unit Mix'!$C$19 -> 24091.463 | E19: =C19/$C$20 -> 0.030785
B20: Total Permanent Sources | C20: =SUM(C15:C19) -> 2.5668345e+08 | D20: =C20/'Unit Mix'!$C$19 -> 782571.5 | E20: =C20/$C$20 -> 1
B22: Uses | D22: Per DU | E22: % of Total
B23: Acquisition | C23: 1 | D23: 0.017241379 | E23: =C23/$C$29 -> 3.8958491e-09
B24: Hard Costs | C24: =Assumptions!C92-Assumptions!C85 -> 205394400 | D24: =C24/'Unit Mix'!$C$19 -> 626202.44 | E24: =C24/$C$29 -> 0.80018559
B25: Soft Costs | C25: =Assumptions!C118-Assumptions!C108 -> 7703079.8 | D25: =C25/'Unit Mix'!$C$19 -> 23484.999 | E25: =C25/$C$29 -> 0.030010037
B26: =Assumptions!B120 -> Finance Cost | C26: =Assumptions!C144 -> 32856072 | D26: =C26/'Unit Mix'!$C$19 -> 100170.95 | E26: =C26/$C$29 -> 0.1280023
B27: Reserves and Escrows | C27: =Assumptions!C148 -> 1949898.8 | D27: =C27/'Unit Mix'!$C$19 -> 5944.8133 | E27: =C27/$C$29 -> 0.0075965114
B28: Developer Fee | C28: =Assumptions!D62 -> 8780000 | D28: =C28/'Unit Mix'!$C$19 -> 26768.293 | E28: =C28/$C$29 -> 0.034205555
B29: TOTAL USES | C29: =SUM(C23:C28) -> 2.5668345e+08 | D29: =C29/'Unit Mix'!$C$19 -> 782571.5 | E29: =C29/$C$29 -> 1

Sheet Mortgage
B2: MORTGAGE
B4: Income
B5: Residential Income | D5: ='Unit Mix'!I81 -> 7752009.3
B6: Parking | D6: ='Unit Mix'!F97 -> 45000
B7: Commercial | D7: ='Unit Mix'!F98 -> 0
B8: Community Facility | D8: ='Unit Mix'!F99 -> 0
B9: Laundry | D9: ='Unit Mix'!F100 -> 39480
B10: Potential Gross Income (PGI) | D10: =SUM(D5:D9) -> 7836489.3
C11: HFA/SONYMA Std:
B12: Less Vacancies
B13: Total Annual Rental Income | C13: 0.05 | D13: =D5*-C13 -> -387600.46
B14: Parking | C14: 0.05 | D14: =D6*-C14 -> -2250
B15: Commercial | C15: 0.1 | D15: =D7*-C15 -> 0
B16: Community Facility | C16: 0.1 | D16: =D8*-C16 -> 0
B17: Laundry | C17: 0.1 | D17: =D9*-C17 -> -3948
B18: Net Residential Income | D18: =D5+D13 -> 7364408.8
B19: Net Comm & Ancillary Income | D19: =SUM(D6:D9)+SUM(D14:D17) -> 78282
B20: Effective Gross Income (EGI) | D20: =D18+D19 -> 7442690.8
B22: Total Expenses & Reserves | D22: ='Operating Expenses & Reserves'!D46+'Operating Expenses & Reserves'!D48 -> 3340897.3
B24: NET OPERATING INCOME (NOI) | D24: =D20-D22 -> 4101793.5
B27: PERMANENT LOAN SIZING
B28: Permanent Credit Enhancer | C28: SONYMA-MIF
B29: Loan type | C29: Tax-Exempt | D29: Self-Amortizing
B30: Interest Rate | C30: Fixed
B31: Term (years) | C31: 30
B32: Interest Rates
B33: Base Underwriting Rate | C33: 0.05
B34: Servicing Fee (HFA) | C34: 0.0025
B35: SONYMA premium | C35: =IF(C28="SONYMA-MIF",0.5%,0) -> 0.005
B36: Sum (All-In Rate): | C36: =SUM(C33:C35) -> 0.0575
B38: Debt Service Coverage Ratio (DSCR): | C38: 1.15
B39: Avail. debt service (NOI): | C39: =D24/C38 -> 3566777
B40: Max. Loan based on DSCR: | C40: =((-PV(C36/12,C31*12,(C39-C69)/12))) -> 47186010
B42: Income to Expense (I-E) Ratio (min) | C42: 1.05
B43: Effective Gross Income (EGI) | C43: =D20 -> 7442690.8
B44: Total Expenses | C44: =-D22 -> -3340897.3
B45: Avai. Debt service (I-E) | C45: =C43/C42+C44 -> 3747379.7
B46: Max. Loan based on I-E | C46: =-(PV(C38/12,C31*12,(C45+C69)/12)) -> 3486764.9
B48: HFA First Mortgage Amount | C48: =C40 -> 47186010
B50: Short term Bond Sizing
B51: Loan Type | C51: Tax-Exempt
B52: Target Total Bond Amount | C52: 0.75126299 | D52: =Assumptions!F150*C52 -> 1.8227316e+08
B53: Permanent Bond Amount | D53: =C48 -> 47186010
B54: Required Short-Term Bond Amount | D54: =D52-D53 -> 1.3508715e+08
D56: =D54+D53+D64 -> 2.2950516e+08
B57: Totl Loan Required | C57: 0.84 | D57: =Amortization!H7*C57 -> 2.3501716e+08 | E57: =Amortization!H7 -> 2.7978234e+08
D58: =D57-D56 -> 5512004.8
B61: SUBSIDY LOAN
B62: Subsidy Type | C62: New Construction Finance (NCF)
B63: Loan Amount | C63: =160000*('Unit Mix'!E57+'Unit Mix'!E63+'Unit Mix'!E69+'Unit Mix'!E75+'Unit Mix'!E81) -> 52480000 | E63: =C63/'Unit Mix'!C19 -> 160000 | F63: per unit
B64: Amount (%) Advanced During Construction | C64: 0.9 | D64: =C63*C64 -> 47232000
B65: Mortgage Type | C65: Interest Only
B66: Construction Interest Rate | C66: 0.005 | D66: HFA standard is 0.5%
B67: Permanent Interest Rate | C67: 0.005 | D67: HFA standard is 0.5%
B68: Term (years) | C68: =SUM(Assumptions!C11:C12,Assumptions!C14)/12 -> 32.5
B69: Annual Hard Interest Payment | C69: =C63*C67 -> 262400

Sheet Construction Interest
B2: Construction Interest
B4: Loan Amount
C5: Amount | D5: % of Bond
B6: Long Term Bond | C6: =Mortgage!C48 -> 47186010 | D6: =C6/SUM($C$6:$C$7) -> 0.25895026
B7: Short Term Bond | C7: ='Sources and Uses'!C6 -> 1.3503435e+08 | D7: =C7/SUM($C$6:$C$7) -> 0.74104974
B8: Total Bond | C8: =C6+C7 -> 1.8222036e+08
B10: Subsidy Loan (NCF) | C10: =Mortgage!D64 -> 47232000
B13: Loan Term (in months)
C14: Months | D14: Years
B15: Construction Period | C15: =Assumptions!C11 -> 24 | D15: =C15/12 -> 2
B16: Rent-up and conversion | C16: =Assumptions!C12 -> 6 | D16: =C16/12 -> 0.5
B17: Total | C17: =C15+C16 -> 30 | D17: =D16+D15 -> 2.5
B20: Construction Loan (Long term) IR
B21: Base Rate (Municipal Bond) | C21: 0.05
B22: Servicing Fee (adjusted in soft cost) | C22: 0
B23: Total Long term IR | C23: =C22+C21 -> 0.05
B25: Construction Loan (NCF) IR
B26: Interest | C26: 0.005
B27: Servicing Fee (optional) | C27: 0.0025
B28: Total NCF IR | C28: =C26 -> 0.005
B31: Loan Interest Rates during Construction
B32: Long Term | C32: =C23 -> 0.05
B33: Short Term | C33: 0.042
B34: Subsidy Loan (NCF) | C34: =C28 -> 0.005
B36: Construction Interest Calculation
C37: Loan Amount | D37: Interest Rate | E37: Monthly Interest | F37: Term (months) | G37: Total
B38: Long Term | C38: =C6 -> 47186010 | D38: =C32 -> 0.05 | E38: =(C38*D38)/12 -> 196608.38 | F38: =$C$17 -> 30 | G38: =E38*F38 -> 5898251.3
B39: Short Term | C39: =C7 -> 1.3503435e+08 | D39: =C33 -> 0.042 | E39: =(C39*D39)/12 -> 472620.23 | F39: =$C$17 -> 30 | G39: =E39*F39 -> 14178607
B40: Subsidy Loan (NCF) | C40: =C10 -> 47232000 | D40: =C34 -> 0.005 | E40: =(C40*D40)/12 -> 19680 | F40: =$C$17 -> 30 | G40: =E40*F40 -> 590400
B43: Letter of Credit (LC)
B44: Bond amount | C44: =C8 -> 1.8222036e+08
B45: Days Interest | C45: =SUM(E38:E39) -> 669228.6
B46: LC amount | C46: =SUM(C44:C45) -> 1.8288959e+08
B48: LC Origination Fee (%) | C48: 0.01 | D48: HFA stds
B49: LC Annual Fee (%) | C49: 0.011 | D49: HFA stds

Sheet Operating Expenses & Reserves
B2: Management & Operating Expense
D3: Units | E3: ='Unit Mix'!C19 -> 328
D4: Rooms | E4: ='Unit Mix'!E37 -> 1207
B6: Please add/modify categories as needed: | C6: Multiplier | D6: Expenses/ Unit | E6: Expenses/ Room | F6: Borrower Projected Expenses | H6: Multiplier | I6: 2024 New Construction Standards Non-Union Building Staff | J6: Multiplier | K6: 2024 New Construction Standards Union Building Staff
B7: Fixed Expenses
B8: Real Estate Taxes | C8: per total project | D8: =F8/$E$3 -> 0 | E8: =F8/$E$4 -> 0 | F8: 0 | H8: per total project | I8: 0 | J8: per total project | K8: 0
B9: Fire & Liability Insurance | C9: per total project | D9: =F9/$E$3 -> 1500 | E9: =F9/$E$4 -> 407.6222 | F9: =I9*$E$3 -> 492000 | H9: per unit | I9: 1500 | J9: per unit | K9: =I9 -> 1500
B10: Total | D10: =SUM(D8:D9) -> 1500 | E10: =SUM(E8:E9) -> 407.6222 | F10: =SUM(F8:F9) -> 492000
B11: Administrative
B12: Accounting | C12: per total project | D12: =F12/$E$3 -> 57.926829 | E12: =F12/$E$4 -> 15.741508 | F12: =I12 -> 19000 | H12: per total project | I12: 19000 | J12: per total project | K12: =I12 -> 19000
B13: Benchmarking | C13: per total project | D13: =F13/$E$3 -> 2.4390244 | E13: =F13/$E$4 -> 0.66280033 | F13: =I13 -> 800 | H13: per total project | I13: 800 | J13: per total project | K13: =I13 -> 800
B14: Legal | C14: per total project | D14: =F14/$E$3 -> 260 | E14: =F14/$E$4 -> 70.654515 | F14: =I14*$E$3 -> 85280 | H14: per unit | I14: 260 | J14: per unit | K14: =I14 -> 260
B15: Total | D15: =SUM(D12:D14) -> 320.36585 | E15: =SUM(E12:E14) -> 87.058824 | F15: =SUM(F12:F14) -> 105080
B17: Management Fee | C17: per total project | D17: =F17/$E$3 -> 1474.9235 | E17: =F17/$E$4 -> 400.80771 | F17: =I17*Mortgage!D20 -> 483774.9 | H17: percent of EGI | I17: 0.065 | J17: percent of EGI | K17: 0.065
B19: Wi-Fi Service | C19: per unit | D19: =F19/$E$3 -> 198.17073 | E19: =F19/$E$4 -> 53.852527 | F19: =65000 -> 65000 | H19: per unit | I19: 500 | J19: per unit | K19: 400
B21: Utilities
B22: Heating | C22: per total project | D22: =F22/$E$3 -> 699.17683 | E22: =F22/$E$4 -> 190 | F22: =I22*$E$4 -> 229330 | H22: per room | I22: 190 | J22: per room | K22: =I22 -> 190
B23: Gas and Electricity | C23: per total project | D23: =F23/$E$3 -> 809.57317 | E23: =F23/$E$4 -> 220 | F23: =I23*$E$4 -> 265540 | H23: per room | I23: 220 | J23: per room | K23: =I23 -> 220
B24: Water/Sewer | C24: per total project | D24: =F24/$E$3 -> 1287.9573 | E24: =F24/$E$4 -> 350 | F24: =I24*$E$4 -> 422450 | H24: per room | I24: 350 | J24: per room | K24: =I24 -> 350
B25: Total | D25: =SUM(D22:D24) -> 2796.7073 | E25: =SUM(E22:E24) -> 760 | F25: =SUM(F22:F24) -> 917320
B26: Repairs and Maintenance
B27: Supplies/Cleaning/Exterminating | C27: per total project | D27: =F27/$E$3 -> 588.78049 | E27: =F27/$E$4 -> 160 | F27: =I27*$E$4 -> 193120 | H27: per room | I27: 160 | J27: per room | K27: =I27 -> 160
B28: Repairs/Replacement | C28: per total project | D28: =F28/$E$3 -> 1500 | E28: =F28/$E$4 -> 407.6222 | F28: =I28*$E$3 -> 492000 | H28: per unit | I28: 1500 | J28: per unit | K28: =I28 -> 1500
B29: Superintendent & Maintenance Staff Salaries | C29: per total project | D29: =F29/$E$3 -> 795.67378 | E29: =F29/$E$4 -> 216.22287 | F29: =F31+F32 -> 260981 | H29: per unit | J29: per unit
C30: Salaries | D30: No. | F30: No.
B31: Super | D31: 1 | F31: 145455
B32: Porter | D32: 7 | F32: 115526
B33: Elevator Maintenance and Repairs | C33: per elevator | D33: 3 | F33: =I33*D33 -> 24000 | H33: per elevator | I33: 8000 | J33: per elevator | K33: =I33 -> 8000
B34: Total | D34: =SUM(D27:D29) -> 2884.4543 | E34: =SUM(E27:E29) -> 783.84507 | F34: =SUM(F27:F33) -> 1231082
B36: Total Operating Expenses | D36: =D15+D17+D25+D34+D10 -> 8976.4509 | E36: =E15+E17+E25+E34+E10 -> 2439.3338 | F36: =F10+F15+F17+F25+F34 -> 3229256.9
B37: Total Expenses Net of Management Fee | D37: =D36-D10 -> 7476.4509 | E37: =E36-E10 -> 2031.7116 | F37: =F36-F17 -> 2745482
B40: Total Operating Expenses | D40: =D36 -> 8976.4509 | E40: =E36 -> 2439.3338 | F40: =F36 -> 3229256.9 | H40: 1 Staff Member for every 65 units. As permitted by law, additional FT or PT Supers or Porters may satisfy the operational needs of bulidings between each 65 unit threshold. | J40: 1 Staff Member for every 65 units. As permitted by law, additional FT or PT Supers or Porters may satisfy the operational needs of bulidings between each 65 unit threshold.
B44: Reserves
D45: Annually
B46: Opertaing Expense | D46: ='Operating Expenses & Reserves'!F36 -> 3229256.9
B47: Operating Reserve | C47: 6 months M&O + debt service | D47: =(D46/2)+(SUM('Construction Interest'!E38:E39,(Mortgage!C63*0.5%)*'Construction Interest'!D40)/2) -> 1949898.8
B48: Replacement Reserve | C48: Per annual HDC M&O standards | D48: =Mortgage!D20*1.5% -> 111640.36
B49: Social Services Reserve (Our Space) | C49: $15,000 max per Our Space unit | D49: 0
B50: Social Services Reserve Cap | C50: 3 years × $5,000/unit = $15,000/unit | D50: =15000*'Unit Mix'!C14 -> 735000
B51: Social Services Budget (Initial) | C51: $7,500 per Our Space unit | D51: =Assumptions!C34*7500 -> 367500
B52: Ongoing Social Services Payment | C52: Up to $5,000 per Our Space unit/year | D52: 0
B53: Homeless Furnishings Budget (Studio) | C53: $2,000 per studio unit | D53: =ROUND('Unit Mix'!C43,0)*2000 -> 18000
B54: Homeless Furnishings Budget (Non-Studio) | C54: $3,000 per non-studio unit | D54: =ROUND(SUM('Unit Mix'!C44:C47),0)*3000 -> 120000

Sheet Tax Credit Analysis
B2: TAX CREDIT ANALYSIS
B3: Eligible Basis | D3: =Assumptions!F150 -> 2.4262231e+08
B4: Eligible Basis with Boost | C4: 1.3 | D4: =D3*C4 -> 3.15409e+08
B5: Applicable Fraction | C5: 1 | D5: =D4*C5 -> 3.15409e+08
B6: Annual Credit Rate | C6: 0.04 | D6: =D5*C6 -> 12616360
B7: Amount Raised per Credit | C7: 0.843 | D7: =D6*C7 -> 10635591
B8: Amount Raised Total | D8: =D7*10 -> 1.0635591e+08 | E8: Federal
B9: Amount Raised per Credit | C9: 0.65 | D9: =D6*C9 -> 8200633.9
B10: Amount Raised Total | D10: =D9*10 -> 82006339 | E10: SLIHC

Sheet Budget
B2: BUDGET
B3: ALL figures are in USD
J5: 1 | K5: 2 | L5: 3 | M5: 4 | N5: 5 | O5: 6 | P5: 7 | Q5: 8 | R5: 9 | S5: 10 | T5: 11 | U5: 12 | V5: 13 | W5: 14 | X5: 15 | Y5: 16 | Z5: 17 | AA5: 18 | AB5: 19 | AC5: 20 | AD5: 21 | AE5: 22 | AF5: 23 | AG5: 24 | AH5: 25 | AI5: 26 | AJ5: 27 | AK5: 28 | AL5: 29 | AM5: 30 | AN5: 31 | AO5: 32 | AP5: 33 | AQ5: 34 | AR5: 35 | AS5: 36 | AT5: 37 | AU5: 38 | AV5: 39 | AW5: 40 | AX5: 41 | AY5: 42 | AZ5: 43 | BA5: 44 | BB5: 45 | BC5: 46 | BD5: 47 | BE5: 48 | BF5: 49 | BG5: 50 | BH5: 51 | BI5: 52 | BJ5: 53 | BK5: 54 | BL5: 55 | BM5: 56 | BN5: 57 | BO5: 58 | BP5: 59 | BQ5: 60 | BR5: 61 | BS5: 62 | BT5: 63 | BU5: 64 | BV5: 65 | BW5: 66 | BX5: 67 | BY5: 68 | BZ5: 69 | CA5: 70 | CB5: 71 | CC5: 72 | CD5: 73 | CE5: 74 | CF5: 75 | CG5: 76 | CH5: 77 | CI5: 78 | CJ5: 79 | CK5: 80 | CL5: 81 | CM5: 82 | CN5: 83 | CO5: 84 | CP5: 85 | CQ5: 86 | CR5: 87 | CS5: 88 | CT5: 89 | CU5: 90 | CV5: 91 | CW5: 92 | CX5: 93 | CY5: 94 | CZ5: 95 | DA5: 96 | DB5: 97 | DC5: 98 | DD5: 99 | DE5: 100 | DF5: 101 | DG5: 102 | DH5: 103 | DI5: 104 | DJ5: 105 | DK5: 106 | DL5: 107 | DM5: 108 | DN5: 109 | DO5: 110 | DP5: 111 | DQ5: 112 | DR5: 113 | DS5: 114 | DT5: 115 | DU5: 116 | DV5: 117 | DW5: 118 | DX5: 119 | DY5: 120 | DZ5: 121 | EA5: 122 | EB5: 123 | EC5: 124 | ED5: 125 | EE5: 126 | EF5: 127 | EG5: 128 | EH5: 129 | EI5: 130 | EJ5: 131 | EK5: 132 | EL5: 133 | EM5: 134 | EN5: 135 | EO5: 136 | EP5: 137 | EQ5: 138 | ER5: 139 | ES5: 140 | ET5: 141 | EU5: 142 | EV5: 143 | EW5: 144 | EX5: 145 | EY5: 146 | EZ5: 147 | FA5: 148 | FB5: 149 | FC5: 150 | FD5: 151 | FE5: 152 | FF5: 153 | FG5: 154 | FH5: 155 | FI5: 156 | FJ5: 157 | FK5: 158 | FL5: 159 | FM5: 160 | FN5: 161 | FO5: 162 | FP5: 163 | FQ5: 164 | FR5: 165 | FS5: 166 | FT5: 167 | FU5: 168 | FV5: 169 | FW5: 170 | FX5: 171 | FY5: 172 | FZ5: 173 | GA5: 174 | GB5: 175 | GC5: 176 | GD5: 177 | GE5: 178 | GF5: 179 | GG5: 180 | GH5: 181 | GI5: 182 | GJ5: 183 | GK5: 184 | GL5: 185 | GM5: 186 | GN5: 187 | GO5: 188 | GP5: 189 | GQ5: 190 | GR5: 191 | GS5: 192 | GT5: 193 | GU5: 194 | GV5: 195 | GW5: 196 | GX5: 197 | GY5: 198 | GZ5: 199 | HA5: 200 | HB5: 201 | HC5: 202 | HD5: 203 | HE5: 204 | HF5: 205 | HG5: 206 | HH5: 207 | HI5: 208 | HJ5: 209 | HK5: 210 | HL5: 211 | HM5: 212 | HN5: 213 | HO5: 214 | HP5: 215 | HQ5: 216 | HR5: 217 | HS5: 218 | HT5: 219 | HU5: 220 | HV5: 221 | HW5: 222 | HX5: 223 | HY5: 224 | HZ5: 225 | IA5: 226 | IB5: 227 | IC5: 228 | ID5: 229 | IE5: 230 | IF5: 231 | IG5: 232 | IH5: 233 | II5: 234 | IJ5: 235 | IK5: 236 | IL5: 237 | IM5: 238 | IN5: 239 | IO5: 240 | IP5: 241 | IQ5: 242 | IR5: 243 | IS5: 244 | IT5: 245 | IU5: 246 | IV5: 247 | IW5: 248 | IX5: 249 | IY5: 250 | IZ5: 251 | JA5: 252 | JB5: 253 | JC5: 254 | JD5: 255 | JE5: 256 | JF5: 257 | JG5: 258 | JH5: 259 | JI5: 260 | JJ5: 261 | JK5: 262 | JL5: 263 | JM5: 264 | JN5: 265 | JO5: 266 | JP5: 267 | JQ5: 268 | JR5: 269 | JS5: 270 | JT5: 271 | JU5: 272 | JV5: 273 | JW5: 274 | JX5: 275 | JY5: 276 | JZ5: 277 | KA5: 278 | KB5: 279 | KC5: 280 | KD5: 281 | KE5: 282 | KF5: 283 | KG5: 284 | KH5: 285 | KI5: 286 | KJ5: 287 | KK5: 288 | KL5: 289 | KM5: 290 | KN5: 291 | KO5: 292 | KP5: 293 | KQ5: 294 | KR5: 295 | KS5: 296 | KT5: 297 | KU5: 298 | KV5: 299 | KW5: 300 | KX5: 301 | KY5: 302 | KZ5: 303 | LA5: 304 | LB5: 305 | LC5: 306 | LD5: 307 | LE5: 308 | LF5: 309 | LG5: 310 | LH5: 311 | LI5: 312 | LJ5: 313 | LK5: 314 | LL5: 315 | LM5: 316 | LN5: 317 | LO5: 318 | LP5: 319 | LQ5: 320 | LR5: 321 | LS5: 322 | LT5: 323 | LU5: 324 | LV5: 325 | LW5: 326 | LX5: 327 | LY5: 328 | LZ5: 329 | MA5: 330 | MB5: 331 | MC5: 332 | MD5: 333 | ME5: 334 | MF5: 335 | MG5: 336 | MH5: 337 | MI5: 338 | MJ5: 339 | MK5: 340 | ML5: 341 | MM5: 342 | MN5: 343 | MO5: 344 | MP5: 345 | MQ5: 346 | MR5: 347 | MS5: 348 | MT5: 349 | MU5: 350 | MV5: 351 | MW5: 352 | MX5: 353 | MY5: 354 | MZ5: 355 | NA5: 356 | NB5: 357 | NC5: 358 | ND5: 359 | NE5: 360 | NF5: 361 | NG5: 362 | NH5: 363 | NI5: 364 | NJ5: 365 | NK5: 366 | NL5: 367 | NM5: 368 | NN5: 369 | NO5: 370 | NP5: 371 | NQ5: 372 | NR5: 373 | NS5: 374 | NT5: 375 | NU5: 376 | NV5: 377 | NW5: 378 | NX5: 379 | NY5: 380 | NZ5: 381 | OA5: 382 | OB5: 383 | OC5: 384 | OD5: 385 | OE5: 386 | OF5: 387 | OG5: 388 | OH5: 389 | OI5: 390 | OJ5: 391 | OK5: 392 | OL5: 393 | OM5: 394 | ON5: 395 | OO5: 396
J6: =YEAR(J7) -> 2026 | K6: =YEAR(K7) -> 2026 | L6: =YEAR(L7) -> 2026 | M6: =YEAR(M7) -> 2026 | N6: =YEAR(N7) -> 2026 | O6: =YEAR(O7) -> 2026 | P6: =YEAR(P7) -> 2027 | Q6: =YEAR(Q7) -> 2027 | ... OO6: =YEAR(OO7) -> 2059
D7: Costs | E7: Start | F7: End | G7: Months | J7: =Assumptions!C8 -> 46204 | K7: =EOMONTH(J7,1) -> 46265 | L7: =EOMONTH(K7,1) -> 46295 | M7: =EOMONTH(L7,1) -> 46326 | N7: =EOMONTH(M7,1) -> 46356 | O7: =EOMONTH(N7,1) -> 46387 | P7: =EOMONTH(O7,1) -> 46418 | Q7: =EOMONTH(P7,1) -> 46446 | R7: =EOMONTH(Q7,1) -> 46477 | ... OO7: =EOMONTH(ON7,1) -> 58256
B9: DEVELOPMENT PHASE
B11: =Assumptions!B74 -> Acquisition Costs
B12: =Assumptions!B75 -> Building Acquisition | D12: =Assumptions!C75 -> 0 | E12: =Assumptions!$C$8 -> 46204 | F12: =E12 -> 46204 | G12: =((YEAR(F12)-YEAR(E12))*12+MONTH(F12)-MONTH(E12)+1) -> 1 | J12: =-IF(J$7>=$E12,IF(J$7<=$F12,$D12/$G12,0),0) -> 0 | K12: =-IF(K$7>=$E12,IF(K$7<=$F12,$D12/$G12,0),0) -> 0 | L12: =-IF(L$7>=$E12,IF(L$7<=$F12,$D12/$G12,0),0) -> 0 | M12: =-IF(M$7>=$E12,IF(M$7<=$F12,$D12/$G12,0),0) -> 0 | N12: =-IF(N$7>=$E12,IF(N$7<=$F12,$D12/$G12,0),0) -> 0 | O12: =-IF(O$7>=$E12,IF(O$7<=$F12,$D12/$G12,0),0) -> 0 | P12: =-IF(P$7>=$E12,IF(P$7<=$F12,$D12/$G12,0),0) -> 0 | Q12: =-IF(Q$7>=$E12,IF(Q$7<=$F12,$D12/$G12,0),0) -> 0 | ... OO12: =-IF(OO$7>=$E12,IF(OO$7<=$F12,$D12/$G12,0),0) -> 0
B13: =Assumptions!B76 -> Land Acquisition | D13: =Assumptions!C76 -> 1 | E13: =Assumptions!$C$8 -> 46204 | F13: =E13 -> 46204 | G13: =((YEAR(F13)-YEAR(E13))*12+MONTH(F13)-MONTH(E13)+1) -> 1 | J13: =-IF(J$7>=$E13,IF(J$7<=$F13,$D13/$G13,0),0) -> -1 | K13: =-IF(K$7>=$E13,IF(K$7<=$F13,$D13/$G13,0),0) -> 0 | L13: =-IF(L$7>=$E13,IF(L$7<=$F13,$D13/$G13,0),0) -> 0 | M13: =-IF(M$7>=$E13,IF(M$7<=$F13,$D13/$G13,0),0) -> 0 | N13: =-IF(N$7>=$E13,IF(N$7<=$F13,$D13/$G13,0),0) -> 0 | O13: =-IF(O$7>=$E13,IF(O$7<=$F13,$D13/$G13,0),0) -> 0 | P13: =-IF(P$7>=$E13,IF(P$7<=$F13,$D13/$G13,0),0) -> 0 | Q13: =-IF(Q$7>=$E13,IF(Q$7<=$F13,$D13/$G13,0),0) -> 0 | ... OO13: =-IF(OO$7>=$E13,IF(OO$7<=$F13,$D13/$G13,0),0) -> 0
B14: =Assumptions!B77 -> Total Acquisition Costs | D14: =SUM(D12:D13) -> 1 | J14: =SUM(J12:J13) -> -1 | K14: =SUM(K12:K13) -> 0 | L14: =SUM(L12:L13) -> 0 | M14: =SUM(M12:M13) -> 0 | N14: =SUM(N12:N13) -> 0 | O14: =SUM(O12:O13) -> 0 | P14: =SUM(P12:P13) -> 0 | Q14: =SUM(Q12:Q13) -> 0 | ... OO14: =SUM(OO12:OO13) -> 0
B16: Hard Cost & Soft Cost
B17: =Assumptions!B80 -> Contractor Price | D17: =Assumptions!C80 -> 0 | E17: =Assumptions!$C$10 -> 46418 | F17: =EOMONTH(E17,Assumptions!$C$11-1) -> 47118 | G17: =((YEAR(F17)-YEAR(E17))*12+MONTH(F17)-MONTH(E17)+1) -> 24 | J17: =-IF(J$7>=$E17,IF(J$7<=$F17,$D17/$G17,0),0) -> 0 | K17: =-IF(K$7>=$E17,IF(K$7<=$F17,$D17/$G17,0),0) -> 0 | L17: =-IF(L$7>=$E17,IF(L$7<=$F17,$D17/$G17,0),0) -> 0 | M17: =-IF(M$7>=$E17,IF(M$7<=$F17,$D17/$G17,0),0) -> 0 | N17: =-IF(N$7>=$E17,IF(N$7<=$F17,$D17/$G17,0),0) -> 0 | O17: =-IF(O$7>=$E17,IF(O$7<=$F17,$D17/$G17,0),0) -> 0 | P17: =-IF(P$7>=$E17,IF(P$7<=$F17,$D17/$G17,0),0) -> 0 | Q17: =-IF(Q$7>=$E17,IF(Q$7<=$F17,$D17/$G17,0),0) -> 0 | ... OO17: =-IF(OO$7>=$E17,IF(OO$7<=$F17,$D17/$G17,0),0) -> 0
B18: =Assumptions!B81 -> Residential | D18: =Assumptions!C81 -> 164862000 | E18: =Assumptions!$C$10 -> 46418 | F18: =EOMONTH(E18,Assumptions!$C$11-1) -> 47118 | G18: =((YEAR(F18)-YEAR(E18))*12+MONTH(F18)-MONTH(E18)+1) -> 24 | J18: =-IF(J$7>=$E18,IF(J$7<=$F18,$D18/$G18,0),0) -> 0 | K18: =-IF(K$7>=$E18,IF(K$7<=$F18,$D18/$G18,0),0) -> 0 | L18: =-IF(L$7>=$E18,IF(L$7<=$F18,$D18/$G18,0),0) -> 0 | M18: =-IF(M$7>=$E18,IF(M$7<=$F18,$D18/$G18,0),0) -> 0 | N18: =-IF(N$7>=$E18,IF(N$7<=$F18,$D18/$G18,0),0) -> 0 | O18: =-IF(O$7>=$E18,IF(O$7<=$F18,$D18/$G18,0),0) -> 0 | P18: =-IF(P$7>=$E18,IF(P$7<=$F18,$D18/$G18,0),0) -> -6869250 | Q18: =-IF(Q$7>=$E18,IF(Q$7<=$F18,$D18/$G18,0),0) -> -6869250 | ... OO18: =-IF(OO$7>=$E18,IF(OO$7<=$F18,$D18/$G18,0),0) -> 0
B19: =Assumptions!B82 -> Commercial Space | D19: =Assumptions!C82 -> 0 | E19: =Assumptions!$C$10 -> 46418 | F19: =EOMONTH(E19,Assumptions!$C$11-1) -> 47118 | G19: =((YEAR(F19)-YEAR(E19))*12+MONTH(F19)-MONTH(E19)+1) -> 24 | J19: =-IF(J$7>=$E19,IF(J$7<=$F19,$D19/$G19,0),0) -> 0 | K19: =-IF(K$7>=$E19,IF(K$7<=$F19,$D19/$G19,0),0) -> 0 | L19: =-IF(L$7>=$E19,IF(L$7<=$F19,$D19/$G19,0),0) -> 0 | M19: =-IF(M$7>=$E19,IF(M$7<=$F19,$D19/$G19,0),0) -> 0 | N19: =-IF(N$7>=$E19,IF(N$7<=$F19,$D19/$G19,0),0) -> 0 | O19: =-IF(O$7>=$E19,IF(O$7<=$F19,$D19/$G19,0),0) -> 0 | P19: =-IF(P$7>=$E19,IF(P$7<=$F19,$D19/$G19,0),0) -> 0 | Q19: =-IF(Q$7>=$E19,IF(Q$7<=$F19,$D19/$G19,0),0) -> 0 | ... OO19: =-IF(OO$7>=$E19,IF(OO$7<=$F19,$D19/$G19,0),0) -> 0
B20: =Assumptions!B83 -> Community Space | D20: =Assumptions!C83 -> 6300000 | E20: =Assumptions!$C$10 -> 46418 | F20: =EOMONTH(E20,Assumptions!$C$11-1) -> 47118 | G20: =((YEAR(F20)-YEAR(E20))*12+MONTH(F20)-MONTH(E20)+1) -> 24 | J20: =-IF(J$7>=$E20,IF(J$7<=$F20,$D20/$G20,0),0) -> 0 | K20: =-IF(K$7>=$E20,IF(K$7<=$F20,$D20/$G20,0),0) -> 0 | L20: =-IF(L$7>=$E20,IF(L$7<=$F20,$D20/$G20,0),0) -> 0 | M20: =-IF(M$7>=$E20,IF(M$7<=$F20,$D20/$G20,0),0) -> 0 | N20: =-IF(N$7>=$E20,IF(N$7<=$F20,$D20/$G20,0),0) -> 0 | O20: =-IF(O$7>=$E20,IF(O$7<=$F20,$D20/$G20,0),0) -> 0 | P20: =-IF(P$7>=$E20,IF(P$7<=$F20,$D20/$G20,0),0) -> -262500 | Q20: =-IF(Q$7>=$E20,IF(Q$7<=$F20,$D20/$G20,0),0) -> -262500 | ... OO20: =-IF(OO$7>=$E20,IF(OO$7<=$F20,$D20/$G20,0),0) -> 0
B21: =Assumptions!B84 -> Parking | D21: =Assumptions!C84 -> 0 | E21: =Assumptions!$C$10 -> 46418 | F21: =EOMONTH(E21,Assumptions!$C$11-1) -> 47118 | G21: =((YEAR(F21)-YEAR(E21))*12+MONTH(F21)-MONTH(E21)+1) -> 24 | J21: =-IF(J$7>=$E21,IF(J$7<=$F21,$D21/$G21,0),0) -> 0 | K21: =-IF(K$7>=$E21,IF(K$7<=$F21,$D21/$G21,0),0) -> 0 | L21: =-IF(L$7>=$E21,IF(L$7<=$F21,$D21/$G21,0),0) -> 0 | M21: =-IF(M$7>=$E21,IF(M$7<=$F21,$D21/$G21,0),0) -> 0 | N21: =-IF(N$7>=$E21,IF(N$7<=$F21,$D21/$G21,0),0) -> 0 | O21: =-IF(O$7>=$E21,IF(O$7<=$F21,$D21/$G21,0),0) -> 0 | P21: =-IF(P$7>=$E21,IF(P$7<=$F21,$D21/$G21,0),0) -> 0 | Q21: =-IF(Q$7>=$E21,IF(Q$7<=$F21,$D21/$G21,0),0) -> 0 | ... OO21: =-IF(OO$7>=$E21,IF(OO$7<=$F21,$D21/$G21,0),0) -> 0
B22: =Assumptions!B85 -> Developer Fee | D22: =Assumptions!C85 -> 878000 | E22: =Assumptions!$C$10 -> 46418 | F22: =EOMONTH(E22,Assumptions!$C$11-1) -> 47118 | G22: =((YEAR(F22)-YEAR(E22))*12+MONTH(F22)-MONTH(E22)+1) -> 24 | J22: =-IF(J$7>=$E22,IF(J$7<=$F22,$D22/$G22,0),0) -> 0 | K22: =-IF(K$7>=$E22,IF(K$7<=$F22,$D22/$G22,0),0) -> 0 | L22: =-IF(L$7>=$E22,IF(L$7<=$F22,$D22/$G22,0),0) -> 0 | M22: =-IF(M$7>=$E22,IF(M$7<=$F22,$D22/$G22,0),0) -> 0 | N22: =-IF(N$7>=$E22,IF(N$7<=$F22,$D22/$G22,0),0) -> 0 | O22: =-IF(O$7>=$E22,IF(O$7<=$F22,$D22/$G22,0),0) -> 0 | P22: =-IF(P$7>=$E22,IF(P$7<=$F22,$D22/$G22,0),0) -> -36583.333 | Q22: =-IF(Q$7>=$E22,IF(Q$7<=$F22,$D22/$G22,0),0) -> -36583.333 | ... OO22: =-IF(OO$7>=$E22,IF(OO$7<=$F22,$D22/$G22,0),0) -> 0
B23: =Assumptions!B86 -> Contingent Hard Costs | D23: =Assumptions!C86 -> 0 | E23: =Assumptions!$C$10 -> 46418 | F23: =EOMONTH(E23,Assumptions!$C$11-1) -> 47118 | G23: =((YEAR(F23)-YEAR(E23))*12+MONTH(F23)-MONTH(E23)+1) -> 24 | J23: =-IF(J$7>=$E23,IF(J$7<=$F23,$D23/$G23,0),0) -> 0 | K23: =-IF(K$7>=$E23,IF(K$7<=$F23,$D23/$G23,0),0) -> 0 | L23: =-IF(L$7>=$E23,IF(L$7<=$F23,$D23/$G23,0),0) -> 0 | M23: =-IF(M$7>=$E23,IF(M$7<=$F23,$D23/$G23,0),0) -> 0 | N23: =-IF(N$7>=$E23,IF(N$7<=$F23,$D23/$G23,0),0) -> 0 | O23: =-IF(O$7>=$E23,IF(O$7<=$F23,$D23/$G23,0),0) -> 0 | P23: =-IF(P$7>=$E23,IF(P$7<=$F23,$D23/$G23,0),0) -> 0 | Q23: =-IF(Q$7>=$E23,IF(Q$7<=$F23,$D23/$G23,0),0) -> 0 | ... OO23: =-IF(OO$7>=$E23,IF(OO$7<=$F23,$D23/$G23,0),0) -> 0
B24: =Assumptions!B87 -> General Conditions | D24: =Assumptions!C87 -> 10269720 | E24: =Assumptions!$C$10 -> 46418 | F24: =EOMONTH(E24,Assumptions!$C$11-1) -> 47118 | G24: =((YEAR(F24)-YEAR(E24))*12+MONTH(F24)-MONTH(E24)+1) -> 24 | J24: =-IF(J$7>=$E24,IF(J$7<=$F24,$D24/$G24,0),0) -> 0 | K24: =-IF(K$7>=$E24,IF(K$7<=$F24,$D24/$G24,0),0) -> 0 | L24: =-IF(L$7>=$E24,IF(L$7<=$F24,$D24/$G24,0),0) -> 0 | M24: =-IF(M$7>=$E24,IF(M$7<=$F24,$D24/$G24,0),0) -> 0 | N24: =-IF(N$7>=$E24,IF(N$7<=$F24,$D24/$G24,0),0) -> 0 | O24: =-IF(O$7>=$E24,IF(O$7<=$F24,$D24/$G24,0),0) -> 0 | P24: =-IF(P$7>=$E24,IF(P$7<=$F24,$D24/$G24,0),0) -> -427905 | Q24: =-IF(Q$7>=$E24,IF(Q$7<=$F24,$D24/$G24,0),0) -> -427905 | ... OO24: =-IF(OO$7>=$E24,IF(OO$7<=$F24,$D24/$G24,0),0) -> 0
B25: =Assumptions!B88 -> Overhead | D25: =Assumptions!C88 -> 3423240 | E25: =Assumptions!$C$10 -> 46418 | F25: =EOMONTH(E25,Assumptions!$C$11-1) -> 47118 | G25: =((YEAR(F25)-YEAR(E25))*12+MONTH(F25)-MONTH(E25)+1) -> 24 | J25: =-IF(J$7>=$E25,IF(J$7<=$F25,$D25/$G25,0),0) -> 0 | K25: =-IF(K$7>=$E25,IF(K$7<=$F25,$D25/$G25,0),0) -> 0 | L25: =-IF(L$7>=$E25,IF(L$7<=$F25,$D25/$G25,0),0) -> 0 | M25: =-IF(M$7>=$E25,IF(M$7<=$F25,$D25/$G25,0),0) -> 0 | N25: =-IF(N$7>=$E25,IF(N$7<=$F25,$D25/$G25,0),0) -> 0 | O25: =-IF(O$7>=$E25,IF(O$7<=$F25,$D25/$G25,0),0) -> 0 | P25: =-IF(P$7>=$E25,IF(P$7<=$F25,$D25/$G25,0),0) -> -142635 | Q25: =-IF(Q$7>=$E25,IF(Q$7<=$F25,$D25/$G25,0),0) -> -142635 | ... OO25: =-IF(OO$7>=$E25,IF(OO$7<=$F25,$D25/$G25,0),0) -> 0
B26: =Assumptions!B89 -> Contractor Profit | D26: =Assumptions!C89 -> 10269720 | E26: =Assumptions!$C$10 -> 46418 | F26: =EOMONTH(E26,Assumptions!$C$11-1) -> 47118 | G26: =((YEAR(F26)-YEAR(E26))*12+MONTH(F26)-MONTH(E26)+1) -> 24 | J26: =-IF(J$7>=$E26,IF(J$7<=$F26,$D26/$G26,0),0) -> 0 | K26: =-IF(K$7>=$E26,IF(K$7<=$F26,$D26/$G26,0),0) -> 0 | L26: =-IF(L$7>=$E26,IF(L$7<=$F26,$D26/$G26,0),0) -> 0 | M26: =-IF(M$7>=$E26,IF(M$7<=$F26,$D26/$G26,0),0) -> 0 | N26: =-IF(N$7>=$E26,IF(N$7<=$F26,$D26/$G26,0),0) -> 0 | O26: =-IF(O$7>=$E26,IF(O$7<=$F26,$D26/$G26,0),0) -> 0 | P26: =-IF(P$7>=$E26,IF(P$7<=$F26,$D26/$G26,0),0) -> -427905 | Q26: =-IF(Q$7>=$E26,IF(Q$7<=$F26,$D26/$G26,0),0) -> -427905 | ... OO26: =-IF(OO$7>=$E26,IF(OO$7<=$F26,$D26/$G26,0),0) -> 0
B27: =Assumptions!B90 -> Bond Premium | D27: =Assumptions!C90 -> 1711620 | E27: =Assumptions!$C$10 -> 46418 | F27: =EOMONTH(E27,Assumptions!$C$11-1) -> 47118 | G27: =((YEAR(F27)-YEAR(E27))*12+MONTH(F27)-MONTH(E27)+1) -> 24 | J27: =-IF(J$7>=$E27,IF(J$7<=$F27,$D27/$G27,0),0) -> 0 | K27: =-IF(K$7>=$E27,IF(K$7<=$F27,$D27/$G27,0),0) -> 0 | L27: =-IF(L$7>=$E27,IF(L$7<=$F27,$D27/$G27,0),0) -> 0 | M27: =-IF(M$7>=$E27,IF(M$7<=$F27,$D27/$G27,0),0) -> 0 | N27: =-IF(N$7>=$E27,IF(N$7<=$F27,$D27/$G27,0),0) -> 0 | O27: =-IF(O$7>=$E27,IF(O$7<=$F27,$D27/$G27,0),0) -> 0 | P27: =-IF(P$7>=$E27,IF(P$7<=$F27,$D27/$G27,0),0) -> -71317.5 | Q27: =-IF(Q$7>=$E27,IF(Q$7<=$F27,$D27/$G27,0),0) -> -71317.5 | ... OO27: =-IF(OO$7>=$E27,IF(OO$7<=$F27,$D27/$G27,0),0) -> 0
B28: =Assumptions!B91 -> Contingency | D28: =Assumptions!C91 -> 8558100 | E28: =Assumptions!$C$10 -> 46418 | F28: =EOMONTH(E28,Assumptions!$C$11-1) -> 47118 | G28: =((YEAR(F28)-YEAR(E28))*12+MONTH(F28)-MONTH(E28)+1) -> 24 | J28: =-IF(J$7>=$E28,IF(J$7<=$F28,$D28/$G28,0),0) -> 0 | K28: =-IF(K$7>=$E28,IF(K$7<=$F28,$D28/$G28,0),0) -> 0 | L28: =-IF(L$7>=$E28,IF(L$7<=$F28,$D28/$G28,0),0) -> 0 | M28: =-IF(M$7>=$E28,IF(M$7<=$F28,$D28/$G28,0),0) -> 0 | N28: =-IF(N$7>=$E28,IF(N$7<=$F28,$D28/$G28,0),0) -> 0 | O28: =-IF(O$7>=$E28,IF(O$7<=$F28,$D28/$G28,0),0) -> 0 | P28: =-IF(P$7>=$E28,IF(P$7<=$F28,$D28/$G28,0),0) -> -356587.5 | Q28: =-IF(Q$7>=$E28,IF(Q$7<=$F28,$D28/$G28,0),0) -> -356587.5 | ... OO28: =-IF(OO$7>=$E28,IF(OO$7<=$F28,$D28/$G28,0),0) -> 0
B30: =Assumptions!B95 -> Accounting & Cost Certification | D30: =Assumptions!C95 -> 30000 | E30: =Assumptions!$C$8 -> 46204 | F30: =EOMONTH(E30,Assumptions!$C$9-1) -> 46387 | G30: =((YEAR(F30)-YEAR(E30))*12+MONTH(F30)-MONTH(E30)+1) -> 6 | J30: =-IF(J$7>=$E30,IF(J$7<=$F30,$D30/$G30,0),0) -> -5000 | K30: =-IF(K$7>=$E30,IF(K$7<=$F30,$D30/$G30,0),0) -> -5000 | L30: =-IF(L$7>=$E30,IF(L$7<=$F30,$D30/$G30,0),0) -> -5000 | M30: =-IF(M$7>=$E30,IF(M$7<=$F30,$D30/$G30,0),0) -> -5000 | N30: =-IF(N$7>=$E30,IF(N$7<=$F30,$D30/$G30,0),0) -> -5000 | O30: =-IF(O$7>=$E30,IF(O$7<=$F30,$D30/$G30,0),0) -> -5000 | P30: =-IF(P$7>=$E30,IF(P$7<=$F30,$D30/$G30,0),0) -> 0 | Q30: =-IF(Q$7>=$E30,IF(Q$7<=$F30,$D30/$G30,0),0) -> 0 | ... OO30: =-IF(OO$7>=$E30,IF(OO$7<=$F30,$D30/$G30,0),0) -> 0
B31: =Assumptions!B96 -> Appraisal | D31: =Assumptions!C96 -> 10000 | E31: =Assumptions!$C$8 -> 46204 | F31: =EOMONTH(E31,Assumptions!$C$9-1) -> 46387 | G31: =((YEAR(F31)-YEAR(E31))*12+MONTH(F31)-MONTH(E31)+1) -> 6 | J31: =-IF(J$7>=$E31,IF(J$7<=$F31,$D31/$G31,0),0) -> -1666.6667 | K31: =-IF(K$7>=$E31,IF(K$7<=$F31,$D31/$G31,0),0) -> -1666.6667 | L31: =-IF(L$7>=$E31,IF(L$7<=$F31,$D31/$G31,0),0) -> -1666.6667 | M31: =-IF(M$7>=$E31,IF(M$7<=$F31,$D31/$G31,0),0) -> -1666.6667 | N31: =-IF(N$7>=$E31,IF(N$7<=$F31,$D31/$G31,0),0) -> -1666.6667 | O31: =-IF(O$7>=$E31,IF(O$7<=$F31,$D31/$G31,0),0) -> -1666.6667 | P31: =-IF(P$7>=$E31,IF(P$7<=$F31,$D31/$G31,0),0) -> 0 | Q31: =-IF(Q$7>=$E31,IF(Q$7<=$F31,$D31/$G31,0),0) -> 0 | ... OO31: =-IF(OO$7>=$E31,IF(OO$7<=$F31,$D31/$G31,0),0) -> 0
B32: =Assumptions!B97 -> Architect / Engineer | D32: =Assumptions!C97 -> 2400000 | E32: =Assumptions!$C$8 -> 46204 | F32: =EOMONTH(E32,Assumptions!$C$9-1) -> 46387 | G32: =((YEAR(F32)-YEAR(E32))*12+MONTH(F32)-MONTH(E32)+1) -> 6 | J32: =-IF(J$7>=$E32,IF(J$7<=$F32,$D32/$G32,0),0) -> -400000 | K32: =-IF(K$7>=$E32,IF(K$7<=$F32,$D32/$G32,0),0) -> -400000 | L32: =-IF(L$7>=$E32,IF(L$7<=$F32,$D32/$G32,0),0) -> -400000 | M32: =-IF(M$7>=$E32,IF(M$7<=$F32,$D32/$G32,0),0) -> -400000 | N32: =-IF(N$7>=$E32,IF(N$7<=$F32,$D32/$G32,0),0) -> -400000 | O32: =-IF(O$7>=$E32,IF(O$7<=$F32,$D32/$G32,0),0) -> -400000 | P32: =-IF(P$7>=$E32,IF(P$7<=$F32,$D32/$G32,0),0) -> 0 | Q32: =-IF(Q$7>=$E32,IF(Q$7<=$F32,$D32/$G32,0),0) -> 0 | ... OO32: =-IF(OO$7>=$E32,IF(OO$7<=$F32,$D32/$G32,0),0) -> 0
B33: =Assumptions!B98 -> Permits and Expediting | D33: =Assumptions!C98 -> 95000 | E33: =Assumptions!$C$8 -> 46204 | F33: =EOMONTH(E33,Assumptions!$C$9-1) -> 46387 | G33: =((YEAR(F33)-YEAR(E33))*12+MONTH(F33)-MONTH(E33)+1) -> 6 | J33: =-IF(J$7>=$E33,IF(J$7<=$F33,$D33/$G33,0),0) -> -15833.333 | K33: =-IF(K$7>=$E33,IF(K$7<=$F33,$D33/$G33,0),0) -> -15833.333 | L33: =-IF(L$7>=$E33,IF(L$7<=$F33,$D33/$G33,0),0) -> -15833.333 | M33: =-IF(M$7>=$E33,IF(M$7<=$F33,$D33/$G33,0),0) -> -15833.333 | N33: =-IF(N$7>=$E33,IF(N$7<=$F33,$D33/$G33,0),0) -> -15833.333 | O33: =-IF(O$7>=$E33,IF(O$7<=$F33,$D33/$G33,0),0) -> -15833.333 | P33: =-IF(P$7>=$E33,IF(P$7<=$F33,$D33/$G33,0),0) -> 0 | Q33: =-IF(Q$7>=$E33,IF(Q$7<=$F33,$D33/$G33,0),0) -> 0 | ... OO33: =-IF(OO$7>=$E33,IF(OO$7<=$F33,$D33/$G33,0),0) -> 0
B34: =Assumptions!B99 -> Environmental Phase I & II | D34: =Assumptions!C99 -> 35000 | E34: =Assumptions!$C$8 -> 46204 | F34: =EOMONTH(E34,Assumptions!$C$9-1) -> 46387 | G34: =((YEAR(F34)-YEAR(E34))*12+MONTH(F34)-MONTH(E34)+1) -> 6 | J34: =-IF(J$7>=$E34,IF(J$7<=$F34,$D34/$G34,0),0) -> -5833.3333 | K34: =-IF(K$7>=$E34,IF(K$7<=$F34,$D34/$G34,0),0) -> -5833.3333 | L34: =-IF(L$7>=$E34,IF(L$7<=$F34,$D34/$G34,0),0) -> -5833.3333 | M34: =-IF(M$7>=$E34,IF(M$7<=$F34,$D34/$G34,0),0) -> -5833.3333 | N34: =-IF(N$7>=$E34,IF(N$7<=$F34,$D34/$G34,0),0) -> -5833.3333 | O34: =-IF(O$7>=$E34,IF(O$7<=$F34,$D34/$G34,0),0) -> -5833.3333 | P34: =-IF(P$7>=$E34,IF(P$7<=$F34,$D34/$G34,0),0) -> 0 | Q34: =-IF(Q$7>=$E34,IF(Q$7<=$F34,$D34/$G34,0),0) -> 0 | ... OO34: =-IF(OO$7>=$E34,IF(OO$7<=$F34,$D34/$G34,0),0) -> 0
B35: =Assumptions!B100 -> Geotechnical | D35: =Assumptions!C100 -> 0 | E35: =Assumptions!$C$8 -> 46204 | F35: =EOMONTH(E35,Assumptions!$C$9-1) -> 46387 | G35: =((YEAR(F35)-YEAR(E35))*12+MONTH(F35)-MONTH(E35)+1) -> 6 | J35: =-IF(J$7>=$E35,IF(J$7<=$F35,$D35/$G35,0),0) -> 0 | K35: =-IF(K$7>=$E35,IF(K$7<=$F35,$D35/$G35,0),0) -> 0 | L35: =-IF(L$7>=$E35,IF(L$7<=$F35,$D35/$G35,0),0) -> 0 | M35: =-IF(M$7>=$E35,IF(M$7<=$F35,$D35/$G35,0),0) -> 0 | N35: =-IF(N$7>=$E35,IF(N$7<=$F35,$D35/$G35,0),0) -> 0 | O35: =-IF(O$7>=$E35,IF(O$7<=$F35,$D35/$G35,0),0) -> 0 | P35: =-IF(P$7>=$E35,IF(P$7<=$F35,$D35/$G35,0),0) -> 0 | Q35: =-IF(Q$7>=$E35,IF(Q$7<=$F35,$D35/$G35,0),0) -> 0 | ... OO35: =-IF(OO$7>=$E35,IF(OO$7<=$F35,$D35/$G35,0),0) -> 0
B36: =Assumptions!B101 -> Insurance | D36: =Assumptions!C101 -> 1000000 | E36: =Assumptions!$C$8 -> 46204 | F36: =EOMONTH(E36,Assumptions!$C$9-1) -> 46387 | G36: =((YEAR(F36)-YEAR(E36))*12+MONTH(F36)-MONTH(E36)+1) -> 6 | J36: =-IF(J$7>=$E36,IF(J$7<=$F36,$D36/$G36,0),0) -> -166666.67 | K36: =-IF(K$7>=$E36,IF(K$7<=$F36,$D36/$G36,0),0) -> -166666.67 | L36: =-IF(L$7>=$E36,IF(L$7<=$F36,$D36/$G36,0),0) -> -166666.67 | M36: =-IF(M$7>=$E36,IF(M$7<=$F36,$D36/$G36,0),0) -> -166666.67 | N36: =-IF(N$7>=$E36,IF(N$7<=$F36,$D36/$G36,0),0) -> -166666.67 | O36: =-IF(O$7>=$E36,IF(O$7<=$F36,$D36/$G36,0),0) -> -166666.67 | P36: =-IF(P$7>=$E36,IF(P$7<=$F36,$D36/$G36,0),0) -> 0 | Q36: =-IF(Q$7>=$E36,IF(Q$7<=$F36,$D36/$G36,0),0) -> 0 | ... OO36: =-IF(OO$7>=$E36,IF(OO$7<=$F36,$D36/$G36,0),0) -> 0
B37: =Assumptions!B102 -> Market Study | D37: =Assumptions!C102 -> 7500 | E37: =Assumptions!$C$8 -> 46204 | F37: =EOMONTH(E37,Assumptions!$C$9-1) -> 46387 | G37: =((YEAR(F37)-YEAR(E37))*12+MONTH(F37)-MONTH(E37)+1) -> 6 | J37: =-IF(J$7>=$E37,IF(J$7<=$F37,$D37/$G37,0),0) -> -1250 | K37: =-IF(K$7>=$E37,IF(K$7<=$F37,$D37/$G37,0),0) -> -1250 | L37: =-IF(L$7>=$E37,IF(L$7<=$F37,$D37/$G37,0),0) -> -1250 | M37: =-IF(M$7>=$E37,IF(M$7<=$F37,$D37/$G37,0),0) -> -1250 | N37: =-IF(N$7>=$E37,IF(N$7<=$F37,$D37/$G37,0),0) -> -1250 | O37: =-IF(O$7>=$E37,IF(O$7<=$F37,$D37/$G37,0),0) -> -1250 | P37: =-IF(P$7>=$E37,IF(P$7<=$F37,$D37/$G37,0),0) -> 0 | Q37: =-IF(Q$7>=$E37,IF(Q$7<=$F37,$D37/$G37,0),0) -> 0 | ... OO37: =-IF(OO$7>=$E37,IF(OO$7<=$F37,$D37/$G37,0),0) -> 0
B38: =Assumptions!B103 -> Marketing | D38: =Assumptions!C103 -> 329000 | E38: =Assumptions!$C$8 -> 46204 | F38: =EOMONTH(E38,Assumptions!$C$9-1) -> 46387 | G38: =((YEAR(F38)-YEAR(E38))*12+MONTH(F38)-MONTH(E38)+1) -> 6 | J38: =-IF(J$7>=$E38,IF(J$7<=$F38,$D38/$G38,0),0) -> -54833.333 | K38: =-IF(K$7>=$E38,IF(K$7<=$F38,$D38/$G38,0),0) -> -54833.333 | L38: =-IF(L$7>=$E38,IF(L$7<=$F38,$D38/$G38,0),0) -> -54833.333 | M38: =-IF(M$7>=$E38,IF(M$7<=$F38,$D38/$G38,0),0) -> -54833.333 | N38: =-IF(N$7>=$E38,IF(N$7<=$F38,$D38/$G38,0),0) -> -54833.333 | O38: =-IF(O$7>=$E38,IF(O$7<=$F38,$D38/$G38,0),0) -> -54833.333 | P38: =-IF(P$7>=$E38,IF(P$7<=$F38,$D38/$G38,0),0) -> 0 | Q38: =-IF(Q$7>=$E38,IF(Q$7<=$F38,$D38/$G38,0),0) -> 0 | ... OO38: =-IF(OO$7>=$E38,IF(OO$7<=$F38,$D38/$G38,0),0) -> 0
B39: =Assumptions!B104 -> Permits / Fees | D39: =Assumptions!C104 -> 75000 | E39: =Assumptions!$C$8 -> 46204 | F39: =EOMONTH(E39,Assumptions!$C$9-1) -> 46387 | G39: =((YEAR(F39)-YEAR(E39))*12+MONTH(F39)-MONTH(E39)+1) -> 6 | J39: =-IF(J$7>=$E39,IF(J$7<=$F39,$D39/$G39,0),0) -> -12500 | K39: =-IF(K$7>=$E39,IF(K$7<=$F39,$D39/$G39,0),0) -> -12500 | L39: =-IF(L$7>=$E39,IF(L$7<=$F39,$D39/$G39,0),0) -> -12500 | M39: =-IF(M$7>=$E39,IF(M$7<=$F39,$D39/$G39,0),0) -> -12500 | N39: =-IF(N$7>=$E39,IF(N$7<=$F39,$D39/$G39,0),0) -> -12500 | O39: =-IF(O$7>=$E39,IF(O$7<=$F39,$D39/$G39,0),0) -> -12500 | P39: =-IF(P$7>=$E39,IF(P$7<=$F39,$D39/$G39,0),0) -> 0 | Q39: =-IF(Q$7>=$E39,IF(Q$7<=$F39,$D39/$G39,0),0) -> 0 | ... OO39: =-IF(OO$7>=$E39,IF(OO$7<=$F39,$D39/$G39,0),0) -> 0
B40: =Assumptions!B105 -> Survey | D40: =Assumptions!C105 -> 7500 | E40: =Assumptions!$C$8 -> 46204 | F40: =EOMONTH(E40,Assumptions!$C$9-1) -> 46387 | G40: =((YEAR(F40)-YEAR(E40))*12+MONTH(F40)-MONTH(E40)+1) -> 6 | J40: =-IF(J$7>=$E40,IF(J$7<=$F40,$D40/$G40,0),0) -> -1250 | K40: =-IF(K$7>=$E40,IF(K$7<=$F40,$D40/$G40,0),0) -> -1250 | L40: =-IF(L$7>=$E40,IF(L$7<=$F40,$D40/$G40,0),0) -> -1250 | M40: =-IF(M$7>=$E40,IF(M$7<=$F40,$D40/$G40,0),0) -> -1250 | N40: =-IF(N$7>=$E40,IF(N$7<=$F40,$D40/$G40,0),0) -> -1250 | O40: =-IF(O$7>=$E40,IF(O$7<=$F40,$D40/$G40,0),0) -> -1250 | P40: =-IF(P$7>=$E40,IF(P$7<=$F40,$D40/$G40,0),0) -> 0 | Q40: =-IF(Q$7>=$E40,IF(Q$7<=$F40,$D40/$G40,0),0) -> 0 | ... OO40: =-IF(OO$7>=$E40,IF(OO$7<=$F40,$D40/$G40,0),0) -> 0
B41: =Assumptions!B106 -> Borings | D41: =Assumptions!C106 -> 125000 | E41: =Assumptions!$C$8 -> 46204 | F41: =EOMONTH(E41,Assumptions!$C$9-1) -> 46387 | G41: =((YEAR(F41)-YEAR(E41))*12+MONTH(F41)-MONTH(E41)+1) -> 6 | J41: =-IF(J$7>=$E41,IF(J$7<=$F41,$D41/$G41,0),0) -> -20833.333 | K41: =-IF(K$7>=$E41,IF(K$7<=$F41,$D41/$G41,0),0) -> -20833.333 | L41: =-IF(L$7>=$E41,IF(L$7<=$F41,$D41/$G41,0),0) -> -20833.333 | M41: =-IF(M$7>=$E41,IF(M$7<=$F41,$D41/$G41,0),0) -> -20833.333 | N41: =-IF(N$7>=$E41,IF(N$7<=$F41,$D41/$G41,0),0) -> -20833.333 | O41: =-IF(O$7>=$E41,IF(O$7<=$F41,$D41/$G41,0),0) -> -20833.333 | P41: =-IF(P$7>=$E41,IF(P$7<=$F41,$D41/$G41,0),0) -> 0 | Q41: =-IF(Q$7>=$E41,IF(Q$7<=$F41,$D41/$G41,0),0) -> 0 | ... OO41: =-IF(OO$7>=$E41,IF(OO$7<=$F41,$D41/$G41,0),0) -> 0
... B44: =Assumptions!B109 -> Soft Cost Contingency | D44: =Assumptions!C109 -> 1885875.5 | E44: =Assumptions!$C$8 -> 46204 | F44: =EOMONTH(E44,Assumptions!$C$9-1) -> 46387 | G44: =((YEAR(F44)-YEAR(E44))*12+MONTH(F44)-MONTH(E44)+1) -> 6 | J44: =-IF(J$7>=$E44,IF(J$7<=$F44,$D44/$G44,0),0) -> -314312.58 | K44: =-IF(K$7>=$E44,IF(K$7<=$F44,$D44/$G44,0),0) -> -314312.58 | L44: =-IF(L$7>=$E44,IF(L$7<=$F44,$D44/$G44,0),0) -> -314312.58 | M44: =-IF(M$7>=$E44,IF(M$7<=$F44,$D44/$G44,0),0) -> -314312.58 | N44: =-IF(N$7>=$E44,IF(N$7<=$F44,$D44/$G44,0),0) -> -314312.58 | O44: =-IF(O$7>=$E44,IF(O$7<=$F44,$D44/$G44,0),0) -> -314312.58 | P44: =-IF(P$7>=$E44,IF(P$7<=$F44,$D44/$G44,0),0) -> 0 | Q44: =-IF(Q$7>=$E44,IF(Q$7<=$F44,$D44/$G44,0),0) -> 0 | ... OO44: =-IF(OO$7>=$E44,IF(OO$7<=$F44,$D44/$G44,0),0) -> 0
B46: =Assumptions!B113 -> Borrower Legal | D46: =Assumptions!C113 -> 375000 | E46: =Assumptions!$C$8 -> 46204 | F46: =EOMONTH(E46,Assumptions!$C$9-1) -> 46387 | G46: =((YEAR(F46)-YEAR(E46))*12+MONTH(F46)-MONTH(E46)+1) -> 6 | J46: =-IF(J$7>=$E46,IF(J$7<=$F46,$D46/$G46,0),0) -> -62500 | K46: =-IF(K$7>=$E46,IF(K$7<=$F46,$D46/$G46,0),0) -> -62500 | L46: =-IF(L$7>=$E46,IF(L$7<=$F46,$D46/$G46,0),0) -> -62500 | M46: =-IF(M$7>=$E46,IF(M$7<=$F46,$D46/$G46,0),0) -> -62500 | N46: =-IF(N$7>=$E46,IF(N$7<=$F46,$D46/$G46,0),0) -> -62500 | O46: =-IF(O$7>=$E46,IF(O$7<=$F46,$D46/$G46,0),0) -> -62500 | P46: =-IF(P$7>=$E46,IF(P$7<=$F46,$D46/$G46,0),0) -> 0 | Q46: =-IF(Q$7>=$E46,IF(Q$7<=$F46,$D46/$G46,0),0) -> 0 | ... OO46: =-IF(OO$7>=$E46,IF(OO$7<=$F46,$D46/$G46,0),0) -> 0
B47: =Assumptions!B114 -> Bank Legal | D47: =Assumptions!C114 -> 40000 | E47: =Assumptions!$C$8 -> 46204 | F47: =EOMONTH(E47,Assumptions!$C$9-1) -> 46387 | G47: =((YEAR(F47)-YEAR(E47))*12+MONTH(F47)-MONTH(E47)+1) -> 6 | J47: =-IF(J$7>=$E47,IF(J$7<=$F47,$D47/$G47,0),0) -> -6666.6667 | K47: =-IF(K$7>=$E47,IF(K$7<=$F47,$D47/$G47,0),0) -> -6666.6667 | L47: =-IF(L$7>=$E47,IF(L$7<=$F47,$D47/$G47,0),0) -> -6666.6667 | M47: =-IF(M$7>=$E47,IF(M$7<=$F47,$D47/$G47,0),0) -> -6666.6667 | N47: =-IF(N$7>=$E47,IF(N$7<=$F47,$D47/$G47,0),0) -> -6666.6667 | O47: =-IF(O$7>=$E47,IF(O$7<=$F47,$D47/$G47,0),0) -> -6666.6667 | P47: =-IF(P$7>=$E47,IF(P$7<=$F47,$D47/$G47,0),0) -> 0 | Q47: =-IF(Q$7>=$E47,IF(Q$7<=$F47,$D47/$G47,0),0) -> 0 | ... OO47: =-IF(OO$7>=$E47,IF(OO$7<=$F47,$D47/$G47,0),0) -> 0
B48: =Assumptions!B115 -> Tax Credit Certification | D48: =Assumptions!C115 -> 421496 | E48: =Assumptions!$C$8 -> 46204 | F48: =EOMONTH(E48,Assumptions!$C$9-1) -> 46387 | G48: =((YEAR(F48)-YEAR(E48))*12+MONTH(F48)-MONTH(E48)+1) -> 6 | J48: =-IF(J$7>=$E48,IF(J$7<=$F48,$D48/$G48,0),0) -> -70249.333 | K48: =-IF(K$7>=$E48,IF(K$7<=$F48,$D48/$G48,0),0) -> -70249.333 | L48: =-IF(L$7>=$E48,IF(L$7<=$F48,$D48/$G48,0),0) -> -70249.333 | M48: =-IF(M$7>=$E48,IF(M$7<=$F48,$D48/$G48,0),0) -> -70249.333 | N48: =-IF(N$7>=$E48,IF(N$7<=$F48,$D48/$G48,0),0) -> -70249.333 | O48: =-IF(O$7>=$E48,IF(O$7<=$F48,$D48/$G48,0),0) -> -70249.333 | P48: =-IF(P$7>=$E48,IF(P$7<=$F48,$D48/$G48,0),0) -> 0 | Q48: =-IF(Q$7>=$E48,IF(Q$7<=$F48,$D48/$G48,0),0) -> 0 | ... OO48: =-IF(OO$7>=$E48,IF(OO$7<=$F48,$D48/$G48,0),0) -> 0
B50: Total Hard & Soft Cost | D50: =SUM(D17:D48) -> 2.1397548e+08 | J50: =SUM(J17:J48) -> -1283846.6 | K50: =SUM(K17:K48) -> -1283846.6 | L50: =SUM(L17:L48) -> -1283846.6 | M50: =SUM(M17:M48) -> -1283846.6 | N50: =SUM(N17:N48) -> -1283846.6 | O50: =SUM(O17:O48) -> -1283846.6 | P50: =SUM(P17:P48) -> -8594683.3 | Q50: =SUM(Q17:Q48) -> -8594683.3 | ... OO50: =SUM(OO17:OO48) -> 0
B52: Finance Cost
B53: Construction Interest: Bonds | D53: =Assumptions!C123 -> 20076858 | E53: =Assumptions!$C$10 -> 46418 | F53: =EOMONTH(E53,SUM(Assumptions!$C$11:$C$12)-1) -> 47299 | G53: =((YEAR(F53)-YEAR(E53))*12+MONTH(F53)-MONTH(E53)+1) -> 30 | J53: =-IF(J$7>=$E53,IF(J$7<=$F53,($D53/12),0),0) -> 0 | K53: =-IF(K$7>=$E53,IF(K$7<=$F53,($D53/12),0),0) -> 0 | L53: =-IF(L$7>=$E53,IF(L$7<=$F53,($D53/12),0),0) -> 0 | M53: =-IF(M$7>=$E53,IF(M$7<=$F53,($D53/12),0),0) -> 0 | N53: =-IF(N$7>=$E53,IF(N$7<=$F53,($D53/12),0),0) -> 0 | O53: =-IF(O$7>=$E53,IF(O$7<=$F53,($D53/12),0),0) -> 0 | P53: =-IF(P$7>=$E53,IF(P$7<=$F53,($D53/12),0),0) -> -1673071.5 | Q53: =-IF(Q$7>=$E53,IF(Q$7<=$F53,($D53/12),0),0) -> -1673071.5 | ... OO53: =-IF(OO$7>=$E53,IF(OO$7<=$F53,($D53/12),0),0) -> 0
B54: Construction Interest: Subsidy Loan NCF | D54: =Assumptions!C124 -> 590400 | E54: =Assumptions!$C$10 -> 46418 | F54: =EOMONTH(E54,SUM(Assumptions!$C$11:$C$12)-1) -> 47299 | G54: =((YEAR(F54)-YEAR(E54))*12+MONTH(F54)-MONTH(E54)+1) -> 30 | J54: =-IF(J$7>=$E54,IF(J$7<=$F54,($D54/12),0),0) -> 0 | K54: =-IF(K$7>=$E54,IF(K$7<=$F54,($D54/12),0),0) -> 0 | L54: =-IF(L$7>=$E54,IF(L$7<=$F54,($D54/12),0),0) -> 0 | M54: =-IF(M$7>=$E54,IF(M$7<=$F54,($D54/12),0),0) -> 0 | N54: =-IF(N$7>=$E54,IF(N$7<=$F54,($D54/12),0),0) -> 0 | O54: =-IF(O$7>=$E54,IF(O$7<=$F54,($D54/12),0),0) -> 0 | P54: =-IF(P$7>=$E54,IF(P$7<=$F54,($D54/12),0),0) -> -49200 | Q54: =-IF(Q$7>=$E54,IF(Q$7<=$F54,($D54/12),0),0) -> -49200 | ... OO54: =-IF(OO$7>=$E54,IF(OO$7<=$F54,($D54/12),0),0) -> 0
B55: Lender LC Origination Fee | D55: =Assumptions!C125 -> 1828895.9 | E55: =Assumptions!$C$8 -> 46204 | F55: =EOMONTH(E55,Assumptions!$C$9-1) -> 46387 | G55: =((YEAR(F55)-YEAR(E55))*12+MONTH(F55)-MONTH(E55)+1) -> 6 | J55: =-IF(J$7>=$E55,IF(J$7<=$F55,$D55/$G55,0),0) -> -304815.98 | K55: =-IF(K$7>=$E55,IF(K$7<=$F55,$D55/$G55,0),0) -> -304815.98 | L55: =-IF(L$7>=$E55,IF(L$7<=$F55,$D55/$G55,0),0) -> -304815.98 | M55: =-IF(M$7>=$E55,IF(M$7<=$F55,$D55/$G55,0),0) -> -304815.98 | N55: =-IF(N$7>=$E55,IF(N$7<=$F55,$D55/$G55,0),0) -> -304815.98 | O55: =-IF(O$7>=$E55,IF(O$7<=$F55,$D55/$G55,0),0) -> -304815.98 | P55: =-IF(P$7>=$E55,IF(P$7<=$F55,$D55/$G55,0),0) -> 0 | Q55: =-IF(Q$7>=$E55,IF(Q$7<=$F55,$D55/$G55,0),0) -> 0 | ... OO55: =-IF(OO$7>=$E55,IF(OO$7<=$F55,$D55/$G55,0),0) -> 0
B56: Lender LC Annual Fee | D56: =Assumptions!C126 -> 5029463.7 | E56: =Assumptions!$C$8 -> 46204 | F56: =EOMONTH(E56,Assumptions!$C$9-1) -> 46387 | G56: =((YEAR(F56)-YEAR(E56))*12+MONTH(F56)-MONTH(E56)+1) -> 6 | J56: =-IF(J$7>=$E56,IF(J$7<=$F56,$D56/$G56,0),0) -> -838243.95 | K56: =-IF(K$7>=$E56,IF(K$7<=$F56,$D56/$G56,0),0) -> -838243.95 | L56: =-IF(L$7>=$E56,IF(L$7<=$F56,$D56/$G56,0),0) -> -838243.95 | M56: =-IF(M$7>=$E56,IF(M$7<=$F56,$D56/$G56,0),0) -> -838243.95 | N56: =-IF(N$7>=$E56,IF(N$7<=$F56,$D56/$G56,0),0) -> -838243.95 | O56: =-IF(O$7>=$E56,IF(O$7<=$F56,$D56/$G56,0),0) -> -838243.95 | P56: =-IF(P$7>=$E56,IF(P$7<=$F56,$D56/$G56,0),0) -> 0 | Q56: =-IF(Q$7>=$E56,IF(Q$7<=$F56,$D56/$G56,0),0) -> 0 | ... OO56: =-IF(OO$7>=$E56,IF(OO$7<=$F56,$D56/$G56,0),0) -> 0
B57: =Assumptions!B129 -> HFA Bond Issuance & Closing Fees | D57: =Assumptions!C142 -> 5330453.9 | E57: =Assumptions!$C$8 -> 46204 | F57: =EOMONTH(E57,Assumptions!$C$9-1) -> 46387 | G57: =((YEAR(F57)-YEAR(E57))*12+MONTH(F57)-MONTH(E57)+1) -> 6 | J57: =-IF(J$7>=$E57,IF(J$7<=$F57,$D57/$G57,0),0) -> -888408.99 | K57: =-IF(K$7>=$E57,IF(K$7<=$F57,$D57/$G57,0),0) -> -888408.99 | L57: =-IF(L$7>=$E57,IF(L$7<=$F57,$D57/$G57,0),0) -> -888408.99 | M57: =-IF(M$7>=$E57,IF(M$7<=$F57,$D57/$G57,0),0) -> -888408.99 | N57: =-IF(N$7>=$E57,IF(N$7<=$F57,$D57/$G57,0),0) -> -888408.99 | O57: =-IF(O$7>=$E57,IF(O$7<=$F57,$D57/$G57,0),0) -> -888408.99 | P57: =-IF(P$7>=$E57,IF(P$7<=$F57,$D57/$G57,0),0) -> 0 | Q57: =-IF(Q$7>=$E57,IF(Q$7<=$F57,$D57/$G57,0),0) -> 0 | ... OO57: =-IF(OO$7>=$E57,IF(OO$7<=$F57,$D57/$G57,0),0) -> 0
B58: Total Finance Cost | D58: =SUM(D53:D57) -> 32856072 | J58: =SUM(J53:J57) -> -2031468.9 | K58: =SUM(K53:K57) -> -2031468.9 | L58: =SUM(L53:L57) -> -2031468.9 | M58: =SUM(M53:M57) -> -2031468.9 | N58: =SUM(N53:N57) -> -2031468.9 | O58: =SUM(O53:O57) -> -2031468.9 | P58: =SUM(P53:P57) -> -1722271.5 | Q58: =SUM(Q53:Q57) -> -1722271.5 | ... OO58: =SUM(OO53:OO57) -> 0
B60: =Assumptions!B146 -> Capitalized Operating Reserve | D60: =Assumptions!C148 -> 1949898.8 | E60: =EOMONTH(Assumptions!C10,SUM(Assumptions!C11:C12,-1)) -> 47299 | F60: =E60 -> 47299 | G60: =((YEAR(F60)-YEAR(E60))*12+MONTH(F60)-MONTH(E60)+1) -> 1 | J60: =-IF(J$7>=$E60,IF(J$7<=$F60,$D60/$G60,0),0) -> 0 | K60: =-IF(K$7>=$E60,IF(K$7<=$F60,$D60/$G60,0),0) -> 0 | L60: =-IF(L$7>=$E60,IF(L$7<=$F60,$D60/$G60,0),0) -> 0 | M60: =-IF(M$7>=$E60,IF(M$7<=$F60,$D60/$G60,0),0) -> 0 | N60: =-IF(N$7>=$E60,IF(N$7<=$F60,$D60/$G60,0),0) -> 0 | O60: =-IF(O$7>=$E60,IF(O$7<=$F60,$D60/$G60,0),0) -> 0 | P60: =-IF(P$7>=$E60,IF(P$7<=$F60,$D60/$G60,0),0) -> 0 | Q60: =-IF(Q$7>=$E60,IF(Q$7<=$F60,$D60/$G60,0),0) -> 0 | ... OO60: =-IF(OO$7>=$E60,IF(OO$7<=$F60,$D60/$G60,0),0) -> 0
B62: Total Development Cost | I62: =SUM(J62:OO62) -> -2.7978234e+08 | J62: =SUM(J58,J14,J50,J60) -> -3315316.6 | K62: =SUM(K58,K14,K50,K60) -> -3315315.6 | L62: =SUM(L58,L14,L50,L60) -> -3315315.6 | M62: =SUM(M58,M14,M50,M60) -> -3315315.6 | N62: =SUM(N58,N14,N50,N60) -> -3315315.6 | O62: =SUM(O58,O14,O50,O60) -> -3315315.6 | P62: =SUM(P58,P14,P50,P60) -> -10316955 | Q62: =SUM(Q58,Q14,Q50,Q60) -> -10316955 | ... OO62: =SUM(OO58,OO14,OO50,OO60) -> 0
B64: POST DEVELOPMENT PHASE
C65: Inflation Rate (%)
B66: Potential Gross Income
B67: Total Annual Rental Income | C67: 0.02 | D67: =Mortgage!D5 -> 7752009.3 | E67: =Assumptions!$C$13 -> 47330 | F67: =EOMONTH(E67,Assumptions!$C$14-1) -> 58256 | G67: =((YEAR(F67)-YEAR(E67))*12+MONTH(F67)-MONTH(E67)+1) -> 360 | J67: =IF(J$7>=$E67,IF(J$7<=$F67,(($D67*(1+$C67)^(IF(J$7>=$E67,J$6-YEAR($E67),0)))/12),0),0) -> 0 | K67: =IF(K$7>=$E67,IF(K$7<=$F67,(($D67*(1+$C67)^(IF(K$7>=$E67,K$6-YEAR($E67),0)))/12),0),0) -> 0 | L67: =IF(L$7>=$E67,IF(L$7<=$F67,(($D67*(1+$C67)^(IF(L$7>=$E67,L$6-YEAR($E67),0)))/12),0),0) -> 0 | M67: =IF(M$7>=$E67,IF(M$7<=$F67,(($D67*(1+$C67)^(IF(M$7>=$E67,M$6-YEAR($E67),0)))/12),0),0) -> 0 | N67: =IF(N$7>=$E67,IF(N$7<=$F67,(($D67*(1+$C67)^(IF(N$7>=$E67,N$6-YEAR($E67),0)))/12),0),0) -> 0 | O67: =IF(O$7>=$E67,IF(O$7<=$F67,(($D67*(1+$C67)^(IF(O$7>=$E67,O$6-YEAR($E67),0)))/12),0),0) -> 0 | P67: =IF(P$7>=$E67,IF(P$7<=$F67,(($D67*(1+$C67)^(IF(P$7>=$E67,P$6-YEAR($E67),0)))/12),0),0) -> 0 | Q67: =IF(Q$7>=$E67,IF(Q$7<=$F67,(($D67*(1+$C67)^(IF(Q$7>=$E67,Q$6-YEAR($E67),0)))/12),0),0) -> 0 | ... OO67: =IF(OO$7>=$E67,IF(OO$7<=$F67,(($D67*(1+$C67)^(IF(OO$7>=$E67,OO$6-YEAR($E67),0)))/12),0),0) -> 1170141
B68: Parking | C68: 0.02 | D68: =Mortgage!D6 -> 45000 | E68: =Assumptions!$C$13 -> 47330 | F68: =EOMONTH(E68,Assumptions!$C$14-1) -> 58256 | G68: =((YEAR(F68)-YEAR(E68))*12+MONTH(F68)-MONTH(E68)+1) -> 360 | J68: =IF(J$7>=$E68,IF(J$7<=$F68,(($D68*(1+$C68)^(IF(J$7>=$E68,J$6-YEAR($E68),0)))/12),0),0) -> 0 | K68: =IF(K$7>=$E68,IF(K$7<=$F68,(($D68*(1+$C68)^(IF(K$7>=$E68,K$6-YEAR($E68),0)))/12),0),0) -> 0 | L68: =IF(L$7>=$E68,IF(L$7<=$F68,(($D68*(1+$C68)^(IF(L$7>=$E68,L$6-YEAR($E68),0)))/12),0),0) -> 0 | M68: =IF(M$7>=$E68,IF(M$7<=$F68,(($D68*(1+$C68)^(IF(M$7>=$E68,M$6-YEAR($E68),0)))/12),0),0) -> 0 | N68: =IF(N$7>=$E68,IF(N$7<=$F68,(($D68*(1+$C68)^(IF(N$7>=$E68,N$6-YEAR($E68),0)))/12),0),0) -> 0 | O68: =IF(O$7>=$E68,IF(O$7<=$F68,(($D68*(1+$C68)^(IF(O$7>=$E68,O$6-YEAR($E68),0)))/12),0),0) -> 0 | P68: =IF(P$7>=$E68,IF(P$7<=$F68,(($D68*(1+$C68)^(IF(P$7>=$E68,P$6-YEAR($E68),0)))/12),0),0) -> 0 | Q68: =IF(Q$7>=$E68,IF(Q$7<=$F68,(($D68*(1+$C68)^(IF(Q$7>=$E68,Q$6-YEAR($E68),0)))/12),0),0) -> 0 | ... OO68: =IF(OO$7>=$E68,IF(OO$7<=$F68,(($D68*(1+$C68)^(IF(OO$7>=$E68,OO$6-YEAR($E68),0)))/12),0),0) -> 6792.6059
B69: Commercial | C69: 0.02 | D69: =Mortgage!D7 -> 0 | E69: =Assumptions!$C$13 -> 47330 | F69: =EOMONTH(E69,Assumptions!$C$14-1) -> 58256 | G69: =((YEAR(F69)-YEAR(E69))*12+MONTH(F69)-MONTH(E69)+1) -> 360 | J69: =IF(J$7>=$E69,IF(J$7<=$F69,(($D69*(1+$C69)^(IF(J$7>=$E69,J$6-YEAR($E69),0)))/12),0),0) -> 0 | K69: =IF(K$7>=$E69,IF(K$7<=$F69,(($D69*(1+$C69)^(IF(K$7>=$E69,K$6-YEAR($E69),0)))/12),0),0) -> 0 | L69: =IF(L$7>=$E69,IF(L$7<=$F69,(($D69*(1+$C69)^(IF(L$7>=$E69,L$6-YEAR($E69),0)))/12),0),0) -> 0 | M69: =IF(M$7>=$E69,IF(M$7<=$F69,(($D69*(1+$C69)^(IF(M$7>=$E69,M$6-YEAR($E69),0)))/12),0),0) -> 0 | N69: =IF(N$7>=$E69,IF(N$7<=$F69,(($D69*(1+$C69)^(IF(N$7>=$E69,N$6-YEAR($E69),0)))/12),0),0) -> 0 | O69: =IF(O$7>=$E69,IF(O$7<=$F69,(($D69*(1+$C69)^(IF(O$7>=$E69,O$6-YEAR($E69),0)))/12),0),0) -> 0 | P69: =IF(P$7>=$E69,IF(P$7<=$F69,(($D69*(1+$C69)^(IF(P$7>=$E69,P$6-YEAR($E69),0)))/12),0),0) -> 0 | Q69: =IF(Q$7>=$E69,IF(Q$7<=$F69,(($D69*(1+$C69)^(IF(Q$7>=$E69,Q$6-YEAR($E69),0)))/12),0),0) -> 0 | ... OO69: =IF(OO$7>=$E69,IF(OO$7<=$F69,(($D69*(1+$C69)^(IF(OO$7>=$E69,OO$6-YEAR($E69),0)))/12),0),0) -> 0
B70: Community Facility | C70: 0.02 | D70: =Mortgage!D8 -> 0 | E70: =Assumptions!$C$13 -> 47330 | F70: =EOMONTH(E70,Assumptions!$C$14-1) -> 58256 | G70: =((YEAR(F70)-YEAR(E70))*12+MONTH(F70)-MONTH(E70)+1) -> 360 | J70: =IF(J$7>=$E70,IF(J$7<=$F70,(($D70*(1+$C70)^(IF(J$7>=$E70,J$6-YEAR($E70),0)))/12),0),0) -> 0 | K70: =IF(K$7>=$E70,IF(K$7<=$F70,(($D70*(1+$C70)^(IF(K$7>=$E70,K$6-YEAR($E70),0)))/12),0),0) -> 0 | L70: =IF(L$7>=$E70,IF(L$7<=$F70,(($D70*(1+$C70)^(IF(L$7>=$E70,L$6-YEAR($E70),0)))/12),0),0) -> 0 | M70: =IF(M$7>=$E70,IF(M$7<=$F70,(($D70*(1+$C70)^(IF(M$7>=$E70,M$6-YEAR($E70),0)))/12),0),0) -> 0 | N70: =IF(N$7>=$E70,IF(N$7<=$F70,(($D70*(1+$C70)^(IF(N$7>=$E70,N$6-YEAR($E70),0)))/12),0),0) -> 0 | O70: =IF(O$7>=$E70,IF(O$7<=$F70,(($D70*(1+$C70)^(IF(O$7>=$E70,O$6-YEAR($E70),0)))/12),0),0) -> 0 | P70: =IF(P$7>=$E70,IF(P$7<=$F70,(($D70*(1+$C70)^(IF(P$7>=$E70,P$6-YEAR($E70),0)))/12),0),0) -> 0 | Q70: =IF(Q$7>=$E70,IF(Q$7<=$F70,(($D70*(1+$C70)^(IF(Q$7>=$E70,Q$6-YEAR($E70),0)))/12),0),0) -> 0 | ... OO70: =IF(OO$7>=$E70,IF(OO$7<=$F70,(($D70*(1+$C70)^(IF(OO$7>=$E70,OO$6-YEAR($E70),0)))/12),0),0) -> 0
B71: Laundry | C71: 0.02 | D71: =Mortgage!D9 -> 39480 | E71: =Assumptions!$C$13 -> 47330 | F71: =EOMONTH(E71,Assumptions!$C$14-1) -> 58256 | G71: =((YEAR(F71)-YEAR(E71))*12+MONTH(F71)-MONTH(E71)+1) -> 360 | J71: =IF(J$7>=$E71,IF(J$7<=$F71,(($D71*(1+$C71)^(IF(J$7>=$E71,J$6-YEAR($E71),0)))/12),0),0) -> 0 | K71: =IF(K$7>=$E71,IF(K$7<=$F71,(($D71*(1+$C71)^(IF(K$7>=$E71,K$6-YEAR($E71),0)))/12),0),0) -> 0 | L71: =IF(L$7>=$E71,IF(L$7<=$F71,(($D71*(1+$C71)^(IF(L$7>=$E71,L$6-YEAR($E71),0)))/12),0),0) -> 0 | M71: =IF(M$7>=$E71,IF(M$7<=$F71,(($D71*(1+$C71)^(IF(M$7>=$E71,M$6-YEAR($E71),0)))/12),0),0) -> 0 | N71: =IF(N$7>=$E71,IF(N$7<=$F71,(($D71*(1+$C71)^(IF(N$7>=$E71,N$6-YEAR($E71),0)))/12),0),0) -> 0 | O71: =IF(O$7>=$E71,IF(O$7<=$F71,(($D71*(1+$C71)^(IF(O$7>=$E71,O$6-YEAR($E71),0)))/12),0),0) -> 0 | P71: =IF(P$7>=$E71,IF(P$7<=$F71,(($D71*(1+$C71)^(IF(P$7>=$E71,P$6-YEAR($E71),0)))/12),0),0) -> 0 | Q71: =IF(Q$7>=$E71,IF(Q$7<=$F71,(($D71*(1+$C71)^(IF(Q$7>=$E71,Q$6-YEAR($E71),0)))/12),0),0) -> 0 | ... OO71: =IF(OO$7>=$E71,IF(OO$7<=$F71,(($D71*(1+$C71)^(IF(OO$7>=$E71,OO$6-YEAR($E71),0)))/12),0),0) -> 5959.3796
B72: Total Potential Gross Income | J72: =SUM(J67:J71) -> 0 | K72: =SUM(K67:K71) -> 0 | L72: =SUM(L67:L71) -> 0 | M72: =SUM(M67:M71) -> 0 | N72: =SUM(N67:N71) -> 0 | O72: =SUM(O67:O71) -> 0 | P72: =SUM(P67:P71) -> 0 | Q72: =SUM(Q67:Q71) -> 0 | ... OO72: =SUM(OO67:OO71) -> 1182893
B74: Vacancy Allowance
B75: Total Annual Rental Income | D75: =Mortgage!D13 -> -387600.46 | E75: =Assumptions!$C$13 -> 47330 | F75: =EOMONTH(E75,Assumptions!$C$14-1) -> 58256 | G75: =((YEAR(F75)-YEAR(E75))*12+MONTH(F75)-MONTH(E75)+1) -> 360 | J75: =IF(J$7>=$E75,IF(J$7<=$F75,($D75/12),0),0) -> 0 | K75: =IF(K$7>=$E75,IF(K$7<=$F75,($D75/12),0),0) -> 0 | L75: =IF(L$7>=$E75,IF(L$7<=$F75,($D75/12),0),0) -> 0 | M75: =IF(M$7>=$E75,IF(M$7<=$F75,($D75/12),0),0) -> 0 | N75: =IF(N$7>=$E75,IF(N$7<=$F75,($D75/12),0),0) -> 0 | O75: =IF(O$7>=$E75,IF(O$7<=$F75,($D75/12),0),0) -> 0 | P75: =IF(P$7>=$E75,IF(P$7<=$F75,($D75/12),0),0) -> 0 | Q75: =IF(Q$7>=$E75,IF(Q$7<=$F75,($D75/12),0),0) -> 0 | ... OO75: =IF(OO$7>=$E75,IF(OO$7<=$F75,($D75/12),0),0) -> -32300.039
B76: Parking | D76: =Mortgage!D14 -> -2250 | E76: =Assumptions!$C$13 -> 47330 | F76: =EOMONTH(E76,Assumptions!$C$14-1) -> 58256 | G76: =((YEAR(F76)-YEAR(E76))*12+MONTH(F76)-MONTH(E76)+1) -> 360 | J76: =IF(J$7>=$E76,IF(J$7<=$F76,($D76/12),0),0) -> 0 | K76: =IF(K$7>=$E76,IF(K$7<=$F76,($D76/12),0),0) -> 0 | L76: =IF(L$7>=$E76,IF(L$7<=$F76,($D76/12),0),0) -> 0 | M76: =IF(M$7>=$E76,IF(M$7<=$F76,($D76/12),0),0) -> 0 | N76: =IF(N$7>=$E76,IF(N$7<=$F76,($D76/12),0),0) -> 0 | O76: =IF(O$7>=$E76,IF(O$7<=$F76,($D76/12),0),0) -> 0 | P76: =IF(P$7>=$E76,IF(P$7<=$F76,($D76/12),0),0) -> 0 | Q76: =IF(Q$7>=$E76,IF(Q$7<=$F76,($D76/12),0),0) -> 0 | ... OO76: =IF(OO$7>=$E76,IF(OO$7<=$F76,($D76/12),0),0) -> -187.5
B77: Commercial | D77: =Mortgage!D15 -> 0 | E77: =Assumptions!$C$13 -> 47330 | F77: =EOMONTH(E77,Assumptions!$C$14-1) -> 58256 | G77: =((YEAR(F77)-YEAR(E77))*12+MONTH(F77)-MONTH(E77)+1) -> 360 | J77: =IF(J$7>=$E77,IF(J$7<=$F77,($D77/12),0),0) -> 0 | K77: =IF(K$7>=$E77,IF(K$7<=$F77,($D77/12),0),0) -> 0 | L77: =IF(L$7>=$E77,IF(L$7<=$F77,($D77/12),0),0) -> 0 | M77: =IF(M$7>=$E77,IF(M$7<=$F77,($D77/12),0),0) -> 0 | N77: =IF(N$7>=$E77,IF(N$7<=$F77,($D77/12),0),0) -> 0 | O77: =IF(O$7>=$E77,IF(O$7<=$F77,($D77/12),0),0) -> 0 | P77: =IF(P$7>=$E77,IF(P$7<=$F77,($D77/12),0),0) -> 0 | Q77: =IF(Q$7>=$E77,IF(Q$7<=$F77,($D77/12),0),0) -> 0 | ... OO77: =IF(OO$7>=$E77,IF(OO$7<=$F77,($D77/12),0),0) -> 0
B78: Community Facility | D78: =Mortgage!D16 -> 0 | E78: =Assumptions!$C$13 -> 47330 | F78: =EOMONTH(E78,Assumptions!$C$14-1) -> 58256 | G78: =((YEAR(F78)-YEAR(E78))*12+MONTH(F78)-MONTH(E78)+1) -> 360 | J78: =IF(J$7>=$E78,IF(J$7<=$F78,($D78/12),0),0) -> 0 | K78: =IF(K$7>=$E78,IF(K$7<=$F78,($D78/12),0),0) -> 0 | L78: =IF(L$7>=$E78,IF(L$7<=$F78,($D78/12),0),0) -> 0 | M78: =IF(M$7>=$E78,IF(M$7<=$F78,($D78/12),0),0) -> 0 | N78: =IF(N$7>=$E78,IF(N$7<=$F78,($D78/12),0),0) -> 0 | O78: =IF(O$7>=$E78,IF(O$7<=$F78,($D78/12),0),0) -> 0 | P78: =IF(P$7>=$E78,IF(P$7<=$F78,($D78/12),0),0) -> 0 | Q78: =IF(Q$7>=$E78,IF(Q$7<=$F78,($D78/12),0),0) -> 0 | ... OO78: =IF(OO$7>=$E78,IF(OO$7<=$F78,($D78/12),0),0) -> 0
B79: Laundry | D79: =Mortgage!D17 -> -3948 | E79: =Assumptions!$C$13 -> 47330 | F79: =EOMONTH(E79,Assumptions!$C$14-1) -> 58256 | G79: =((YEAR(F79)-YEAR(E79))*12+MONTH(F79)-MONTH(E79)+1) -> 360 | J79: =IF(J$7>=$E79,IF(J$7<=$F79,($D79/12),0),0) -> 0 | K79: =IF(K$7>=$E79,IF(K$7<=$F79,($D79/12),0),0) -> 0 | L79: =IF(L$7>=$E79,IF(L$7<=$F79,($D79/12),0),0) -> 0 | M79: =IF(M$7>=$E79,IF(M$7<=$F79,($D79/12),0),0) -> 0 | N79: =IF(N$7>=$E79,IF(N$7<=$F79,($D79/12),0),0) -> 0 | O79: =IF(O$7>=$E79,IF(O$7<=$F79,($D79/12),0),0) -> 0 | P79: =IF(P$7>=$E79,IF(P$7<=$F79,($D79/12),0),0) -> 0 | Q79: =IF(Q$7>=$E79,IF(Q$7<=$F79,($D79/12),0),0) -> 0 | ... OO79: =IF(OO$7>=$E79,IF(OO$7<=$F79,($D79/12),0),0) -> -329
B80: Total Vacancy Allowance | J80: =SUM(J75:J79) -> 0 | K80: =SUM(K75:K79) -> 0 | L80: =SUM(L75:L79) -> 0 | M80: =SUM(M75:M79) -> 0 | N80: =SUM(N75:N79) -> 0 | O80: =SUM(O75:O79) -> 0 | P80: =SUM(P75:P79) -> 0 | Q80: =SUM(Q75:Q79) -> 0 | ... OO80: =SUM(OO75:OO79) -> -32816.539
B82: Effective Gross Income
B83: Total Annual Rental Income | D83: =D67+D75 -> 7364408.8 | E83: =Assumptions!$C$13 -> 47330 | F83: =EOMONTH(E83,Assumptions!$C$14-1) -> 58256 | G83: =((YEAR(F83)-YEAR(E83))*12+MONTH(F83)-MONTH(E83)+1) -> 360 | J83: =J67+J75 -> 0 | K83: =K67+K75 -> 0 | L83: =L67+L75 -> 0 | M83: =M67+M75 -> 0 | N83: =N67+N75 -> 0 | O83: =O67+O75 -> 0 | P83: =P67+P75 -> 0 | Q83: =Q67+Q75 -> 0 | ... OO83: =OO67+OO75 -> 1137840.9
B84: Parking | D84: =D68+D76 -> 42750 | E84: =Assumptions!$C$13 -> 47330 | F84: =EOMONTH(E84,Assumptions!$C$14-1) -> 58256 | G84: =((YEAR(F84)-YEAR(E84))*12+MONTH(F84)-MONTH(E84)+1) -> 360 | J84: =J68+J76 -> 0 | K84: =K68+K76 -> 0 | L84: =L68+L76 -> 0 | M84: =M68+M76 -> 0 | N84: =N68+N76 -> 0 | O84: =O68+O76 -> 0 | P84: =P68+P76 -> 0 | Q84: =Q68+Q76 -> 0 | ... OO84: =OO68+OO76 -> 6605.1059
B85: Commercial | D85: =D69+D77 -> 0 | E85: =Assumptions!$C$13 -> 47330 | F85: =EOMONTH(E85,Assumptions!$C$14-1) -> 58256 | G85: =((YEAR(F85)-YEAR(E85))*12+MONTH(F85)-MONTH(E85)+1) -> 360 | J85: =J69+J77 -> 0 | K85: =K69+K77 -> 0 | L85: =L69+L77 -> 0 | M85: =M69+M77 -> 0 | N85: =N69+N77 -> 0 | O85: =O69+O77 -> 0 | P85: =P69+P77 -> 0 | Q85: =Q69+Q77 -> 0 | ... OO85: =OO69+OO77 -> 0
B86: Community Facility | D86: =D70+D78 -> 0 | E86: =Assumptions!$C$13 -> 47330 | F86: =EOMONTH(E86,Assumptions!$C$14-1) -> 58256 | G86: =((YEAR(F86)-YEAR(E86))*12+MONTH(F86)-MONTH(E86)+1) -> 360 | J86: =J70+J78 -> 0 | K86: =K70+K78 -> 0 | L86: =L70+L78 -> 0 | M86: =M70+M78 -> 0 | N86: =N70+N78 -> 0 | O86: =O70+O78 -> 0 | P86: =P70+P78 -> 0 | Q86: =Q70+Q78 -> 0 | ... OO86: =OO70+OO78 -> 0
B87: Laundry | D87: =D71+D79 -> 35532 | E87: =Assumptions!$C$13 -> 47330 | F87: =EOMONTH(E87,Assumptions!$C$14-1) -> 58256 | G87: =((YEAR(F87)-YEAR(E87))*12+MONTH(F87)-MONTH(E87)+1) -> 360 | J87: =J71+J79 -> 0 | K87: =K71+K79 -> 0 | L87: =L71+L79 -> 0 | M87: =M71+M79 -> 0 | N87: =N71+N79 -> 0 | O87: =O71+O79 -> 0 | P87: =P71+P79 -> 0 | Q87: =Q71+Q79 -> 0 | ... OO87: =OO71+OO79 -> 5630.3796
B88: Effective Gross Income: | J88: =SUM(J83:J87) -> 0 | K88: =SUM(K83:K87) -> 0 | L88: =SUM(L83:L87) -> 0 | M88: =SUM(M83:M87) -> 0 | N88: =SUM(N83:N87) -> 0 | O88: =SUM(O83:O87) -> 0 | P88: =SUM(P83:P87) -> 0 | Q88: =SUM(Q83:Q87) -> 0 | ... OO88: =SUM(OO83:OO87) -> 1150076.4
B90: Maintenance & Operating Expenses
B91: Operating Expenses: | C91: 0.03 | D91: =-'Operating Expenses & Reserves'!F37 -> -2745482 | E91: =Assumptions!$C$13 -> 47330 | F91: =EOMONTH(E91,Assumptions!$C$14-1) -> 58256 | G91: =((YEAR(F91)-YEAR(E91))*12+MONTH(F91)-MONTH(E91)+1) -> 360 | J91: =IF(J$7>=$E91,IF(J$7<=$F91,(($D91*(1+$C91)^(IF(J$7>=$E91,J$6-YEAR($E91),0)))/12),0),0) -> 0 | K91: =IF(K$7>=$E91,IF(K$7<=$F91,(($D91*(1+$C91)^(IF(K$7>=$E91,K$6-YEAR($E91),0)))/12),0),0) -> 0 | L91: =IF(L$7>=$E91,IF(L$7<=$F91,(($D91*(1+$C91)^(IF(L$7>=$E91,L$6-YEAR($E91),0)))/12),0),0) -> 0 | M91: =IF(M$7>=$E91,IF(M$7<=$F91,(($D91*(1+$C91)^(IF(M$7>=$E91,M$6-YEAR($E91),0)))/12),0),0) -> 0 | N91: =IF(N$7>=$E91,IF(N$7<=$F91,(($D91*(1+$C91)^(IF(N$7>=$E91,N$6-YEAR($E91),0)))/12),0),0) -> 0 | O91: =IF(O$7>=$E91,IF(O$7<=$F91,(($D91*(1+$C91)^(IF(O$7>=$E91,O$6-YEAR($E91),0)))/12),0),0) -> 0 | P91: =IF(P$7>=$E91,IF(P$7<=$F91,(($D91*(1+$C91)^(IF(P$7>=$E91,P$6-YEAR($E91),0)))/12),0),0) -> 0 | Q91: =IF(Q$7>=$E91,IF(Q$7<=$F91,(($D91*(1+$C91)^(IF(Q$7>=$E91,Q$6-YEAR($E91),0)))/12),0),0) -> 0 | ... OO91: =IF(OO$7>=$E91,IF(OO$7<=$F91,(($D91*(1+$C91)^(IF(OO$7>=$E91,OO$6-YEAR($E91),0)))/12),0),0) -> -555333.79
B92: Management Fee | C92: 0.03 | D92: =-'Operating Expenses & Reserves'!F17 -> -483774.9 | E92: =Assumptions!$C$13 -> 47330 | F92: =EOMONTH(E92,Assumptions!$C$14-1) -> 58256 | G92: =((YEAR(F92)-YEAR(E92))*12+MONTH(F92)-MONTH(E92)+1) -> 360 | J92: =IF(J$7>=$E92,IF(J$7<=$F92,(($D92*(1+$C92)^(IF(J$7>=$E92,J$6-YEAR($E92),0)))/12),0),0) -> 0 | K92: =IF(K$7>=$E92,IF(K$7<=$F92,(($D92*(1+$C92)^(IF(K$7>=$E92,K$6-YEAR($E92),0)))/12),0),0) -> 0 | L92: =IF(L$7>=$E92,IF(L$7<=$F92,(($D92*(1+$C92)^(IF(L$7>=$E92,L$6-YEAR($E92),0)))/12),0),0) -> 0 | M92: =IF(M$7>=$E92,IF(M$7<=$F92,(($D92*(1+$C92)^(IF(M$7>=$E92,M$6-YEAR($E92),0)))/12),0),0) -> 0 | N92: =IF(N$7>=$E92,IF(N$7<=$F92,(($D92*(1+$C92)^(IF(N$7>=$E92,N$6-YEAR($E92),0)))/12),0),0) -> 0 | O92: =IF(O$7>=$E92,IF(O$7<=$F92,(($D92*(1+$C92)^(IF(O$7>=$E92,O$6-YEAR($E92),0)))/12),0),0) -> 0 | P92: =IF(P$7>=$E92,IF(P$7<=$F92,(($D92*(1+$C92)^(IF(P$7>=$E92,P$6-YEAR($E92),0)))/12),0),0) -> 0 | Q92: =IF(Q$7>=$E92,IF(Q$7<=$F92,(($D92*(1+$C92)^(IF(Q$7>=$E92,Q$6-YEAR($E92),0)))/12),0),0) -> 0 | ... OO92: =IF(OO$7>=$E92,IF(OO$7<=$F92,(($D92*(1+$C92)^(IF(OO$7>=$E92,OO$6-YEAR($E92),0)))/12),0),0) -> -97854.055
B93: Total Operating Expenses | J93: =SUM(J91:J92) -> 0 | K93: =SUM(K91:K92) -> 0 | L93: =SUM(L91:L92) -> 0 | M93: =SUM(M91:M92) -> 0 | N93: =SUM(N91:N92) -> 0 | O93: =SUM(O91:O92) -> 0 | P93: =SUM(P91:P92) -> 0 | Q93: =SUM(Q91:Q92) -> 0 | ... OO93: =SUM(OO91:OO92) -> -653187.84
B95: Replacement Reserves | C95: 0.03 | D95: =-'Operating Expenses & Reserves'!D48 -> -111640.36 | E95: =Assumptions!$C$13 -> 47330 | F95: =EOMONTH(E95,Assumptions!$C$14-1) -> 58256 | G95: =((YEAR(F95)-YEAR(E95))*12+MONTH(F95)-MONTH(E95)+1) -> 360 | J95: =IF(J$7>=$E95,IF(J$7<=$F95,(($D95*(1+$C95)^(IF(J$7>=$E95,J$6-YEAR($E95),0)))/12),0),0) -> 0 | K95: =IF(K$7>=$E95,IF(K$7<=$F95,(($D95*(1+$C95)^(IF(K$7>=$E95,K$6-YEAR($E95),0)))/12),0),0) -> 0 | L95: =IF(L$7>=$E95,IF(L$7<=$F95,(($D95*(1+$C95)^(IF(L$7>=$E95,L$6-YEAR($E95),0)))/12),0),0) -> 0 | M95: =IF(M$7>=$E95,IF(M$7<=$F95,(($D95*(1+$C95)^(IF(M$7>=$E95,M$6-YEAR($E95),0)))/12),0),0) -> 0 | N95: =IF(N$7>=$E95,IF(N$7<=$F95,(($D95*(1+$C95)^(IF(N$7>=$E95,N$6-YEAR($E95),0)))/12),0),0) -> 0 | O95: =IF(O$7>=$E95,IF(O$7<=$F95,(($D95*(1+$C95)^(IF(O$7>=$E95,O$6-YEAR($E95),0)))/12),0),0) -> 0 | P95: =IF(P$7>=$E95,IF(P$7<=$F95,(($D95*(1+$C95)^(IF(P$7>=$E95,P$6-YEAR($E95),0)))/12),0),0) -> 0 | Q95: =IF(Q$7>=$E95,IF(Q$7<=$F95,(($D95*(1+$C95)^(IF(Q$7>=$E95,Q$6-YEAR($E95),0)))/12),0),0) -> 0 | ... OO95: =IF(OO$7>=$E95,IF(OO$7<=$F95,(($D95*(1+$C95)^(IF(OO$7>=$E95,OO$6-YEAR($E95),0)))/12),0),0) -> -22581.705
B96: Total Expenses & Reserves | J96: =SUM(J95) -> 0 | K96: =SUM(K95) -> 0 | L96: =SUM(L95) -> 0 | M96: =SUM(M95) -> 0 | N96: =SUM(N95) -> 0 | O96: =SUM(O95) -> 0 | P96: =SUM(P95) -> 0 | Q96: =SUM(Q95) -> 0 | ... OO96: =SUM(OO95) -> -22581.705
B98: Net Operating Income | J98: =J88+J96 -> 0 | K98: =K88+K96 -> 0 | L98: =L88+L96 -> 0 | M98: =M88+M96 -> 0 | N98: =N88+N96 -> 0 | O98: =O88+O96 -> 0 | P98: =P88+P96 -> 0 | Q98: =Q88+Q96 -> 0 | ... OO98: =OO88+OO96 -> 1127494.7
B100: Debt Service
B101: HFA First Mortgage (Construction phase) | C101: ='Construction Interest'!C23 -> 0.05 | E101: =Assumptions!$C$10 -> 46418 | F101: =EOMONTH(E101,SUM(Assumptions!$C$11:$C$12)-1) -> 47299 | G101: =((YEAR(F101)-YEAR(E101))*12+MONTH(F101)-MONTH(E101)+1) -> 30 | J101: =-IF(J$7>=$E101,IF(J$7<=$F101,'Construction Interest'!$E$38,0),0) -> 0 | K101: =-IF(K$7>=$E101,IF(K$7<=$F101,'Construction Interest'!$E$38,0),0) -> 0 | L101: =-IF(L$7>=$E101,IF(L$7<=$F101,'Construction Interest'!$E$38,0),0) -> 0 | M101: =-IF(M$7>=$E101,IF(M$7<=$F101,'Construction Interest'!$E$38,0),0) -> 0 | N101: =-IF(N$7>=$E101,IF(N$7<=$F101,'Construction Interest'!$E$38,0),0) -> 0 | O101: =-IF(O$7>=$E101,IF(O$7<=$F101,'Construction Interest'!$E$38,0),0) -> 0 | P101: =-IF(P$7>=$E101,IF(P$7<=$F101,'Construction Interest'!$E$38,0),0) -> -196608.38 | Q101: =-IF(Q$7>=$E101,IF(Q$7<=$F101,'Construction Interest'!$E$38,0),0) -> -196608.38 | ... OO101: =-IF(OO$7>=$E101,IF(OO$7<=$F101,'Construction Interest'!$E$38,0),0) -> 0
B102: First Mortgage Debt Service (Post conversion) | C102: =Mortgage!C36 -> 0.0575 | E102: =Assumptions!C13 -> 47330 | F102: =EOMONTH(E102,Assumptions!$C$14-1) -> 58256 | G102: =((YEAR(F102)-YEAR(E102))*12+MONTH(F102)-MONTH(E102)+1) -> 360 | J102: =-IF(J$7>=$E102,IF(J$7<=$F102,($C$102*Mortgage!$C$48)/12,0),0) -> 0 | K102: =-IF(K$7>=$E102,IF(K$7<=$F102,($C$102*Mortgage!$C$48)/12,0),0) -> 0 | L102: =-IF(L$7>=$E102,IF(L$7<=$F102,($C$102*Mortgage!$C$48)/12,0),0) -> 0 | M102: =-IF(M$7>=$E102,IF(M$7<=$F102,($C$102*Mortgage!$C$48)/12,0),0) -> 0 | N102: =-IF(N$7>=$E102,IF(N$7<=$F102,($C$102*Mortgage!$C$48)/12,0),0) -> 0 | O102: =-IF(O$7>=$E102,IF(O$7<=$F102,($C$102*Mortgage!$C$48)/12,0),0) -> 0 | P102: =-IF(P$7>=$E102,IF(P$7<=$F102,($C$102*Mortgage!$C$48)/12,0),0) -> 0 | Q102: =-IF(Q$7>=$E102,IF(Q$7<=$F102,($C$102*Mortgage!$C$48)/12,0),0) -> 0 | ... OO102: =-IF(OO$7>=$E102,IF(OO$7<=$F102,($C$102*Mortgage!$C$48)/12,0),0) -> -226099.63
B104: Subsidy Loan (NCF) (Post conversion) | C104: ='Construction Interest'!C28 -> 0.005 | E104: =Assumptions!$C$13 -> 47330 | F104: =EOMONTH(E104,Assumptions!$C$14-1) -> 58256 | G104: =((YEAR(F104)-YEAR(E104))*12+MONTH(F104)-MONTH(E104)+1) -> 360 | J104: =-IF(J$7>=$E104,IF(J$7<=$F104,($C$104*Mortgage!$C$63)/12,0),0) -> 0 | K104: =-IF(K$7>=$E104,IF(K$7<=$F104,($C$104*Mortgage!$C$63)/12,0),0) -> 0 | L104: =-IF(L$7>=$E104,IF(L$7<=$F104,($C$104*Mortgage!$C$63)/12,0),0) -> 0 | M104: =-IF(M$7>=$E104,IF(M$7<=$F104,($C$104*Mortgage!$C$63)/12,0),0) -> 0 | N104: =-IF(N$7>=$E104,IF(N$7<=$F104,($C$104*Mortgage!$C$63)/12,0),0) -> 0 | O104: =-IF(O$7>=$E104,IF(O$7<=$F104,($C$104*Mortgage!$C$63)/12,0),0) -> 0 | P104: =-IF(P$7>=$E104,IF(P$7<=$F104,($C$104*Mortgage!$C$63)/12,0),0) -> 0 | Q104: =-IF(Q$7>=$E104,IF(Q$7<=$F104,($C$104*Mortgage!$C$63)/12,0),0) -> 0 | ... OO104: =-IF(OO$7>=$E104,IF(OO$7<=$F104,($C$104*Mortgage!$C$63)/12,0),0) -> -21866.667
B105: Total Debt Service | J105: =SUM(J101:J104) -> 0 | K105: =SUM(K101:K104) -> 0 | L105: =SUM(L101:L104) -> 0 | M105: =SUM(M101:M104) -> 0 | N105: =SUM(N101:N104) -> 0 | O105: =SUM(O101:O104) -> 0 | P105: =SUM(P101:P104) -> -196608.38 | Q105: =SUM(Q101:Q104) -> -196608.38 | ... OO105: =SUM(OO101:OO104) -> -247966.3
B107: LIHTC Equity
B108: During Construction | D108: ='Sources and Uses'!$C$8 -> 10635591 | E108: =Assumptions!$C$10 -> 46418 | F108: =E108 -> 46418 | G108: =((YEAR(F108)-YEAR(E108))*12+MONTH(F108)-MONTH(E108)+1) -> 1 | J108: =IF(J$7>=$E108,IF(J$7<=$F108,$D$108/$G$108,0),0) -> 0 | K108: =IF(K$7>=$E108,IF(K$7<=$F108,$D$108/$G$108,0),0) -> 0 | L108: =IF(L$7>=$E108,IF(L$7<=$F108,$D$108/$G$108,0),0) -> 0 | M108: =IF(M$7>=$E108,IF(M$7<=$F108,$D$108/$G$108,0),0) -> 0 | N108: =IF(N$7>=$E108,IF(N$7<=$F108,$D$108/$G$108,0),0) -> 0 | O108: =IF(O$7>=$E108,IF(O$7<=$F108,$D$108/$G$108,0),0) -> 0 | P108: =IF(P$7>=$E108,IF(P$7<=$F108,$D$108/$G$108,0),0) -> 10635591 | Q108: =IF(Q$7>=$E108,IF(Q$7<=$F108,$D$108/$G$108,0),0) -> 0 | ... OO108: =IF(OO$7>=$E108,IF(OO$7<=$F108,$D$108/$G$108,0),0) -> 0
B109: Post Construction | D109: ='Tax Credit Analysis'!$D$8-Budget!D108 -> 95720322 | E109: =Assumptions!$C$13 -> 47330 | F109: =E109 -> 47330 | G109: =((YEAR(F109)-YEAR(E109))*12+MONTH(F109)-MONTH(E109)+1) -> 1 | J109: =IF(J$7>=$E109,IF(J$7<=$F109,$D$109/$G$109,0),0) -> 0 | K109: =IF(K$7>=$E109,IF(K$7<=$F109,$D$109/$G$109,0),0) -> 0 | L109: =IF(L$7>=$E109,IF(L$7<=$F109,$D$109/$G$109,0),0) -> 0 | M109: =IF(M$7>=$E109,IF(M$7<=$F109,$D$109/$G$109,0),0) -> 0 | N109: =IF(N$7>=$E109,IF(N$7<=$F109,$D$109/$G$109,0),0) -> 0 | O109: =IF(O$7>=$E109,IF(O$7<=$F109,$D$109/$G$109,0),0) -> 0 | P109: =IF(P$7>=$E109,IF(P$7<=$F109,$D$109/$G$109,0),0) -> 0 | Q109: =IF(Q$7>=$E109,IF(Q$7<=$F109,$D$109/$G$109,0),0) -> 0 | ... OO109: =IF(OO$7>=$E109,IF(OO$7<=$F109,$D$109/$G$109,0),0) -> 0
B112: ANNUAL BUDGET
J113: 1 | K113: 2 | L113: 3 | M113: 4 | N113: 5 | O113: 6 | P113: 7 | Q113: 8 | R113: 9 | S113: 10 | T113: 11 | U113: 12 | V113: 13 | W113: 14 | X113: 15 | Y113: 16 | Z113: 17 | AA113: 18 | AB113: 19 | AC113: 20 | AD113: 21 | AE113: 22 | AF113: 23 | AG113: 24 | AH113: 25 | AI113: 26 | AJ113: 27 | AK113: 28 | AL113: 29 | AM113: 30 | AN113: 31 | AO113: 32 | AP113: 33 | AQ113: 33
J114: =YEAR(J115) -> 2026 | K114: =YEAR(K115) -> 2027 | L114: =YEAR(L115) -> 2028 | M114: =YEAR(M115) -> 2029 | N114: =YEAR(N115) -> 2030 | O114: =YEAR(O115) -> 2031 | P114: =YEAR(P115) -> 2032 | Q114: =YEAR(Q115) -> 2033 | ... AQ114: =YEAR(AQ115) -> 2059
I115: Total | J115: 46387 | K115: =EOMONTH(J115,12) -> 46752 | L115: =EOMONTH(K115,12) -> 47118 | M115: =EOMONTH(L115,12) -> 47483 | N115: =EOMONTH(M115,12) -> 47848 | O115: =EOMONTH(N115,12) -> 48213 | P115: =EOMONTH(O115,12) -> 48579 | Q115: =EOMONTH(P115,12) -> 48944 | R115: =EOMONTH(Q115,12) -> 49309 | ... AQ115: =EOMONTH(AP115,12) -> 58440
B117: =B9 -> DEVELOPMENT PHASE
B119: =B11 -> Acquisition Costs
B120: =B12 -> Building Acquisition | I120: =SUM(J120:AQ120) -> 0 | J120: =SUMIF($J$6:$OO$6,J$114,$J12:$OO12) -> 0 | K120: =SUMIF($J$6:$OO$6,K$114,$J12:$OO12) -> 0 | L120: =SUMIF($J$6:$OO$6,L$114,$J12:$OO12) -> 0 | M120: =SUMIF($J$6:$OO$6,M$114,$J12:$OO12) -> 0 | N120: =SUMIF($J$6:$OO$6,N$114,$J12:$OO12) -> 0 | O120: =SUMIF($J$6:$OO$6,O$114,$J12:$OO12) -> 0 | P120: =SUMIF($J$6:$OO$6,P$114,$J12:$OO12) -> 0 | Q120: =SUMIF($J$6:$OO$6,Q$114,$J12:$OO12) -> 0 | ... AQ120: =SUMIF($J$6:$OO$6,AQ$114,$J12:$OO12) -> 0
B121: =B13 -> Land Acquisition | I121: =SUM(J121:AQ121) -> -1 | J121: =SUMIF($J$6:$OO$6,J$114,$J13:$OO13) -> -1 | K121: =SUMIF($J$6:$OO$6,K$114,$J13:$OO13) -> 0 | L121: =SUMIF($J$6:$OO$6,L$114,$J13:$OO13) -> 0 | M121: =SUMIF($J$6:$OO$6,M$114,$J13:$OO13) -> 0 | N121: =SUMIF($J$6:$OO$6,N$114,$J13:$OO13) -> 0 | O121: =SUMIF($J$6:$OO$6,O$114,$J13:$OO13) -> 0 | P121: =SUMIF($J$6:$OO$6,P$114,$J13:$OO13) -> 0 | Q121: =SUMIF($J$6:$OO$6,Q$114,$J13:$OO13) -> 0 | ... AQ121: =SUMIF($J$6:$OO$6,AQ$114,$J13:$OO13) -> 0
B122: =B14 -> Total Acquisition Costs | I122: =SUM(J122:AQ122) -> -1 | J122: =SUMIF($J$6:$OO$6,J$114,$J14:$OO14) -> -1 | K122: =SUMIF($J$6:$OO$6,K$114,$J14:$OO14) -> 0 | L122: =SUMIF($J$6:$OO$6,L$114,$J14:$OO14) -> 0 | M122: =SUMIF($J$6:$OO$6,M$114,$J14:$OO14) -> 0 | N122: =SUMIF($J$6:$OO$6,N$114,$J14:$OO14) -> 0 | O122: =SUMIF($J$6:$OO$6,O$114,$J14:$OO14) -> 0 | P122: =SUMIF($J$6:$OO$6,P$114,$J14:$OO14) -> 0 | Q122: =SUMIF($J$6:$OO$6,Q$114,$J14:$OO14) -> 0 | ... AQ122: =SUMIF($J$6:$OO$6,AQ$114,$J14:$OO14) -> 0
B124: =B16 -> Hard Cost & Soft Cost
B125: =B17 -> Contractor Price | I125: =SUM(J125:AQ125) -> 0 | J125: =SUMIF($J$6:$OO$6,J$114,$J17:$OO17) -> 0 | K125: =SUMIF($J$6:$OO$6,K$114,$J17:$OO17) -> 0 | L125: =SUMIF($J$6:$OO$6,L$114,$J17:$OO17) -> 0 | M125: =SUMIF($J$6:$OO$6,M$114,$J17:$OO17) -> 0 | N125: =SUMIF($J$6:$OO$6,N$114,$J17:$OO17) -> 0 | O125: =SUMIF($J$6:$OO$6,O$114,$J17:$OO17) -> 0 | P125: =SUMIF($J$6:$OO$6,P$114,$J17:$OO17) -> 0 | Q125: =SUMIF($J$6:$OO$6,Q$114,$J17:$OO17) -> 0 | ... AQ125: =SUMIF($J$6:$OO$6,AQ$114,$J17:$OO17) -> 0
B126: =B18 -> Residential | I126: =SUM(J126:AQ126) -> -164862000 | J126: =SUMIF($J$6:$OO$6,J$114,$J18:$OO18) -> 0 | K126: =SUMIF($J$6:$OO$6,K$114,$J18:$OO18) -> -82431000 | L126: =SUMIF($J$6:$OO$6,L$114,$J18:$OO18) -> -82431000 | M126: =SUMIF($J$6:$OO$6,M$114,$J18:$OO18) -> 0 | N126: =SUMIF($J$6:$OO$6,N$114,$J18:$OO18) -> 0 | O126: =SUMIF($J$6:$OO$6,O$114,$J18:$OO18) -> 0 | P126: =SUMIF($J$6:$OO$6,P$114,$J18:$OO18) -> 0 | Q126: =SUMIF($J$6:$OO$6,Q$114,$J18:$OO18) -> 0 | ... AQ126: =SUMIF($J$6:$OO$6,AQ$114,$J18:$OO18) -> 0
B127: =B19 -> Commercial Space | I127: =SUM(J127:AQ127) -> 0 | J127: =SUMIF($J$6:$OO$6,J$114,$J19:$OO19) -> 0 | K127: =SUMIF($J$6:$OO$6,K$114,$J19:$OO19) -> 0 | L127: =SUMIF($J$6:$OO$6,L$114,$J19:$OO19) -> 0 | M127: =SUMIF($J$6:$OO$6,M$114,$J19:$OO19) -> 0 | N127: =SUMIF($J$6:$OO$6,N$114,$J19:$OO19) -> 0 | O127: =SUMIF($J$6:$OO$6,O$114,$J19:$OO19) -> 0 | P127: =SUMIF($J$6:$OO$6,P$114,$J19:$OO19) -> 0 | Q127: =SUMIF($J$6:$OO$6,Q$114,$J19:$OO19) -> 0 | ... AQ127: =SUMIF($J$6:$OO$6,AQ$114,$J19:$OO19) -> 0
...

Sheet Development CF
B2: Development CASH FLOW
B3: ALL figures are in USD
B5: Development amount coverage | D5: loan draws % | E5: LIHTC + def. developer fee | F5: Amt after LIHTC
B6: =Assumptions!C150 -> 2.4878145e+08 | D6: =Amortization!H8 -> 0.82029895 | E6: =100%-D6 -> 0.17970105 | F6: ='Sources and Uses'!C8 -> 10635591
D7: =B6*D6 -> 2.0407516e+08 | E7: =B6*E6 -> 44706287 | F7: =E7-F6 -> 34070696
E10: 1 | F10: 2 | G10: 3 | H10: 4 | I10: 5 | J10: 6 | K10: 7 | L10: 8 | M10: 9 | N10: 10 | O10: 11 | P10: 12 | Q10: 13 | R10: 14 | S10: 15 | T10: 16 | U10: 17 | V10: 18 | W10: 19 | X10: 20 | Y10: 21 | Z10: 22 | AA10: 23 | AB10: 24 | AC10: 25 | AD10: 26 | AE10: 27 | AF10: 28 | AG10: 29 | AH10: 30
E11: =YEAR(E12) -> 2027 | F11: =YEAR(F12) -> 2027 | G11: =YEAR(G12) -> 2027 | H11: =YEAR(H12) -> 2027 | I11: =YEAR(I12) -> 2027 | J11: =YEAR(J12) -> 2027 | K11: =YEAR(K12) -> 2027 | L11: =YEAR(L12) -> 2027 | ... AH11: =YEAR(AH12) -> 2029
E12: =Assumptions!C10 -> 46418 | F12: =EOMONTH(E12,1) -> 46446 | G12: =EOMONTH(F12,1) -> 46477 | H12: =EOMONTH(G12,1) -> 46507 | I12: =EOMONTH(H12,1) -> 46538 | J12: =EOMONTH(I12,1) -> 46568 | K12: =EOMONTH(J12,1) -> 46599 | L12: =EOMONTH(K12,1) -> 46630 | M12: =EOMONTH(L12,1) -> 46660 | ... AH12: =EOMONTH(AG12,1) -> 47299
B14: Inflow
B15: Rental Income | D15: =-SUM(E15:AH15) -> 0 | E15: =IF(E12>=Assumptions!$C$13,'Rental CF'!F$29,0) -> 0 | F15: =IF(F12>=Assumptions!$C$13,'Rental CF'!G$29,0) -> 0 | G15: =IF(G12>=Assumptions!$C$13,'Rental CF'!H$29,0) -> 0 | H15: =IF(H12>=Assumptions!$C$13,'Rental CF'!I$29,0) -> 0 | I15: =IF(I12>=Assumptions!$C$13,'Rental CF'!J$29,0) -> 0 | J15: =IF(J12>=Assumptions!$C$13,'Rental CF'!K$29,0) -> 0 | K15: =IF(K12>=Assumptions!$C$13,'Rental CF'!L$29,0) -> 0 | L15: =IF(L12>=Assumptions!$C$13,'Rental CF'!M$29,0) -> 0 | ... AH15: =IF(AH12>=Assumptions!$C$13,'Rental CF'!AI$29,0) -> 0
B16: LIHTC Equity | E16: =IF(E12=Assumptions!$C$10,'Sources and Uses'!$C$8,0) -> 10635591 | F16: =IF(F12=Assumptions!$C$10,'Sources and Uses'!$C$8,0) -> 0 | G16: =IF(G12=Assumptions!$C$10,'Sources and Uses'!$C$8,0) -> 0 | H16: =IF(H12=Assumptions!$C$10,'Sources and Uses'!$C$8,0) -> 0 | I16: =IF(I12=Assumptions!$C$10,'Sources and Uses'!$C$8,0) -> 0 | J16: =IF(J12=Assumptions!$C$10,'Sources and Uses'!$C$8,0) -> 0 | K16: =IF(K12=Assumptions!$C$10,'Sources and Uses'!$C$8,0) -> 0 | L16: =IF(L12=Assumptions!$C$10,'Sources and Uses'!$C$8,0) -> 0 | ... AH16: =IF(AH12=Assumptions!$C$10,'Sources and Uses'!$C$8,0) -> 0
B17: Loan draws | E17: =-E28*$D$6 -> 8462988.1 | F17: =-F28*$D$6 -> 8462987.3 | G17: =-G28*$D$6 -> 8462987.3 | H17: =-H28*$D$6 -> 8462987.3 | I17: =-I28*$D$6 -> 8462987.3 | J17: =-J28*$D$6 -> 8462987.3 | K17: =-K28*$D$6 -> 8462987.3 | L17: =-L28*$D$6 -> 8462987.3 | ... AH17: =-AH28*$D$6 -> 1412777.5
B18: Defered Developer Fee | E18: =IF(E12=Assumptions!$C$10,Assumptions!$D$63,IF(AND(E12>=Assumptions!$C$10,E12<=EOMONTH(Assumptions!$C$10,Assumptions!$C$11)),Assumptions!$D$64/Assumptions!$C$11,IF(E12=EOMONTH(Assumptions!$C$13,Assumptions!$E$65),Assumptions!$D$65,0))) -> 0 | F18: =IF(F12=Assumptions!$C$10,Assumptions!$D$63,IF(AND(F12>=Assumptions!$C$10,F12<=EOMONTH(Assumptions!$C$10,Assumptions!$C$11)),Assumptions!$D$64/Assumptions!$C$11,IF(F12=EOMONTH(Assumptions!$C$13,Assumptions!$E$65),Assumptions!$D$65,0))) -> 36583.333 | G18: =IF(G12=Assumptions!$C$10,Assumptions!$D$63,IF(AND(G12>=Assumptions!$C$10,G12<=EOMONTH(Assumptions!$C$10,Assumptions!$C$11)),Assumptions!$D$64/Assumptions!$C$11,IF(G12=EOMONTH(Assumptions!$C$13,Assumptions!$E$65),Assumptions!$D$65,0))) -> 36583.333 | H18: =IF(H12=Assumptions!$C$10,Assumptions!$D$63,IF(AND(H12>=Assumptions!$C$10,H12<=EOMONTH(Assumptions!$C$10,Assumptions!$C$11)),Assumptions!$D$64/Assumptions!$C$11,IF(H12=EOMONTH(Assumptions!$C$13,Assumptions!$E$65),Assumptions!$D$65,0))) -> 36583.333 | I18: =IF(I12=Assumptions!$C$10,Assumptions!$D$63,IF(AND(I12>=Assumptions!$C$10,I12<=EOMONTH(Assumptions!$C$10,Assumptions!$C$11)),Assumptions!$D$64/Assumptions!$C$11,IF(I12=EOMONTH(Assumptions!$C$13,Assumptions!$E$65),Assumptions!$D$65,0))) -> 36583.333 | J18: =IF(J12=Assumptions!$C$10,Assumptions!$D$63,IF(AND(J12>=Assumptions!$C$10,J12<=EOMONTH(Assumptions!$C$10,Assumptions!$C$11)),Assumptions!$D$64/Assumptions!$C$11,IF(J12=EOMONTH(Assumptions!$C$13,Assumptions!$E$65),Assumptions!$D$65,0))) -> 36583.333 | K18: =IF(K12=Assumptions!$C$10,Assumptions!$D$63,IF(AND(K12>=Assumptions!$C$10,K12<=EOMONTH(Assumptions!$C$10,Assumptions!$C$11)),Assumptions!$D$64/Assumptions!$C$11,IF(K12=EOMONTH(Assumptions!$C$13,Assumptions!$E$65),Assumptions!$D$65,0))) -> 36583.333 | L18: =IF(L12=Assumptions!$C$10,Assumptions!$D$63,IF(AND(L12>=Assumptions!$C$10,L12<=EOMONTH(Assumptions!$C$10,Assumptions!$C$11)),Assumptions!$D$64/Assumptions!$C$11,IF(L12=EOMONTH(Assumptions!$C$13,Assumptions!$E$65),Assumptions!$D$65,0))) -> 36583.333 | ... AH18: =IF(AH12=Assumptions!$C$10,Assumptions!$D$63,IF(AND(AH12>=Assumptions!$C$10,AH12<=EOMONTH(Assumptions!$C$10,Assumptions!$C$11)),Assumptions!$D$64/Assumptions!$C$11,IF(AH12=EOMONTH(Assumptions!$C$13,Assumptions!$E$65),Assumptions!$D$65,0))) -> 0
B20: Total Inflow | E20: =SUM(E15:E19) -> 19098579 | F20: =SUM(F15:F19) -> 8499570.6 | G20: =SUM(G15:G19) -> 8499570.6 | H20: =SUM(H15:H19) -> 8499570.6 | I20: =SUM(I15:I19) -> 8499570.6 | J20: =SUM(J15:J19) -> 8499570.6 | K20: =SUM(K15:K19) -> 8499570.6 | L20: =SUM(L15:L19) -> 8499570.6 | ... AH20: =SUM(AH15:AH19) -> 1412777.5
B22: Ouflow
B24: Acquisition Cost | E24: =Budget!J122 -> -1 | F24: =Budget!K122 -> 0 | G24: =Budget!L122 -> 0 | H24: =Budget!M122 -> 0 | I24: =Budget!N122 -> 0 | J24: =Budget!O122 -> 0 | K24: =Budget!P122 -> 0 | L24: =Budget!Q122 -> 0 | ... AH24: =Budget!AM122 -> 0
B25: Soft & Hard Cost | E25: =_xlfn.XLOOKUP('Development CF'!E12,Budget!$J$7:$OO$7,Budget!$J$50:$OO$50) -> -8594683.3 | F25: =_xlfn.XLOOKUP('Development CF'!F12,Budget!$J$7:$OO$7,Budget!$J$50:$OO$50) -> -8594683.3 | G25: =_xlfn.XLOOKUP('Development CF'!G12,Budget!$J$7:$OO$7,Budget!$J$50:$OO$50) -> -8594683.3 | H25: =_xlfn.XLOOKUP('Development CF'!H12,Budget!$J$7:$OO$7,Budget!$J$50:$OO$50) -> -8594683.3 | I25: =_xlfn.XLOOKUP('Development CF'!I12,Budget!$J$7:$OO$7,Budget!$J$50:$OO$50) -> -8594683.3 | J25: =_xlfn.XLOOKUP('Development CF'!J12,Budget!$J$7:$OO$7,Budget!$J$50:$OO$50) -> -8594683.3 | K25: =_xlfn.XLOOKUP('Development CF'!K12,Budget!$J$7:$OO$7,Budget!$J$50:$OO$50) -> -8594683.3 | L25: =_xlfn.XLOOKUP('Development CF'!L12,Budget!$J$7:$OO$7,Budget!$J$50:$OO$50) -> -8594683.3 | ... AH25: =_xlfn.XLOOKUP('Development CF'!AH12,Budget!$J$7:$OO$7,Budget!$J$50:$OO$50) -> 0
B26: Finance Cost | E26: =_xlfn.XLOOKUP(E12,Budget!$J$7:$OO$7,Budget!$J$58:$OO$58) -> -1722271.5 | F26: =_xlfn.XLOOKUP(F12,Budget!$J$7:$OO$7,Budget!$J$58:$OO$58) -> -1722271.5 | G26: =_xlfn.XLOOKUP(G12,Budget!$J$7:$OO$7,Budget!$J$58:$OO$58) -> -1722271.5 | H26: =_xlfn.XLOOKUP(H12,Budget!$J$7:$OO$7,Budget!$J$58:$OO$58) -> -1722271.5 | I26: =_xlfn.XLOOKUP(I12,Budget!$J$7:$OO$7,Budget!$J$58:$OO$58) -> -1722271.5 | J26: =_xlfn.XLOOKUP(J12,Budget!$J$7:$OO$7,Budget!$J$58:$OO$58) -> -1722271.5 | K26: =_xlfn.XLOOKUP(K12,Budget!$J$7:$OO$7,Budget!$J$58:$OO$58) -> -1722271.5 | L26: =_xlfn.XLOOKUP(L12,Budget!$J$7:$OO$7,Budget!$J$58:$OO$58) -> -1722271.5 | ... AH26: =_xlfn.XLOOKUP(AH12,Budget!$J$7:$OO$7,Budget!$J$58:$OO$58) -> -1722271.5
B28: Total Outflow | E28: =SUM(E24:E27) -> -10316956 | F28: =SUM(F25:F27) -> -10316955 | G28: =SUM(G25:G27) -> -10316955 | H28: =SUM(H25:H27) -> -10316955 | I28: =SUM(I25:I27) -> -10316955 | J28: =SUM(J25:J27) -> -10316955 | K28: =SUM(K25:K27) -> -10316955 | L28: =SUM(L25:L27) -> -10316955 | M28: =SUM(M25:M27) -> -10316955 | ... AH28: =SUM(AH25:AH27) -> -1722271.5
B30: Net Cash Flow | E30: =E20+E28 -> 8781623.6 | F30: =F20+F28 -> -1817384.2 | G30: =G20+G28 -> -1817384.2 | H30: =H20+H28 -> -1817384.2 | I30: =I20+I28 -> -1817384.2 | J30: =J20+J28 -> -1817384.2 | K30: =K20+K28 -> -1817384.2 | L30: =L20+L28 -> -1817384.2 | ... AH30: =AH20+AH28 -> -309493.99
B33: IRR | C33: =(1+XIRR(E30:AH30,E12:AH12))^(1/12)-1 -> 0.20661034

Sheet Rental CF
B2: Rental Cash Flow
B3: ALL figures are in USD
F5: 1 | G5: 2 | H5: 3 | I5: 4 | J5: 5 | K5: 6 | L5: 7 | M5: 8 | N5: 9 | O5: 10 | P5: 11 | Q5: 12 | R5: 13 | S5: 14 | T5: 15 | U5: 16 | V5: 17 | W5: 18 | X5: 19 | Y5: 20 | Z5: 21 | AA5: 22 | AB5: 23 | AC5: 24 | AD5: 25 | AE5: 26 | AF5: 27 | AG5: 28 | AH5: 29 | AI5: 30
F6: =YEAR(F7) -> 2029 | G6: =YEAR(G7) -> 2030 | H6: =YEAR(H7) -> 2031 | I6: =YEAR(I7) -> 2032 | J6: =YEAR(J7) -> 2033 | K6: =YEAR(K7) -> 2034 | L6: =YEAR(L7) -> 2035 | M6: =YEAR(M7) -> 2036 | ... AI6: =YEAR(AI7) -> 2058
F7: =Assumptions!C13 -> 47330 | G7: =EOMONTH(F7,12) -> 47695 | H7: =EOMONTH(G7,12) -> 48060 | I7: =EOMONTH(H7,12) -> 48426 | J7: =EOMONTH(I7,12) -> 48791 | K7: =EOMONTH(J7,12) -> 49156 | L7: =EOMONTH(K7,12) -> 49521 | M7: =EOMONTH(L7,12) -> 49887 | N7: =EOMONTH(M7,12) -> 50252 | ... AI7: =EOMONTH(AH7,12) -> 57922
C8: Escalator (%)
B9: Potential Gross Income
B10: Total Annual Rental Income | C10: 0.02 | F10: ='Unit Mix'!I81 -> 7752009.3 | G10: =F10+(F10*$C10) -> 7907049.4 | H10: =G10+(G10*$C10) -> 8065190.4 | I10: =H10+(H10*$C10) -> 8226494.2 | J10: =I10+(I10*$C10) -> 8391024.1 | K10: =J10+(J10*$C10) -> 8558844.6 | L10: =K10+(K10*$C10) -> 8730021.5 | M10: =L10+(L10*$C10) -> 8904621.9 | N10: =M10+(M10*$C10) -> 9082714.4 | ... AI10: =AH10+(AH10*$C10) -> 13766364
B11: Parking | C11: 0.02 | F11: =Mortgage!D6 -> 45000 | G11: =F11+(F11*$C11) -> 45900 | H11: =G11+(G11*$C11) -> 46818 | I11: =H11+(H11*$C11) -> 47754.36 | J11: =I11+(I11*$C11) -> 48709.447 | K11: =J11+(J11*$C11) -> 49683.636 | L11: =K11+(K11*$C11) -> 50677.309 | M11: =L11+(L11*$C11) -> 51690.855 | N11: =M11+(M11*$C11) -> 52724.672 | ... AI11: =AH11+(AH11*$C11) -> 79913.011
B12: Commercial | C12: 0.02 | F12: =Mortgage!D7 -> 0 | G12: =F12+(F12*$C12) -> 0 | H12: =G12+(G12*$C12) -> 0 | I12: =H12+(H12*$C12) -> 0 | J12: =I12+(I12*$C12) -> 0 | K12: =J12+(J12*$C12) -> 0 | L12: =K12+(K12*$C12) -> 0 | M12: =L12+(L12*$C12) -> 0 | N12: =M12+(M12*$C12) -> 0 | ... AI12: =AH12+(AH12*$C12) -> 0
B13: Community Facility | C13: 0.02 | F13: =Mortgage!D8 -> 0 | G13: =F13+(F13*$C13) -> 0 | H13: =G13+(G13*$C13) -> 0 | I13: =H13+(H13*$C13) -> 0 | J13: =I13+(I13*$C13) -> 0 | K13: =J13+(J13*$C13) -> 0 | L13: =K13+(K13*$C13) -> 0 | M13: =L13+(L13*$C13) -> 0 | N13: =M13+(M13*$C13) -> 0 | ... AI13: =AH13+(AH13*$C13) -> 0
B14: Laundry | C14: 0.02 | F14: =Mortgage!D9 -> 39480 | G14: =F14+(F14*$C14) -> 40269.6 | H14: =G14+(G14*$C14) -> 41074.992 | I14: =H14+(H14*$C14) -> 41896.492 | J14: =I14+(I14*$C14) -> 42734.422 | K14: =J14+(J14*$C14) -> 43589.11 | L14: =K14+(K14*$C14) -> 44460.892 | M14: =L14+(L14*$C14) -> 45350.11 | N14: =M14+(M14*$C14) -> 46257.112 | ... AI14: =AH14+(AH14*$C14) -> 70110.348
B15: Total Potential Gross Income: | F15: =SUM(F10:F14) -> 7836489.3 | G15: =SUM(G10:G14) -> 7993219 | H15: =SUM(H10:H14) -> 8153083.4 | I15: =SUM(I10:I14) -> 8316145.1 | J15: =SUM(J10:J14) -> 8482468 | K15: =SUM(K10:K14) -> 8652117.4 | L15: =SUM(L10:L14) -> 8825159.7 | M15: =SUM(M10:M14) -> 9001662.9 | ... AI15: =SUM(AI10:AI14) -> 13916388
B16: Vacancy Allowance
B17: Total Annual Rental Income | D17: =Mortgage!C13 -> 0.05 | F17: =-(F10*$D17) -> -387600.46 | G17: =-(G10*$D17) -> -395352.47 | H17: =-(H10*$D17) -> -403259.52 | I17: =-(I10*$D17) -> -411324.71 | J17: =-(J10*$D17) -> -419551.21 | K17: =-(K10*$D17) -> -427942.23 | L17: =-(L10*$D17) -> -436501.07 | M17: =-(M10*$D17) -> -445231.1 | ... AI17: =-(AI10*$D17) -> -688318.22
B18: Parking | D18: 0.05 | F18: =-(F11*$D18) -> -2250 | G18: =-(G11*$D18) -> -2295 | H18: =-(H11*$D18) -> -2340.9 | I18: =-(I11*$D18) -> -2387.718 | J18: =-(J11*$D18) -> -2435.4724 | K18: =-(K11*$D18) -> -2484.1818 | L18: =-(L11*$D18) -> -2533.8654 | M18: =-(M11*$D18) -> -2584.5428 | ... AI18: =-(AI11*$D18) -> -3995.6506
B19: Commercial | D19: =Mortgage!C15 -> 0.1 | F19: =-(F12*$D19) -> 0 | G19: =-(G12*$D19) -> 0 | H19: =-(H12*$D19) -> 0 | I19: =-(I12*$D19) -> 0 | J19: =-(J12*$D19) -> 0 | K19: =-(K12*$D19) -> 0 | L19: =-(L12*$D19) -> 0 | M19: =-(M12*$D19) -> 0 | ... AI19: =-(AI12*$D19) -> 0
B20: Community Facility | D20: =Mortgage!C16 -> 0.1 | F20: =-(F13*$D20) -> 0 | G20: =-(G13*$D20) -> 0 | H20: =-(H13*$D20) -> 0 | I20: =-(I13*$D20) -> 0 | J20: =-(J13*$D20) -> 0 | K20: =-(K13*$D20) -> 0 | L20: =-(L13*$D20) -> 0 | M20: =-(M13*$D20) -> 0 | ... AI20: =-(AI13*$D20) -> 0
B21: Laundry | D21: =Mortgage!C17 -> 0.1 | F21: =-(F14*$D21) -> -3948 | G21: =-(G14*$D21) -> -4026.96 | H21: =-(H14*$D21) -> -4107.4992 | I21: =-(I14*$D21) -> -4189.6492 | J21: =-(J14*$D21) -> -4273.4422 | K21: =-(K14*$D21) -> -4358.911 | L21: =-(L14*$D21) -> -4446.0892 | M21: =-(M14*$D21) -> -4535.011 | ... AI21: =-(AI14*$D21) -> -7011.0348
B22: Total Vacancy Allowance: | F22: =SUM(F17:F21) -> -393798.46 | G22: =SUM(G17:G21) -> -401674.43 | H22: =SUM(H17:H21) -> -409707.92 | I22: =SUM(I17:I21) -> -417902.08 | J22: =SUM(J17:J21) -> -426260.12 | K22: =SUM(K17:K21) -> -434785.32 | L22: =SUM(L17:L21) -> -443481.03 | M22: =SUM(M17:M21) -> -452350.65 | ... AI22: =SUM(AI17:AI21) -> -699324.91
B23: Effective Gross Income
B24: Total Annual Rental Income | F24: =F10+F17 -> 7364408.8 | G24: =G10+G17 -> 7511697 | H24: =H10+H17 -> 7661930.9 | I24: =I10+I17 -> 7815169.5 | J24: =J10+J17 -> 7971472.9 | K24: =K10+K17 -> 8130902.4 | L24: =L10+L17 -> 8293520.4 | M24: =M10+M17 -> 8459390.8 | ... AI24: =AI10+AI17 -> 13078046
B25: Parking | F25: =F11+F18 -> 42750 | G25: =G11+G18 -> 43605 | H25: =H11+H18 -> 44477.1 | I25: =I11+I18 -> 45366.642 | J25: =J11+J18 -> 46273.975 | K25: =K11+K18 -> 47199.454 | L25: =L11+L18 -> 48143.443 | M25: =M11+M18 -> 49106.312 | ... AI25: =AI11+AI18 -> 75917.361
B26: Commercial | F26: =F12+F19 -> 0 | G26: =G12+G19 -> 0 | H26: =H12+H19 -> 0 | I26: =I12+I19 -> 0 | J26: =J12+J19 -> 0 | K26: =K12+K19 -> 0 | L26: =L12+L19 -> 0 | M26: =M12+M19 -> 0 | ... AI26: =AI12+AI19 -> 0
B27: Community Facility | F27: =F13+F20 -> 0 | G27: =G13+G20 -> 0 | H27: =H13+H20 -> 0 | I27: =I13+I20 -> 0 | J27: =J13+J20 -> 0 | K27: =K13+K20 -> 0 | L27: =L13+L20 -> 0 | M27: =M13+M20 -> 0 | ... AI27: =AI13+AI20 -> 0
B28: Laundry | F28: =F14+F21 -> 35532 | G28: =G14+G21 -> 36242.64 | H28: =H14+H21 -> 36967.493 | I28: =I14+I21 -> 37706.843 | J28: =J14+J21 -> 38460.98 | K28: =K14+K21 -> 39230.199 | L28: =L14+L21 -> 40014.803 | M28: =M14+M21 -> 40815.099 | ... AI28: =AI14+AI21 -> 63099.314
B29: Effective Gross Income: | F29: =SUM(F24:F28) -> 7442690.8 | G29: =SUM(G24:G28) -> 7591544.6 | H29: =SUM(H24:H28) -> 7743375.5 | I29: =SUM(I24:I28) -> 7898243 | J29: =SUM(J24:J28) -> 8056207.9 | K29: =SUM(K24:K28) -> 8217332 | L29: =SUM(L24:L28) -> 8381678.7 | M29: =SUM(M24:M28) -> 8549312.2 | ... AI29: =SUM(AI24:AI28) -> 13217063
B30: Maintenance & Operating Expenses
B31: Operating Expenses: | C31: 0.03 | F31: =-'Operating Expenses & Reserves'!F37 -> -2745482 | G31: =F31+(F31*$C31) -> -2827846.5 | H31: =G31+(G31*$C31) -> -2912681.9 | I31: =H31+(H31*$C31) -> -3000062.3 | J31: =I31+(I31*$C31) -> -3090064.2 | K31: =J31+(J31*$C31) -> -3182766.1 | L31: =K31+(K31*$C31) -> -3278249.1 | M31: =L31+(L31*$C31) -> -3376596.6 | N31: =M31+(M31*$C31) -> -3477894.5 | ... AI31: =AH31+(AH31*$C31) -> -6469908.2
B32: Management Fee | C32: 0.03 | F32: =-'Operating Expenses & Reserves'!F17 -> -483774.9 | G32: =F32+(F32*$C32) -> -498288.15 | H32: =G32+(G32*$C32) -> -513236.79 | I32: =H32+(H32*$C32) -> -528633.9 | J32: =I32+(I32*$C32) -> -544492.91 | K32: =J32+(J32*$C32) -> -560827.7 | L32: =K32+(K32*$C32) -> -577652.53 | M32: =L32+(L32*$C32) -> -594982.11 | N32: =M32+(M32*$C32) -> -612831.57 | ... AI32: =AH32+(AH32*$C32) -> -1140047.2
B33: Total Operating Expenses: | F33: =SUM(F31:F32) -> -3229256.9 | G33: =SUM(G31:G32) -> -3326134.6 | H33: =SUM(H31:H32) -> -3425918.6 | I33: =SUM(I31:I32) -> -3528696.2 | J33: =SUM(J31:J32) -> -3634557.1 | K33: =SUM(K31:K32) -> -3743593.8 | L33: =SUM(L31:L32) -> -3855901.6 | M33: =SUM(M31:M32) -> -3971578.7 | ... AI33: =SUM(AI31:AI32) -> -7609955.4
B34: Replacement Reserves | C34: 0.03 | F34: =-'Operating Expenses & Reserves'!D48 -> -111640.36 | G34: =F34+(F34*$C34) -> -114989.57 | H34: =G34+(G34*$C34) -> -118439.26 | I34: =H34+(H34*$C34) -> -121992.44 | J34: =I34+(I34*$C34) -> -125652.21 | K34: =J34+(J34*$C34) -> -129421.78 | L34: =K34+(K34*$C34) -> -133304.43 | M34: =L34+(L34*$C34) -> -137303.56 | N34: =M34+(M34*$C34) -> -141422.67 | ... AI34: =AH34+(AH34*$C34) -> -263087.83
B35: Total Expenses & Reserves: | F35: =F34+F33 -> -3340897.3 | G35: =G34+G33 -> -3441124.2 | H35: =H34+H33 -> -3544357.9 | I35: =I34+I33 -> -3650688.6 | J35: =J34+J33 -> -3760209.3 | K35: =K34+K33 -> -3873015.6 | L35: =L34+L33 -> -3989206 | M35: =M34+M33 -> -4108882.2 | ... AI35: =AI34+AI33 -> -7873043.3
B36: Net Operating Income: | F36: =F29+F35 -> 4101793.5 | G36: =G29+G35 -> 4150420.4 | H36: =H29+H35 -> 4199017.6 | I36: =I29+I35 -> 4247554.4 | J36: =J29+J35 -> 4295998.6 | K36: =K29+K35 -> 4344316.4 | L36: =L29+L35 -> 4392472.6 | M36: =M29+M35 -> 4440430 | ... AI36: =AI29+AI35 -> 5344019.7
B38: Debt Service | C38: IR (%)
B39: HFA First Mortgage | C39: ='Construction Interest'!C21 -> 0.05 | F39: =-Mortgage!$C$48*'Rental CF'!$C$39 -> -2359300.5 | G39: =-Mortgage!$C$48*'Rental CF'!$C$39 -> -2359300.5 | H39: =-Mortgage!$C$48*'Rental CF'!$C$39 -> -2359300.5 | I39: =-Mortgage!$C$48*'Rental CF'!$C$39 -> -2359300.5 | J39: =-Mortgage!$C$48*'Rental CF'!$C$39 -> -2359300.5 | K39: =-Mortgage!$C$48*'Rental CF'!$C$39 -> -2359300.5 | L39: =-Mortgage!$C$48*'Rental CF'!$C$39 -> -2359300.5 | M39: =-Mortgage!$C$48*'Rental CF'!$C$39 -> -2359300.5 | ... AI39: =-Mortgage!$C$48*'Rental CF'!$C$39 -> -2359300.5
B40: SONYMA premium | C40: =Mortgage!C35 -> 0.005 | F40: =-Mortgage!$C$48*$C$40 -> -235930.05 | G40: =-Mortgage!$C$48*$C$40 -> -235930.05 | H40: =-Mortgage!$C$48*$C$40 -> -235930.05 | I40: =-Mortgage!$C$48*$C$40 -> -235930.05 | J40: =-Mortgage!$C$48*$C$40 -> -235930.05 | K40: =-Mortgage!$C$48*$C$40 -> -235930.05 | L40: =-Mortgage!$C$48*$C$40 -> -235930.05 | M40: =-Mortgage!$C$48*$C$40 -> -235930.05 | ... AI40: =-Mortgage!$C$48*$C$40 -> -235930.05
B41: Servicing Fee | C41: =Mortgage!C34 -> 0.0025 | F41: =-Mortgage!$C$48*$C$41 -> -117965.03 | G41: =-Mortgage!$C$48*$C$41 -> -117965.03 | H41: =-Mortgage!$C$48*$C$41 -> -117965.03 | I41: =-Mortgage!$C$48*$C$41 -> -117965.03 | J41: =-Mortgage!$C$48*$C$41 -> -117965.03 | K41: =-Mortgage!$C$48*$C$41 -> -117965.03 | L41: =-Mortgage!$C$48*$C$41 -> -117965.03 | M41: =-Mortgage!$C$48*$C$41 -> -117965.03 | ... AI41: =-Mortgage!$C$48*$C$41 -> -117965.03
B42: Total First Mortgage Debt Service: | F42: =SUM(F39:F41) -> -2713195.6 | G42: =SUM(G39:G41) -> -2713195.6 | H42: =SUM(H39:H41) -> -2713195.6 | I42: =SUM(I39:I41) -> -2713195.6 | J42: =SUM(J39:J41) -> -2713195.6 | K42: =SUM(K39:K41) -> -2713195.6 | L42: =SUM(L39:L41) -> -2713195.6 | M42: =SUM(M39:M41) -> -2713195.6 | ... AI42: =SUM(AI39:AI41) -> -2713195.6
B44: ='Construction Interest'!B34 -> Subsidy Loan (NCF) | C44: ='Construction Interest'!C28 -> 0.005 | F44: =-Mortgage!$C$63*'Rental CF'!$C$44 -> -262400 | G44: =-Mortgage!$C$63*'Rental CF'!$C$44 -> -262400 | H44: =-Mortgage!$C$63*'Rental CF'!$C$44 -> -262400 | I44: =-Mortgage!$C$63*'Rental CF'!$C$44 -> -262400 | J44: =-Mortgage!$C$63*'Rental CF'!$C$44 -> -262400 | K44: =-Mortgage!$C$63*'Rental CF'!$C$44 -> -262400 | L44: =-Mortgage!$C$63*'Rental CF'!$C$44 -> -262400 | M44: =-Mortgage!$C$63*'Rental CF'!$C$44 -> -262400 | ... AI44: =-Mortgage!$C$63*'Rental CF'!$C$44 -> -262400
B46: Total Debt Service: | F46: =F44+F42 -> -2975595.6 | G46: =G44+G42 -> -2975595.6 | H46: =H44+H42 -> -2975595.6 | I46: =I44+I42 -> -2975595.6 | J46: =J44+J42 -> -2975595.6 | K46: =K44+K42 -> -2975595.6 | L46: =L44+L42 -> -2975595.6 | M46: =M44+M42 -> -2975595.6 | ... AI46: =AI44+AI42 -> -2975595.6
B48: Net Cash Flow | F48: =F36+F46 -> 1126197.9 | G48: =G36+G46 -> 1174824.8 | H48: =H36+H46 -> 1223422 | I48: =I36+I46 -> 1271958.8 | J48: =J36+J46 -> 1320403 | K48: =K36+K46 -> 1368720.9 | L48: =L36+L46 -> 1416877 | M48: =M36+M46 -> 1464834.4 | ... AI48: =AI36+AI46 -> 2368424.1
B50: Income to Expense Ratio | C50: 1.05 (min) | F50: =-F29/(F35+F46) -> 1.1782948 | G50: =-G29/(G35+G46) -> 1.1830881 | H50: =-H29/(H35+H46) -> 1.1876427 | I50: =-I29/(I35+I46) -> 1.1919566 | J50: =-J29/(J35+J46) -> 1.1960275 | K50: =-K29/(K35+K46) -> 1.1998538 | L50: =-L29/(L35+L46) -> 1.2034339 | M50: =-M29/(M35+M46) -> 1.2067667 | ... AI50: =-AI29/(AI35+AI46) -> 1.2183153
B51: Debt Service Coverage Ratio (Global) | C51: 1.15 (min) | F51: =-F36/F46 -> 1.3784782 | G51: =-G36/G46 -> 1.3948201 | H51: =-H36/H46 -> 1.411152 | I51: =-I36/I46 -> 1.4274636 | J51: =-J36/J46 -> 1.4437441 | K51: =-K36/K46 -> 1.4599821 | L51: =-L36/L46 -> 1.4761659 | M51: =-M36/M46 -> 1.4922828 | ... AI51: =-AI36/AI46 -> 1.7959496
B52: Debt Coverage Ratio (Senior) | F52: =-F36/F42 -> 1.5117943 | G52: =-G36/G42 -> 1.5297166 | H52: =-H36/H42 -> 1.547628 | I52: =-I36/I42 -> 1.5655172 | J52: =-J36/J42 -> 1.5833722 | K52: =-K36/K42 -> 1.6011807 | L52: =-L36/L42 -> 1.6189296 | M52: =-M36/M42 -> 1.6366052 | ... AI52: =-AI36/AI42 -> 1.9696404
B54: Cap Rate | C54: 0.07
B55: Property Value | F55: =F36/$C$54 -> 58597050 | G55: =G36/$C$54 -> 59291720 | H55: =H36/$C$54 -> 59985966 | I55: =I36/$C$54 -> 60679348 | J55: =J36/$C$54 -> 61371408 | K55: =K36/$C$54 -> 62061664 | L55: =L36/$C$54 -> 62749609 | M55: =M36/$C$54 -> 63434714 | ... AI55: =AI36/$C$54 -> 76343138

Sheet Amortization
B2: DEBT SCHEDULE
B3: All Figures are in USD
B5: HFA Frist Mortgage (Senior loan) | F5: Loan to Cost
B6: Permanent Credit Enhancer | C6: =Mortgage!C28 -> SONYMA-MIF | F6: Total Loan | H6: =Mortgage!D56 -> 2.2950516e+08
B7: Loan Type | C7: Self-Amortizing, Tax-Exempt | F7: Total Development Cost | H7: =-SUM(Budget!J62:OO62) -> 2.7978234e+08
B8: Loan Amount | C8: =Mortgage!C48 -> 47186010 | F8: LTC | H8: =H6/H7 -> 0.82029895 | I8: Max LTC is 90%
B9: Loan Commencement Date | C9: =Assumptions!C10 -> 46418
B10: Loan Term (years) | C10: 30
B11: Amortization Period (years) | C11: =C10 -> 30
B13: Permanent Rates
B14: Base Underwriting Rate | C14: =Mortgage!C33 -> 0.05
B15: SONYMA premium | C15: =Mortgage!C35 -> 0.005
B16: Servicing Fee | C16: =Mortgage!C34 -> 0.0025
B17: Sum (All-In Rate) | C17: =Mortgage!C36 -> 0.0575
F21: Period | G21: 0 | H21: 1 | I21: 2 | J21: 3 | K21: 4 | L21: 5 | M21: 6 | N21: 7 | O21: 8 | P21: 9 | Q21: 10 | R21: 11 | S21: 12 | T21: 13 | U21: 14 | V21: 15 | W21: 16 | X21: 17 | Y21: 18 | Z21: 19 | AA21: 20 | AB21: 21 | AC21: 22 | AD21: 23 | AE21: 24 | AF21: 25 | AG21: 26 | AH21: 27 | AI21: 28 | AJ21: 29 | AK21: 30 | AL21: 31 | AM21: 32 | AN21: 33 | AO21: 34 | AP21: 35 | AQ21: 36 | AR21: 37 | AS21: 38 | AT21: 39 | AU21: 40 | AV21: 41 | AW21: 42 | AX21: 43 | AY21: 44 | AZ21: 45 | BA21: 46 | BB21: 47 | BC21: 48 | BD21: 49 | BE21: 50 | BF21: 51 | BG21: 52 | BH21: 53 | BI21: 54 | BJ21: 55 | BK21: 56 | BL21: 57 | BM21: 58 | BN21: 59 | BO21: 60 | BP21: 61 | BQ21: 62 | BR21: 63 | BS21: 64 | BT21: 65 | BU21: 66 | BV21: 67 | BW21: 68 | BX21: 69 | BY21: 70 | BZ21: 71 | CA21: 72 | CB21: 73 | CC21: 74 | CD21: 75 | CE21: 76 | CF21: 77 | CG21: 78 | CH21: 79 | CI21: 80 | CJ21: 81 | CK21: 82 | CL21: 83 | CM21: 84 | CN21: 85 | CO21: 86 | CP21: 87 | CQ21: 88 | CR21: 89 | CS21: 90 | CT21: 91 | CU21: 92 | CV21: 93 | CW21: 94 | CX21: 95 | CY21: 96 | CZ21: 97 | DA21: 98 | DB21: 99 | DC21: 100 | DD21: 101 | DE21: 102 | DF21: 103 | DG21: 104 | DH21: 105 | DI21: 106 | DJ21: 107 | DK21: 108 | DL21: 109 | DM21: 110 | DN21: 111 | DO21: 112 | DP21: 113 | DQ21: 114 | DR21: 115 | DS21: 116 | DT21: 117 | DU21: 118 | DV21: 119 | DW21: 120 | DX21: 121 | DY21: 122 | DZ21: 123 | EA21: 124 | EB21: 125 | EC21: 126 | ED21: 127 | EE21: 128 | EF21: 129 | EG21: 130 | EH21: 131 | EI21: 132 | EJ21: 133 | EK21: 134 | EL21: 135 | EM21: 136 | EN21: 137 | EO21: 138 | EP21: 139 | EQ21: 140 | ER21: 141 | ES21: 142 | ET21: 143 | EU21: 144 | EV21: 145 | EW21: 146 | EX21: 147 | EY21: 148 | EZ21: 149 | FA21: 150 | FB21: 151 | FC21: 152 | FD21: 153 | FE21: 154 | FF21: 155 | FG21: 156 | FH21: 157 | FI21: 158 | FJ21: 159 | FK21: 160 | FL21: 161 | FM21: 162 | FN21: 163 | FO21: 164 | FP21: 165 | FQ21: 166 | FR21: 167 | FS21: 168 | FT21: 169 | FU21: 170 | FV21: 171 | FW21: 172 | FX21: 173 | FY21: 174 | FZ21: 175 | GA21: 176 | GB21: 177 | GC21: 178 | GD21: 179 | GE21: 180 | GF21: 181 | GG21: 182 | GH21: 183 | GI21: 184 | GJ21: 185 | GK21: 186 | GL21: 187 | GM21: 188 | GN21: 189 | GO21: 190 | GP21: 191 | GQ21: 192 | GR21: 193 | GS21: 194 | GT21: 195 | GU21: 196 | GV21: 197 | GW21: 198 | GX21: 199 | GY21: 200 | GZ21: 201 | HA21: 202 | HB21: 203 | HC21: 204 | HD21: 205 | HE21: 206 | HF21: 207 | HG21: 208 | HH21: 209 | HI21: 210 | HJ21: 211 | HK21: 212 | HL21: 213 | HM21: 214 | HN21: 215 | HO21: 216 | HP21: 217 | HQ21: 218 | HR21: 219 | HS21: 220 | HT21: 221 | HU21: 222 | HV21: 223 | HW21: 224 | HX21: 225 | HY21: 226 | HZ21: 227 | IA21: 228 | IB21: 229 | IC21: 230 | ID21: 231 | IE21: 232 | IF21: 233 | IG21: 234 | IH21: 235 | II21: 236 | IJ21: 237 | IK21: 238 | IL21: 239 | IM21: 240 | IN21: 241 | IO21: 242 | IP21: 243 | IQ21: 244 | IR21: 245 | IS21: 246 | IT21: 247 | IU21: 248 | IV21: 249 | IW21: 250 | IX21: 251 | IY21: 252 | IZ21: 253 | JA21: 254 | JB21: 255 | JC21: 256 | JD21: 257 | JE21: 258 | JF21: 259 | JG21: 260 | JH21: 261 | JI21: 262 | JJ21: 263 | JK21: 264 | JL21: 265 | JM21: 266 | JN21: 267 | JO21: 268 | JP21: 269 | JQ21: 270 | JR21: 271 | JS21: 272 | JT21: 273 | JU21: 274 | JV21: 275 | JW21: 276 | JX21: 277 | JY21: 278 | JZ21: 279 | KA21: 280 | KB21: 281 | KC21: 282 | KD21: 283 | KE21: 284 | KF21: 285 | KG21: 286 | KH21: 287 | KI21: 288 | KJ21: 289 | KK21: 290 | KL21: 291 | KM21: 292 | KN21: 293 | KO21: 294 | KP21: 295 | KQ21: 296 | KR21: 297 | KS21: 298 | KT21: 299 | KU21: 300 | KV21: 301 | KW21: 302 | KX21: 303 | KY21: 304 | KZ21: 305 | LA21: 306 | LB21: 307 | LC21: 308 | LD21: 309 | LE21: 310 | LF21: 311 | LG21: 312 | LH21: 313 | LI21: 314 | LJ21: 315 | LK21: 316 | LL21: 317 | LM21: 318 | LN21: 319 | LO21: 320 | LP21: 321 | LQ21: 322 | LR21: 323 | LS21: 324 | LT21: 325 | LU21: 326 | LV21: 327 | LW21: 328 | LX21: 329 | LY21: 330 | LZ21: 331 | MA21: 332 | MB21: 333 | MC21: 334 | MD21: 335 | ME21: 336 | MF21: 337 | MG21: 338 | MH21: 339 | MI21: 340 | MJ21: 341 | MK21: 342 | ML21: 343 | MM21: 344 | MN21: 345 | MO21: 346 | MP21: 347 | MQ21: 348 | MR21: 349 | MS21: 350 | MT21: 351 | MU21: 352 | MV21: 353 | MW21: 354 | MX21: 355 | MY21: 356 | MZ21: 357 | NA21: 358 | NB21: 359 | NC21: 360 | ND21: 361 | NE21: 362 | NF21: 363 | NG21: 364 | NH21: 365 | NI21: 366 | NJ21: 367 | NK21: 368 | NL21: 369 | NM21: 370 | NN21: 371 | NO21: 372 | NP21: 373 | NQ21: 374 | NR21: 375 | NS21: 376 | NT21: 377 | NU21: 378 | NV21: 379 | NW21: 380 | NX21: 381 | NY21: 382 | NZ21: 383 | OA21: 384 | OB21: 385 | OC21: 386 | OD21: 387 | OE21: 388 | OF21: 389 | OG21: 390
F22: Year | G22: =YEAR(G23) -> 2027 | H22: =YEAR(H23) -> 2027 | I22: =YEAR(I23) -> 2027 | J22: =YEAR(J23) -> 2027 | K22: =YEAR(K23) -> 2027 | L22: =YEAR(L23) -> 2027 | M22: =YEAR(M23) -> 2027 | N22: =YEAR(N23) -> 2027 | ... OG22: =YEAR(OG23) -> 2059
F23: Month | G23: =EOMONTH(C9,-1)+1 -> 46388 | H23: =EDATE(G23,1) -> 46419 | I23: =EDATE(H23,1) -> 46447 | J23: =EDATE(I23,1) -> 46478 | K23: =EDATE(J23,1) -> 46508 | L23: =EDATE(K23,1) -> 46539 | M23: =EDATE(L23,1) -> 46569 | N23: =EDATE(M23,1) -> 46600 | O23: =EDATE(N23,1) -> 46631 | ... OG23: =EDATE(OF23,1) -> 58257
B25: Principal | H25: =PPMT($C$14/12,H21,$C$10*12,-$C$8) -> 56696.33 | I25: =PPMT($C$14/12,I21,$C$10*12,-$C$8) -> 56932.565 | J25: =PPMT($C$14/12,J21,$C$10*12,-$C$8) -> 57169.784 | K25: =PPMT($C$14/12,K21,$C$10*12,-$C$8) -> 57407.991 | L25: =PPMT($C$14/12,L21,$C$10*12,-$C$8) -> 57647.191 | M25: =PPMT($C$14/12,M21,$C$10*12,-$C$8) -> 57887.388 | N25: =PPMT($C$14/12,N21,$C$10*12,-$C$8) -> 58128.585 | O25: =PPMT($C$14/12,O21,$C$10*12,-$C$8) -> 58370.788 | ... NC25: =PPMT($C$14/12,NC21,$C$10*12,-$C$8) -> 252253.65
B26: Interest | H26: =$C$8*($C$14/12) -> 196608.38 | I26: =H32*($C$14/12) -> 196372.14 | J26: =I32*($C$14/12) -> 196134.92 | K26: =J32*($C$14/12) -> 195896.72 | L26: =K32*($C$14/12) -> 195657.52 | M26: =L32*($C$14/12) -> 195417.32 | N26: =M32*($C$14/12) -> 195176.12 | O26: =N32*($C$14/12) -> 194933.92 | P26: =O32*($C$14/12) -> 194690.71 | ... NC26: =NB32*($C$14/12) -> 1051.0569
B27: Total Mortgage Payment | H27: =H26+H25 -> 253304.71 | I27: =I26+I25 -> 253304.71 | J27: =J26+J25 -> 253304.71 | K27: =K26+K25 -> 253304.71 | L27: =L26+L25 -> 253304.71 | M27: =M26+M25 -> 253304.71 | N27: =N26+N25 -> 253304.71 | O27: =O26+O25 -> 253304.71 | ... NC27: =NC26+NC25 -> 253304.71
B28: HFA Servicing Fee | H28: =IF(MONTH(H23)=2,ROUND($C$8*$C$16*YEARFRAC(H23,G23),2),G28) -> 9830.42 | I28: =IF(MONTH(I23)=2,ROUND(H32*$C$16*YEARFRAC(I23,H23),2),H28) -> 9830.42 | J28: =IF(MONTH(J23)=2,ROUND(I32*$C$16*YEARFRAC(J23,I23),2),I28) -> 9830.42 | K28: =IF(MONTH(K23)=2,ROUND(J32*$C$16*YEARFRAC(K23,J23),2),J28) -> 9830.42 | L28: =IF(MONTH(L23)=2,ROUND(K32*$C$16*YEARFRAC(L23,K23),2),K28) -> 9830.42 | M28: =IF(MONTH(M23)=2,ROUND(L32*$C$16*YEARFRAC(M23,L23),2),L28) -> 9830.42 | N28: =IF(MONTH(N23)=2,ROUND(M32*$C$16*YEARFRAC(N23,M23),2),M28) -> 9830.42 | O28: =IF(MONTH(O23)=2,ROUND(N32*$C$16*YEARFRAC(O23,N23),2),N28) -> 9830.42 | P28: =IF(MONTH(P23)=2,ROUND(O32*$C$16*YEARFRAC(P23,O23),2),O28) -> 9830.42 | ... NC28: =IF(MONTH(NC23)=2,ROUND(NB32*$C$16*YEARFRAC(NC23,NB23),2),NB28) -> 616.44
B29: SONYMA Servicing Fee | H29: =IF(MONTH(H23)=2,ROUND($C$8*$C$15*YEARFRAC(H23,G23),2),G29) -> 19660.84 | I29: =IF(MONTH(I23)=2,ROUND(H32*$C$15*YEARFRAC(I23,H23),2),H29) -> 19660.84 | J29: =IF(MONTH(J23)=2,ROUND(I32*$C$15*YEARFRAC(J23,I23),2),I29) -> 19660.84 | K29: =IF(MONTH(K23)=2,ROUND(J32*$C$15*YEARFRAC(K23,J23),2),J29) -> 19660.84 | L29: =IF(MONTH(L23)=2,ROUND(K32*$C$15*YEARFRAC(L23,K23),2),K29) -> 19660.84 | M29: =IF(MONTH(M23)=2,ROUND(L32*$C$15*YEARFRAC(M23,L23),2),L29) -> 19660.84 | N29: =IF(MONTH(N23)=2,ROUND(M32*$C$15*YEARFRAC(N23,M23),2),M29) -> 19660.84 | O29: =IF(MONTH(O23)=2,ROUND(N32*$C$15*YEARFRAC(O23,N23),2),N29) -> 19660.84 | P29: =IF(MONTH(P23)=2,ROUND(O32*$C$15*YEARFRAC(P23,O23),2),O29) -> 19660.84 | ... NC29: =IF(MONTH(NC23)=2,ROUND(NB32*$C$15*YEARFRAC(NC23,NB23),2),NB29) -> 1232.88
B30: SONYMA Upfront Fee | H30: =IF(H21=1,$C$8*$C$15,0) -> 235930.05 | I30: =IF(I21=1,$C$8*$C$15,0) -> 0 | J30: =IF(J21=1,$C$8*$C$15,0) -> 0 | K30: =IF(K21=1,$C$8*$C$15,0) -> 0 | L30: =IF(L21=1,$C$8*$C$15,0) -> 0 | M30: =IF(M21=1,$C$8*$C$15,0) -> 0 | N30: =IF(N21=1,$C$8*$C$15,0) -> 0 | O30: =IF(O21=1,$C$8*$C$15,0) -> 0 | ... NC30: =IF(NC21=1,$C$8*$C$15,0) -> 0
B31: Total Debt Service Payment | H31: =SUM(H27:H29) -> 282795.97 | I31: =SUM(I27:I29) -> 282795.97 | J31: =SUM(J27:J29) -> 282795.97 | K31: =SUM(K27:K29) -> 282795.97 | L31: =SUM(L27:L29) -> 282795.97 | M31: =SUM(M27:M29) -> 282795.97 | N31: =SUM(N27:N29) -> 282795.97 | O31: =SUM(O27:O29) -> 282795.97 | ... NC31: =SUM(NC27:NC29) -> 255154.03
B32: Mortgage Balance | H32: =C8-H25 -> 47129314 | I32: =H32-I25 -> 47072381 | J32: =I32-J25 -> 47015212 | K32: =J32-K25 -> 46957804 | L32: =K32-L25 -> 46900157 | M32: =L32-M25 -> 46842269 | N32: =M32-N25 -> 46784141 | O32: =N32-O25 -> 46725770 | P32: =O32-P25 -> 46667156 | ... NC32: =NB32-NC25 -> 4.8312359e-09

Sheet KPI's
B2: KPI's
B4: KPIs | D4: ='Rental CF'!F7 -> 47330 | E4: ='Rental CF'!G7 -> 47695 | F4: ='Rental CF'!H7 -> 48060 | G4: ='Rental CF'!I7 -> 48426 | H4: ='Rental CF'!J7 -> 48791 | I4: ='Rental CF'!K7 -> 49156 | J4: ='Rental CF'!L7 -> 49521 | K4: ='Rental CF'!M7 -> 49887 | ... AG4: ='Rental CF'!AI7 -> 57922
B6: Value of Property | D6: ='Rental CF'!F55 -> 58597050 | E6: ='Rental CF'!G55 -> 59291720 | F6: ='Rental CF'!H55 -> 59985966 | G6: ='Rental CF'!I55 -> 60679348 | H6: ='Rental CF'!J55 -> 61371408 | I6: ='Rental CF'!K55 -> 62061664 | J6: ='Rental CF'!L55 -> 62749609 | K6: ='Rental CF'!M55 -> 63434714 | ... AG6: ='Rental CF'!AI55 -> 76343138
B7: Potential Gross Income | D7: ='Rental CF'!F15 -> 7836489.3 | E7: ='Rental CF'!G15 -> 7993219 | F7: ='Rental CF'!H15 -> 8153083.4 | G7: ='Rental CF'!I15 -> 8316145.1 | H7: ='Rental CF'!J15 -> 8482468 | I7: ='Rental CF'!K15 -> 8652117.4 | J7: ='Rental CF'!L15 -> 8825159.7 | K7: ='Rental CF'!M15 -> 9001662.9 | ... AG7: ='Rental CF'!AI15 -> 13916388
B8: Effective Gross Rental Income | D8: ='Rental CF'!F29 -> 7442690.8 | E8: ='Rental CF'!G29 -> 7591544.6 | F8: ='Rental CF'!H29 -> 7743375.5 | G8: ='Rental CF'!I29 -> 7898243 | H8: ='Rental CF'!J29 -> 8056207.9 | I8: ='Rental CF'!K29 -> 8217332 | J8: ='Rental CF'!L29 -> 8381678.7 | K8: ='Rental CF'!M29 -> 8549312.2 | ... AG8: ='Rental CF'!AI29 -> 13217063
B9: Gross Rent Multiplier | D9: =D6/D8 -> 7.8731002 | E9: =E6/E8 -> 7.8102314 | F9: =F6/F8 -> 7.7467463 | G9: =G6/G8 -> 7.6826388 | H9: =H6/H8 -> 7.6179028 | I9: =I6/I8 -> 7.5525321 | J9: =J6/J8 -> 7.4865205 | K9: =K6/K8 -> 7.4198617 | ... AG9: =AG6/AG8 -> 5.7761046
B10: SONYMA Income to Expense Ratio | D10: ='Rental CF'!F50 -> 1.1782948 | E10: ='Rental CF'!G50 -> 1.1830881 | F10: ='Rental CF'!H50 -> 1.1876427 | G10: ='Rental CF'!I50 -> 1.1919566 | H10: ='Rental CF'!J50 -> 1.1960275 | I10: ='Rental CF'!K50 -> 1.1998538 | J10: ='Rental CF'!L50 -> 1.2034339 | K10: ='Rental CF'!M50 -> 1.2067667 | ... AG10: ='Rental CF'!AI50 -> 1.2183153
B11: NOI | D11: ='Rental CF'!F36 -> 4101793.5 | E11: ='Rental CF'!G36 -> 4150420.4 | F11: ='Rental CF'!H36 -> 4199017.6 | G11: ='Rental CF'!I36 -> 4247554.4 | H11: ='Rental CF'!J36 -> 4295998.6 | I11: ='Rental CF'!K36 -> 4344316.4 | J11: ='Rental CF'!L36 -> 4392472.6 | K11: ='Rental CF'!M36 -> 4440430 | ... AG11: ='Rental CF'!AI36 -> 5344019.7
B12: Debt Services | D12: =-'Rental CF'!F46 -> 2975595.6 | E12: =-'Rental CF'!G46 -> 2975595.6 | F12: =-'Rental CF'!H46 -> 2975595.6 | G12: =-'Rental CF'!I46 -> 2975595.6 | H12: =-'Rental CF'!J46 -> 2975595.6 | I12: =-'Rental CF'!K46 -> 2975595.6 | J12: =-'Rental CF'!L46 -> 2975595.6 | K12: =-'Rental CF'!M46 -> 2975595.6 | ... AG12: =-'Rental CF'!AI46 -> 2975595.6
B13: Debt Coverage Ratio | D13: ='Rental CF'!F51 -> 1.3784782 | E13: ='Rental CF'!G51 -> 1.3948201 | F13: ='Rental CF'!H51 -> 1.411152 | G13: ='Rental CF'!I51 -> 1.4274636 | H13: ='Rental CF'!J51 -> 1.4437441 | I13: ='Rental CF'!K51 -> 1.4599821 | J13: ='Rental CF'!L51 -> 1.4761659 | K13: ='Rental CF'!M51 -> 1.4922828 | ... AG13: ='Rental CF'!AI51 -> 1.7959496
B14: Net Cash Flow | D14: ='Rental CF'!F48 -> 1126197.9 | E14: ='Rental CF'!G48 -> 1174824.8 | F14: ='Rental CF'!H48 -> 1223422 | G14: ='Rental CF'!I48 -> 1271958.8 | H14: ='Rental CF'!J48 -> 1320403 | I14: ='Rental CF'!K48 -> 1368720.9 | J14: ='Rental CF'!L48 -> 1416877 | K14: ='Rental CF'!M48 -> 1464834.4 | ... AG14: ='Rental CF'!AI48 -> 2368424.1

Sheet tSET
E3: Dev | F3: =-Budget!I62 -> 2.7978234e+08 | H3: 0.9 | J3: =H3*F3 -> 2.518041e+08 | P3: Acquisition Costs | R3: Acquisition Costs
E4: Non Debt | P4: Building Acquisition | R4: Building Acquisition
F5: ='Sources and Uses'!C8 -> 10635591 | P5: Land Acquisition | R5: Land Acquisition
P6: Total Acquisition Costs | R6: Total Acquisition Costs
F7: =F3-F5 -> 2.6914675e+08
P8: Hard Cost & Soft Cost | R8: Hard Cost & Soft Cost
F9: 0.9 | P9: Contractor Price | R9: Contractor Price
P10: Residential | R10: Residential
F11: =F9*F7 -> 2.4223207e+08 | P11: Commercial Space | R11: Commercial Space
P12: Community Space | R12: Community Space
F13: ='Sources and Uses'!C5 -> 47186010 | P13: Parking | R13: Parking
F14: ='Sources and Uses'!C7 -> 47232000 | P14: Developer Fee | R14: Developer Fee
F15: =SUM(F13:F14) -> 94418010 | P15: Contingent Hard Costs | R15: Contingent Hard Costs
P16: General Conditions | R16: General Conditions
P17: Overhead | R17: Overhead
P18: Contractor Profit | R18: Contractor Profit
P19: Bond Premium | R19: Bond Premium
P20: Contingency | R20: Contingency
P22: Accounting & Cost Certification | R22: Accounting & Cost Certification
P23: Appraisal | R23: Appraisal
P24: Architect / Engineer | R24: Architect / Engineer
P25: Permits and Expediting | R25: Permits and Expediting
P26: Environmental Phase I & II | R26: Environmental Phase I & II
P27: Geotechnical | R27: Geotechnical
P28: Insurance | R28: Insurance
... P54: Total Development Cost | R54: Total Development Cost

Sheet References
B2: Area | C2: Reference
B3: Units Size | C3: HPD New Construction Finance Term Sheet
B4: Units Rent | C4: Area Median Income - HPD
B5: LIHTC eligible cost | C5: LIHTC Eligible Basis: Definition, Costs, and Calculations - LegalClarity
B6: Average Price (psf) Residential | C6: Housing Inventory: Median Listing Price per Square Feet in New York-Newark-Jersey City, NY-NJ-PA (CBSA) (MEDLISPRIPERSQUFEE35620) | FRED | St. Louis Fed
B7: Average Price (psf) Non-Residential | C7: https://www.propertyshark.com/mason/market-trends/commercial/nyc/manhattan
B8: AFR (April 26) | C8: Determination of Issue Price in the Case of Certain Debt Instruments Issued for Property
B9: Interest Rate (Long term) | C9: New York City Housing Development Corporation
B17: NYC Cap Rate | C17: NYC Cap Rates Explained: A Guide for Property Owners | NYC Property Value
P20: Yes | Q20: 0.025
B21: Developer Fee Calculator (enter total units in B16) | P21: No | Q21: 0.05
B22: Input – Total Units (excl. super unit if applicable) | C22: ='Unit Mix'!C19 -> 328 | Q22: 0.075
B23: Tier 1 Fee (units 1–100) | C23: =MIN(C22,100)*50000 -> 5000000 | Q23: 0.1
B24: Tier 2 Fee (units 101–250) | C24: =MAX(0,MIN(C22,250)-100)*20000 -> 3000000 | Q24: 0.125
B25: Tier 3 Fee (units 251+) | C25: =MAX(0,C22-250)*10000 -> 780000 | Q25: 0.15
B26: TOTAL PAID DEVELOPER FEE | C26: =C23+C24+C25 -> 8780000 | Q26: 0.175
Q27: 0.2
B28: Amount Raised per Credit | C28: https://www.bing.com/ck/a?!&&p=15c793bea8b209e83ff74b8ddb2a1fa42a0ffd2e2a1a822affad60ff49c850bcJmltdHM9MTc3NzE2MTYwMA&ptn=3&ver=2&hsh=4&fclid=06048e13-886b-6fd4-387b-98a289ea6e3c&u=a1aHR0cHM6Ly93d3cuY29obnJlem5pY2suY29tLy0vbWVkaWEvcmVzb3VyY2VzL3RjYS1ob3VzaW5nLXRheC1jcmVkaXQtbW9uaXRvcl9tYXJjaC0yMDI2LnBkZg&ntb=1
N31: Ballon paymenat short term
N32: total amt | O32: =Mortgage!D54 -> 1.3508715e+08
N33: paid

Sheet Market Research
B2: Development Cost Structure | E2: https://ipedconference.com/powerpoints/0200PM_03.21.2024_THURS_Numbers-Panel_Sample%204_%20LIHTC%20Model.pdf
B3: Category | C3: Sub-Category | D3: Line Item
B4: Acquisition Costs | D4: Building Acquisition
D5: Land Acquisition
D6: Total Acquisition Costs
B7: Hard Costs | D7: Site work - Off Site
D8: Site work - On site direct
D9: Furniture, fixtures
D10: Solar
C11: Rehab | D11: Demolition/Masonry
D12: Environmental
D13: Roofing
D14: Windows
D15: Electrical/HVAC
D16: Plumbing
D17: Drywall
D18: Structural
D19: Carpentry
D20: Flooring
D21: Cabinets
D22: Permits
D23: Painting
... D29: Total Hard Costs
B30: Soft Costs | D30: Impact Fees
D31: Eligible Fees (H.A. Financing, etc.)
D32: Non-Eligible Fees/Costs (Org., Synd., T.C. Fees, etc.)
D33: Relocation costs and Lease-up Reserves
D34: Loan Issuance Costs
D35: Interest
D36: Developer Fee
D37: Total Soft Costs
B38: Reserves | D38: Reserves
B39: TOTAL | D39: TOTAL DEVELOPMENT COSTS

Sheet Sheet1
D4: 1 | E4: 2 | F4: 3 | G4: 4 | H4: 5 | I4: 6 | J4: 7 | K4: 8 | L4: 9 | M4: 10 | N4: 11 | O4: 12 | P4: 13 | Q4: 14 | R4: 15 | S4: 16 | T4: 17 | U4: 18 | V4: 19 | W4: 20 | X4: 21 | Y4: 22 | Z4: 23 | AA4: 24 | AB4: 25 | AC4: 26 | AD4: 27 | AE4: 28 | AF4: 29 | AG4: 30
D5: 2027 | E5: 2027 | F5: 2027 | G5: 2027 | H5: 2027 | I5: 2027 | J5: 2027 | K5: 2027 | L5: 2027 | M5: 2027 | N5: 2027 | O5: 2027 | P5: 2028 | Q5: 2028 | R5: 2028 | S5: 2028 | T5: 2028 | U5: 2028 | V5: 2028 | W5: 2028 | X5: 2028 | Y5: 2028 | Z5: 2028 | AA5: 2028 | AB5: 2029 | AC5: 2029 | AD5: 2029 | AE5: 2029 | AF5: 2029 | AG5: 2029
D6: 46418 | E6: 46446 | F6: 46477 | G6: 46507 | H6: 46538 | I6: 46568 | J6: 46599 | K6: 46630 | L6: 46660 | M6: 46691 | N6: 46721 | O6: 46752 | P6: 46783 | Q6: 46812 | R6: 46843 | S6: 46873 | T6: 46904 | U6: 46934 | V6: 46965 | W6: 46996 | X6: 47026 | Y6: 47057 | Z6: 47087 | AA6: 47118 | AB6: 47149 | AC6: 47177 | AD6: 47208 | AE6: 47238 | AF6: 47269 | AG6: 47299
B8: out flow
B9: TDC | D9: =Budget!J62 -> -3315316.6 | E9: =Budget!K62 -> -3315315.6 | F9: =Budget!L62 -> -3315315.6 | G9: =Budget!M62 -> -3315315.6 | H9: =Budget!N62 -> -3315315.6 | I9: =Budget!O62 -> -3315315.6 | J9: =Budget!P62 -> -10316955 | K9: =Budget!Q62 -> -10316955 | ... AG9: =Budget!AM62 -> -10316955
B15: inflow
B16: developer fee
B17: lihtc equity
B18: loan draw
